Workbook

Sheet Сводка
A1: Советник: справедливые цены и сигналы
A2: ="Котировки на "&TEXT(Параметры!$B$5,"DD.MM.YYYY")&" · текущие цены — столбец D (жёлтый) · правила зон — на листе «Параметры»" -> Котировки на 24.10.2026 · текущие цены — столбец D (жёлтый) · правила зон — на листе «Параметры»
A4: Тикер | B4: Компания | C4: Метод | D4: Текущая цена, ₽ | E4: Справедливая, ₽ | F4: Зона покупки ≤, ₽ | G4: Приближается ≥, ₽ | H4: Цена продажи, ₽ | I4: До справедливой | J4: До продажи | K4: Статус | L4: Позиция, шт | M4: Стоимость, ₽ | N4: Доля | O4: Справедливая без мира, ₽ | P4: Прибавка от мира, ₽
A5: SBER | B5: Сбербанк | C5: Дивиденды (Гордон) | D5: 292.32 | E5: =SBER!$B$39 -> 547.65241 | F5: =SBER!$B$41 -> 421.69236 | G5: =SBER!$B$43 -> 613.91835 | H5: =SBER!$B$42 -> 646.22984 | I5: =IF(D5>0,E5/D5-1,0) -> 0.87346884 | J5: =IF(D5>0,H5/D5-1,0) -> 1.2106932 | K5: =IF(D5<=F5,"ЗОНА ПОКУПКИ",IF(D5>=H5,"ЦЕНА ПРОДАЖИ",IF(D5>=G5,"ПРИБЛИЖАЕТСЯ К ПРОДАЖЕ","ДЕРЖАТЬ"))) -> ЗОНА ПОКУПКИ | L5: =SUMIF(Портфели!$B:$B,A5,Портфели!$D:$D) -> 192 | M5: =L5*D5 -> 56125.44 | N5: =IF(Портфели!$G$18>0,M5/Портфели!$G$18,0) -> 0.2036149 | O5: =SBER!$B$33 -> 508.99281 | P5: =E5-O5 -> 38.659598
A6: PLZL | B6: Полюс | C6: EV/EBITDA от золота | D6: 1098.2 | E6: =PLZL!$B$38 -> 1610.6026 | F6: =PLZL!$B$40 -> 1240.164 | G6: =PLZL!$B$42 -> 1805.4856 | H6: =PLZL!$B$41 -> 1900.5111 | I6: =IF(D6>0,E6/D6-1,0) -> 0.46658408 | J6: =IF(D6>0,H6/D6-1,0) -> 0.73056922 | K6: =IF(D6<=F6,"ЗОНА ПОКУПКИ",IF(D6>=H6,"ЦЕНА ПРОДАЖИ",IF(D6>=G6,"ПРИБЛИЖАЕТСЯ К ПРОДАЖЕ","ДЕРЖАТЬ"))) -> ЗОНА ПОКУПКИ | L6: =SUMIF(Портфели!$B:$B,A6,Портфели!$D:$D) -> 41 | M6: =L6*D6 -> 45026.2 | N6: =IF(Портфели!$G$18>0,M6/Портфели!$G$18,0) -> 0.16334848 | O6: =PLZL!$B$32 -> 1288.8231 | P6: =E6-O6 -> 321.77956
A7: POSI | B7: Группа Позитив | C7: P/E на NIC 2027П | D7: 1176.8 | E7: =POSI!$B$30 -> 1672.9057 | F7: =POSI!$B$32 -> 1288.1374 | G7: =POSI!$B$34 -> 1875.3273 | H7: =POSI!$B$33 -> 1974.0287 | I7: =IF(D7>0,E7/D7-1,0) -> 0.4215718 | J7: =IF(D7>0,H7/D7-1,0) -> 0.67745472 | K7: =IF(D7<=F7,"ЗОНА ПОКУПКИ",IF(D7>=H7,"ЦЕНА ПРОДАЖИ",IF(D7>=G7,"ПРИБЛИЖАЕТСЯ К ПРОДАЖЕ","ДЕРЖАТЬ"))) -> ЗОНА ПОКУПКИ | L7: =SUMIF(Портфели!$B:$B,A7,Портфели!$D:$D) -> 32 | M7: =L7*D7 -> 37657.6 | N7: =IF(Портфели!$G$18>0,M7/Портфели!$G$18,0) -> 0.13661628 | O7: =POSI!$B$24 -> 1381.7508 | P7: =E7-O7 -> 291.15491
A8: PRMD | B8: Промомед | C8: EV/EBITDA 2027П | D8: 407 | E8: =PRMD!$B$32 -> 713.59824 | F8: =PRMD!$B$34 -> 549.47065 | G8: =PRMD!$B$36 -> 799.94363 | H8: =PRMD!$B$35 -> 842.04593 | I8: =IF(D8>0,E8/D8-1,0) -> 0.75331264 | J8: =IF(D8>0,H8/D8-1,0) -> 1.0689089 | K8: =IF(D8<=F8,"ЗОНА ПОКУПКИ",IF(D8>=H8,"ЦЕНА ПРОДАЖИ",IF(D8>=G8,"ПРИБЛИЖАЕТСЯ К ПРОДАЖЕ","ДЕРЖАТЬ"))) -> ЗОНА ПОКУПКИ | L8: =SUMIF(Портфели!$B:$B,A8,Портфели!$D:$D) -> 79 | M8: =L8*D8 -> 32153 | N8: =IF(Портфели!$G$18>0,M8/Портфели!$G$18,0) -> 0.11664639 | O8: =PRMD!$B$26 -> 584.65882 | P8: =E8-O8 -> 128.93942
A9: YDEX | B9: Яндекс | C9: EV/EBITDA 2027П | D9: 3400 | E9: =YDEX!$B$43 -> 12985.469 | F9: =YDEX!$B$45 -> 9998.8112 | G9: =YDEX!$B$47 -> 14556.711 | H9: =YDEX!$B$46 -> 15322.853 | I9: =IF(D9>0,E9/D9-1,0) -> 2.8192556 | J9: =IF(D9>0,H9/D9-1,0) -> 3.5067216 | K9: =IF(D9<=F9,"ЗОНА ПОКУПКИ",IF(D9>=H9,"ЦЕНА ПРОДАЖИ",IF(D9>=G9,"ПРИБЛИЖАЕТСЯ К ПРОДАЖЕ","ДЕРЖАТЬ"))) -> ЗОНА ПОКУПКИ | L9: =SUMIF(Портфели!$B:$B,A9,Портфели!$D:$D) -> 9 | M9: =L9*D9 -> 30600 | N9: =IF(Портфели!$G$18>0,M9/Портфели!$G$18,0) -> 0.11101233 | O9: =YDEX!$B$37 -> 11063.275 | P9: =E9-O9 -> 1922.1941
A10: MTSS | B10: МТС | C10: Выплаты акционерам (Гордон) | D10: 176.45 | E10: =MTSS!$B$42 -> 430.37534 | F10: =MTSS!$B$44 -> 331.38901 | G10: =MTSS!$B$46 -> 482.45076 | H10: =MTSS!$B$45 -> 507.8429 | I10: =IF(D10>0,E10/D10-1,0) -> 1.4390782 | J10: =IF(D10>0,H10/D10-1,0) -> 1.8781122 | K10: =IF(D10<=F10,"ЗОНА ПОКУПКИ",IF(D10>=H10,"ЦЕНА ПРОДАЖИ",IF(D10>=G10,"ПРИБЛИЖАЕТСЯ К ПРОДАЖЕ","ДЕРЖАТЬ"))) -> ЗОНА ПОКУПКИ | L10: =SUMIF(Портфели!$B:$B,A10,Портфели!$D:$D) -> 150 | M10: =L10*D10 -> 26467.5 | N10: =IF(Портфели!$G$18>0,M10/Портфели!$G$18,0) -> 0.096020226 | O10: =MTSS!$B$36 -> 370.74046 | P10: =E10-O10 -> 59.634876
A11: GAZP | B11: Газпром | C11: EV/EBITDA + опционы | D11: 114.75 | E11: =GAZP!$B$63 -> 144.70446 | F11: =GAZP!$B$65 -> 111.42244 | G11: =GAZP!$B$67 -> 162.2137 | H11: =GAZP!$B$66 -> 170.75127 | I11: =IF(D11>0,E11/D11-1,0) -> 0.26104108 | J11: =IF(D11>0,H11/D11-1,0) -> 0.48802847 | K11: =IF(D11<=F11,"ЗОНА ПОКУПКИ",IF(D11>=H11,"ЦЕНА ПРОДАЖИ",IF(D11>=G11,"ПРИБЛИЖАЕТСЯ К ПРОДАЖЕ","ДЕРЖАТЬ"))) -> ДЕРЖАТЬ | L11: =SUMIF(Портфели!$B:$B,A11,Портфели!$D:$D) -> 210 | M11: =L11*D11 -> 24097.5 | N11: =IF(Портфели!$G$18>0,M11/Портфели!$G$18,0) -> 0.087422212 | O11: =GAZP!$B$56 -> 114.95422 | P11: =E11-O11 -> 29.750245
A12: NLMK | B12: НЛМК | C12: EV/EBITDA цикла | D12: 76.44 | E12: =NLMK!$B$33 -> 106.97302 | F12: =NLMK!$B$35 -> 82.369229 | G12: =NLMK!$B$37 -> 119.91676 | H12: =NLMK!$B$36 -> 126.22817 | I12: =IF(D12>0,E12/D12-1,0) -> 0.39943779 | J12: =IF(D12>0,H12/D12-1,0) -> 0.65133659 | K12: =IF(D12<=F12,"ЗОНА ПОКУПКИ",IF(D12>=H12,"ЦЕНА ПРОДАЖИ",IF(D12>=G12,"ПРИБЛИЖАЕТСЯ К ПРОДАЖЕ","ДЕРЖАТЬ"))) -> ЗОНА ПОКУПКИ | L12: =SUMIF(Портфели!$B:$B,A12,Портфели!$D:$D) -> 270 | M12: =L12*D12 -> 20638.8 | N12: =IF(Портфели!$G$18>0,M12/Портфели!$G$18,0) -> 0.074874553 | O12: =NLMK!$B$27 -> 92.138149 | P12: =E12-O12 -> 14.834876
A13: BSPB | B13: Банк Санкт-Петербург | C13: Дивиденды (Гордон) | D13: 257.06 | E13: =BSPB!$B$30 -> 258.09106 | F13: =BSPB!$B$32 -> 198.73012 | G13: =BSPB!$B$34 -> 289.32008 | H13: =BSPB!$B$33 -> 304.54745 | I13: =IF(D13>0,E13/D13-1,0) -> 0.0040109644 | J13: =IF(D13>0,H13/D13-1,0) -> 0.18473294 | K13: =IF(D13<=F13,"ЗОНА ПОКУПКИ",IF(D13>=H13,"ЦЕНА ПРОДАЖИ",IF(D13>=G13,"ПРИБЛИЖАЕТСЯ К ПРОДАЖЕ","ДЕРЖАТЬ"))) -> ДЕРЖАТЬ | L13: =SUMIF(Портфели!$B:$B,A13,Портфели!$D:$D) -> 0 | M13: =L13*D13 -> 0 | N13: =IF(Портфели!$G$18>0,M13/Портфели!$G$18,0) -> 0 | O13: =BSPB!$B$24 -> 240.55424 | P13: =E13-O13 -> 17.536822
A14: Итого акции | M14: =SUM(M5:M13) -> 272766.04 | N14: =SUM(N5:N13) -> 0.98955537
A15: Как читать: «ДЕРЖАТЬ» — цена между зоной покупки и сигналом «приближается»; «ЗОНА ПОКУПКИ» — бумага заметно дешевле справедливой; «ПРИБЛИЖАЕТСЯ К ПРОДАЖЕ» / «ЦЕНА ПРОДАЖИ» — повод открыть модель и проверить тезис.
A16: Справедливая цена считается на листе эмитента. Меняйте синие вводные там — сводка пересчитается сама.
A17: Это аналитическая модель для ваших решений, а не индивидуальная инвестиционная рекомендация. Сделки бот не совершает.

Sheet Портфели
A1: Портфели
A2: Количество и средняя цена — со скриншотов брокеров (синие, обновляйте при сделках). Текущая цена подтягивается со «Сводки».
A4: Счёт | B4: Тикер | C4: Компания | D4: Кол-во, шт | E4: Средняя цена, ₽ | F4: Текущая цена, ₽ | G4: Стоимость, ₽ | H4: Вложено, ₽ | I4: Результат, ₽ | J4: Результат | K4: Доля в общем
A5: ИИС | B5: SBER | C5: Сбербанк | D5: 192 | E5: 286.95 | F5: =IFERROR(INDEX(Сводка!$D$5:$D$13,MATCH(B5,Сводка!$A$5:$A$13,0)),0) -> 292.32 | G5: =D5*F5 -> 56125.44 | H5: =D5*E5 -> 55094.4 | I5: =G5-H5 -> 1031.04 | J5: =IF(H5>0,I5/H5,0) -> 0.018714062 | K5: =IF($G$18>0,G5/$G$18,0) -> 0.2036149
A6: ИИС | B6: POSI | C6: Группа Позитив | D6: 32 | E6: 982.9 | F6: =IFERROR(INDEX(Сводка!$D$5:$D$13,MATCH(B6,Сводка!$A$5:$A$13,0)),0) -> 1176.8 | G6: =D6*F6 -> 37657.6 | H6: =D6*E6 -> 31452.8 | I6: =G6-H6 -> 6204.8 | J6: =IF(H6>0,I6/H6,0) -> 0.19727337 | K6: =IF($G$18>0,G6/$G$18,0) -> 0.13661628
A7: ИИС | B7: PRMD | C7: Промомед | D7: 79 | E7: 387.48 | F7: =IFERROR(INDEX(Сводка!$D$5:$D$13,MATCH(B7,Сводка!$A$5:$A$13,0)),0) -> 407 | G7: =D7*F7 -> 32153 | H7: =D7*E7 -> 30610.92 | I7: =G7-H7 -> 1542.08 | J7: =IF(H7>0,I7/H7,0) -> 0.050376794 | K7: =IF($G$18>0,G7/$G$18,0) -> 0.11664639
A8: ИИС | B8: YDEX | C8: Яндекс | D8: 9 | E8: 4193.7 | F8: =IFERROR(INDEX(Сводка!$D$5:$D$13,MATCH(B8,Сводка!$A$5:$A$13,0)),0) -> 3400 | G8: =D8*F8 -> 30600 | H8: =D8*E8 -> 37743.3 | I8: =G8-H8 -> -7143.3 | J8: =IF(H8>0,I8/H8,0) -> -0.18926008 | K8: =IF($G$18>0,G8/$G$18,0) -> 0.11101233
A9: ИИС | B9: MTSS | C9: МТС | D9: 150 | E9: 195.35 | F9: =IFERROR(INDEX(Сводка!$D$5:$D$13,MATCH(B9,Сводка!$A$5:$A$13,0)),0) -> 176.45 | G9: =D9*F9 -> 26467.5 | H9: =D9*E9 -> 29302.5 | I9: =G9-H9 -> -2835 | J9: =IF(H9>0,I9/H9,0) -> -0.096749424 | K9: =IF($G$18>0,G9/$G$18,0) -> 0.096020226
A10: Счёт 2 | B10: PLZL | C10: Полюс | D10: 41 | E10: 1135 | F10: =IFERROR(INDEX(Сводка!$D$5:$D$13,MATCH(B10,Сводка!$A$5:$A$13,0)),0) -> 1098.2 | G10: =D10*F10 -> 45026.2 | H10: =D10*E10 -> 46535 | I10: =G10-H10 -> -1508.8 | J10: =IF(H10>0,I10/H10,0) -> -0.032422907 | K10: =IF($G$18>0,G10/$G$18,0) -> 0.16334848
A11: Счёт 2 | B11: GAZP | C11: Газпром | D11: 210 | E11: 100.05 | F11: =IFERROR(INDEX(Сводка!$D$5:$D$13,MATCH(B11,Сводка!$A$5:$A$13,0)),0) -> 114.75 | G11: =D11*F11 -> 24097.5 | H11: =D11*E11 -> 21010.5 | I11: =G11-H11 -> 3087 | J11: =IF(H11>0,I11/H11,0) -> 0.14692654 | K11: =IF($G$18>0,G11/$G$18,0) -> 0.087422212
A12: Счёт 2 | B12: NLMK | C12: НЛМК | D12: 270 | E12: 71.71 | F12: =IFERROR(INDEX(Сводка!$D$5:$D$13,MATCH(B12,Сводка!$A$5:$A$13,0)),0) -> 76.44 | G12: =D12*F12 -> 20638.8 | H12: =D12*E12 -> 19361.7 | I12: =G12-H12 -> 1277.1 | J12: =IF(H12>0,I12/H12,0) -> 0.065960117 | K12: =IF($G$18>0,G12/$G$18,0) -> 0.074874553
A13: ИИС | B13: RUB | C13: Рубли на счёте | G13: 1015 | H13: =G13 -> 1015 | I13: =G13-H13 -> 0 | K13: =IF($G$18>0,G13/$G$18,0) -> 0.0036822718
A14: Счёт 2 | B14: RUB | C14: Рубли на счёте | G14: 1864.01 | H14: =G14 -> 1864.01 | I14: =G14-H14 -> 0 | K14: =IF($G$18>0,G14/$G$18,0) -> 0.0067623562
A16: ИИС | G16: =SUMIF($A$5:$A$14,"ИИС",G$5:G$14) -> 184018.54 | H16: =SUMIF($A$5:$A$14,"ИИС",H$5:H$14) -> 185218.92 | I16: =SUMIF($A$5:$A$14,"ИИС",I$5:I$14) -> -1200.38 | J16: =IF(H16>0,I16/H16,0) -> -0.0064808714 | K16: =IF($G$18>0,G16/$G$18,0) -> 0.6675924
A17: Счёт 2 | G17: =SUMIF($A$5:$A$14,"Счёт 2",G$5:G$14) -> 91626.51 | H17: =SUMIF($A$5:$A$14,"Счёт 2",H$5:H$14) -> 88771.21 | I17: =SUMIF($A$5:$A$14,"Счёт 2",I$5:I$14) -> 2855.3 | J17: =IF(H17>0,I17/H17,0) -> 0.032164707 | K17: =IF($G$18>0,G17/$G$18,0) -> 0.3324076
A18: ИТОГО по всем счетам | G18: =SUM(G5:G14) -> 275645.05 | H18: =SUM(H5:H14) -> 273990.13 | I18: =SUM(I5:I14) -> 1654.92 | J18: =IF(H18>0,I18/H18,0) -> 0.0060400716 | K18: =IF($G$18>0,G18/$G$18,0) -> 1
A20: «Вложено» и «Результат» — по средней цене текущих позиций (как показывает брокер), без учёта уже закрытых сделок и дивидендов. Рубли на счёте учтены как вложенные по номиналу (результат 0).

Sheet Параметры
A1: Глобальные параметры моделей
A2: Синий — вводные, которые можно менять; жёлтая заливка — главные рычаги. Все модели ссылаются сюда.
A4: Параметр | B4: Значение | C4: Ед. | D4: Источник / комментарий
A5: Дата котировок | B5: 46319 | D5: Цены в «Сводке» — со скриншотов брокеров 24.10.2026 (сессия выходного дня); дальше обновляет бот.
A6: Средняя ключевая ставка 2027 (прогноз ЦБ) | B6: 0.13 | C6: % | D6: ЦБ 23.10.2026 сохранил ставку 14% и повысил прогноз средней ставки на 2027 до 12,5–13,5% (было 10,5–12,5%); берём середину. Коммерсантъ, 23.10.2026: https://www.kommersant.ru/doc/9059054
A7: Премия за риск российских акций | B7: 0.06 | C7: % | D7: Допущение модели: надбавка за риск акций над безрисковой ставкой; типичный диапазон в оценках инвестдомов 5–7%.
A8: Доходность 10-летних ОФЗ (для сравнения) | B8: 0.166 | C8: % | D8: Длинные ОФЗ 26250–26254 ~16,6% (smart-lab, 23.10.2026); 10-летние 16,46% (Fomag, 18.09.2026). Модель берёт ставку ЦБ на 2027, а не ОФЗ: в ОФЗ заложена рыночная инфляция ~8%, а рост g в моделях — при инфляции ~4–5%. Проверка «по ОФЗ» — на листах SBER и MTSS.
A9: Базовая требуемая доходность акций | B9: =$B$6+$B$7 -> 0.19 | C9: % | D9: Ставка + премия. Используется в дивидендных моделях (Сбер, МТС) и как ориентир для мультипликаторов.
A10: Зона покупки: скидка к справедливой | B10: 0.23 | C10: % | D10: Цена ниже справедливой на эту величину — бот шлёт сигнал «зона покупки» (запас прочности долгосрочного инвестора).
A11: Цена продажи: премия к справедливой | B11: 0.18 | C11: % | D11: Продаём не на справедливой цене, а с запасом: хорошая компания растёт вместе с прибылью.
A12: Порог «приближается к продаже» | B12: 0.05 | C12: % | D12: За сколько процентов до цены продажи бот предупреждает заранее.
A13: Курс USD/RUB (прогноз на горизонт оценки) | B13: 85 | C13: ₽ | D13: Курс ЦБ на 24.10.2026 — 80,54 ₽; опрос аналитиков ЦБ (октябрь 2026): средний курс 2027 — 89,4 ₽. Берём 85 ₽ — середину. Влияет на Полюс и газовые опционы Газпрома.
A14: Цена золота (прогноз на горизонт оценки) | B14: 3800 | C14: $/унц | D14: Спот 23–24.10.2026 ~3 995 $/унц (пик ~5 595 $ в январе 2026). Берём 3 800 $ — ниже спота, с запасом. Ключевая вводная для Полюса.
A15: Мир: вероятность мира и снятия всех санкций | B15: 0.5 | C15: % | D15: Решение пользователя (25.10.2026): 50% — мир и снятие всех санкций в течение 5 лет. Прибавка от мира пропорциональна вероятности.
A16: Мир: лет до снятия санкций | B16: 5 | C16: лет | D16: К этому году рынок возвращается к оценкам компаний до 2022 года. Прибавка к цене приводится к сегодняшнему дню по ставке эмитента.
A17: ИИ: рынок генеративного ИИ в РФ в 2030 | B17: 778 | C17: млрд ₽ | D17: Onside / Just AI (февраль 2026): 58 млрд в 2025 → 778 млрд в 2030 (+68% в год); Just AI — заинтересованная сторона. AIANA (август 2026): весь рынок ИИ с оборудованием 316 млрд в 2025 → 830 млрд в 2030 (база), 1 120 млрд (оптимистичный). Иностранные модели в РФ ограничены — рынок делят российские игроки (Яндекс, Сбер, МТС, VK, Т-Банк).
A18: ИИ: лет до 2030 | B18: 4 | C18: лет | D18: ИИ-бизнес оценивается на 2030 год и дисконтируется к сегодняшнему дню по ставке эмитента.
A19: ИИ: OpenAI — оценка / годовая выручка | B19: 28 | C19: x | D19: Переговоры о раунде при оценке ~$1,4 трлн (Bloomberg, сентябрь 2026) / годовой темп выручки ~$50 млрд (Axios, октябрь 2026). Последний закрытый раунд — $852 млрд (март 2026). Компания убыточна: операционный убыток $20,9 млрд в 2025.
A20: ИИ: Anthropic — оценка / годовая выручка | B20: 14.8 | C20: x | D20: $965 млрд (раунд серии H, май 2026) / годовой темп выручки $65 млрд (июль 2026, Bloomberg/CNBC).
A21: ИИ: Alphabet — капитализация / выручка 2026П | B21: 8.1 | C21: x | D21: $3,88 трлн (24.10.2026, companiesmarketcap) / ~$480 млрд выручки 2026П (1К $109,9 млрд, 2К $119,8 млрд, рост 24%).
A22: ИИ: мультипликатор лидеров (среднее трёх) | B22: =AVERAGE($B$19,$B$20,$B$21) -> 16.966667 | C22: x | D22: Стоимость компании, делённая на годовую выручку. Применяется к ИИ-выручке Яндекса, Сбера и МТС в 2030 году.
A23: ИИ: поправка на стоимость денег в РФ | B23: 1 | C23: x | D23: 1,0 — российский ИИ-бизнес оценивается так же, как OpenAI, Anthropic и Alphabet (допущение пользователя). Остальной бизнес тех же компаний рынок РФ оценивает примерно в 5 раз дешевле американских аналогов (строка ниже). Поставьте 0,2, чтобы увидеть консервативный вариант.
A24: Для сравнения: скидка рынка РФ к США | B24: 0.2 | C24: x | D24: Яндекс ~3,7x EV/EBITDA 2026П против ~19–20x у Alphabet (капитализация $3,88 трлн, EBITDA 2026П ~$195 млрд — оценка). Используется только в строках проверки.

Sheet SBER
A1: SBER — Сбербанк: модель справедливой стоимости
A2: Метод: дивидендная модель (формула Гордона)
A3: Банк платит 50% прибыли, поэтому стоимость акции = будущий дивиденд / (требуемая доходность − рост дивиденда). Проверка — P/E при справедливой цене против исторической нормы Сбера 4–6x.
A4: Синий — вводные (меняйте их), чёрный — формулы, зелёный — ссылки на другие листы, жёлтый — главные рычаги модели.
A6: Показатель | B6: Значение | C6: Ед. | D6: Источник / комментарий
A7: ВВОДНЫЕ
A8: Чистая прибыль 2026П (МСФО) | B8: 1950 | C8: млрд ₽ | D8: 9М 2026 РСБУ: 1 501 млрд (+18,2% г/г), ROE 23,0% (Reuters, 09.10.2026); 1П 2026 МСФО: 1 019 млрд; цель менеджмента ROE 22%; аналитики ждут 1,9–2,0 трлн.
A9: Доля прибыли на дивиденды | B9: 0.5 | C9: % | D9: Дивполитика: 50% прибыли МСФО; сохраняется в стратегии 2027–2029.
A10: Акций всего (обыкн. + преф.) | B10: 22.587 | C10: млрд шт | D10: 21,587 млрд обыкн. + 1,0 млрд преф. Сверка: дивиденды за 2025 = 850,2 млрд ₽ / 37,64 ₽ = 22,59 млрд.
A11: Базовая требуемая доходность | B11: =Параметры!$B$9 -> 0.19 | C11: % | D11: Из «Параметров»: ставка ЦБ 2027 + премия за риск акций.
A12: Премия за специфический риск | B12: 0 | C12: % | D12: Сбер — эталон рынка, дополнительная премия не нужна.
A13: Долгосрочный рост дивиденда | B13: 0.08 | C13: % | D13: Номинальный рост: инфляция в долгую ~4–5% + реальный рост бизнеса ~3–4%.
A14: ИИ: рынок генеративного ИИ в РФ в 2030 | B14: =Параметры!$B$17 -> 778 | C14: млрд ₽ | D14: Из «Параметров».
A15: ИИ: доля компании на рынке в 2030 | B15: 0.4 | C15: % | D15: GigaChat — лидер в банках, страховании и госсекторе (банки и страхование — 20% рынка генИИ), облако Cloud.ru. Вместе с Яндексом делят большую часть рынка. Оценка модели.
A16: ИИ: мультипликатор лидеров (оценка / выручка) | B16: =Параметры!$B$22 -> 16.966667 | C16: x | D16: Из «Параметров»: среднее OpenAI, Anthropic, Alphabet.
A17: ИИ: поправка на стоимость денег в РФ | B17: =Параметры!$B$23 -> 1 | C17: x | D17: Из «Параметров»: 1,0 — как у американских лидеров.
A18: ИИ: лет до 2030 | B18: =Параметры!$B$18 -> 4 | C18: лет | D18: Из «Параметров».
A19: Мир: вероятность мира и снятия санкций | B19: =Параметры!$B$15 -> 0.5 | C19: % | D19: Из «Параметров».
A20: Мир: лет до снятия санкций | B20: =Параметры!$B$16 -> 5 | C20: лет | D20: Из «Параметров».
A21: Мир: P/E как до 2022 года | B21: 6 | C21: x | D21: P/E Сбера в 2017–2021 был ~5–7x (2019 ~6,7x, 2021 ~5x). Применяется к прибыли 2026П.
A22: Мир: рост показателя до года мира, % в год | B22: 0.08 | C22: % | D22: Как рост дивиденда.
A24: РАСЧЁТ
A25: Дивиденд за 2026 (выплата летом 2027) | B25: =$B$8*$B$9/$B$10 -> 43.166423 | C25: ₽/акц.
A26: Требуемая доходность | B26: =$B$11+$B$12 -> 0.19 | C26: %
A27: Справедливая дивдоходность (r − g) | B27: =$B$26-$B$13 -> 0.11 | C27: %
A28: Базовая цена = дивиденд / (r − g) | B28: =IF($B$27>0,$B$25/$B$27,0) -> 392.42203 | C28: ₽ | D28: Банк без отдельной оценки ИИ.
A29: ИИ: выручка компании в 2030 | B29: =$B$14*$B$15 -> 311.2 | C29: млрд ₽
A30: ИИ: стоимость ИИ-бизнеса в 2030 | B30: =$B$29*$B$16*$B$17 -> 5280.0267 | C30: млрд ₽ | D30: Выручка × мультипликатор лидеров × поправка РФ.
A31: ИИ: стоимость сегодня (дисконт до 2030) | B31: =$B$30/(1+$B$11)^$B$18 -> 2632.9843 | C31: млрд ₽
A32: ИИ: прибавка к цене акции | B32: =IF($B$10>0,$B$31/$B$10,0) -> 116.57078 | C32: ₽
A33: Справедливая цена без мира | B33: =$B$28+$B$32 -> 508.99281 | C33: ₽
A34: Мир: цена в мирном режиме на сегодняшних показателях | B34: =$B$21*$B$8/$B$10 -> 517.99708 | C34: ₽ | D34: Если бы рынок уже сегодня оценивал компанию как до 2022 года. Без ИИ-блока.
A35: Мир: прибавка к цене сегодня | B35: =$B$19*($B$34-$B$28)*((1+$B$22)/(1+$B$11))^$B$20 -> 38.659598 | C35: ₽ | D35: Вероятность × разница цен × рост показателя до года мира, приведённый к сегодняшнему дню.
A36: Справедливая цена с миром | B36: =$B$33+$B$35 -> 547.65241 | C36: ₽
A38: РЕЗУЛЬТАТ
A39: Справедливая цена | B39: =$B$36 -> 547.65241 | C39: ₽ | D39: Главный вывод модели
A40: Текущая цена | B40: =Сводка!$D$5 -> 292.32 | C40: ₽ | D40: Берётся со «Сводки» (столбец D)
A41: Зона покупки: цена не выше | B41: =$B$39*(1-Параметры!$B$10) -> 421.69236 | C41: ₽ | D41: Справедливая минус скидка из «Параметров»
A42: Цена продажи | B42: =$B$39*(1+Параметры!$B$11) -> 646.22984 | C42: ₽ | D42: Справедливая плюс премия из «Параметров»
A43: Сигнал «приближается к продаже» от | B43: =$B$42*(1-Параметры!$B$12) -> 613.91835 | C43: ₽ | D43: За сколько % до цены продажи бот предупреждает
A44: Потенциал до справедливой | B44: =IF($B$40>0,$B$39/$B$40-1,0) -> 0.87346884 | C44: %
A45: До цены продажи | B45: =IF($B$40>0,$B$42/$B$40-1,0) -> 1.2106932 | C45: %
A46: Статус | B46: =IF($B$40<=$B$41,"ЗОНА ПОКУПКИ",IF($B$40>=$B$42,"ЦЕНА ПРОДАЖИ",IF($B$40>=$B$43,"ПРИБЛИЖАЕТСЯ К ПРОДАЖЕ","ДЕРЖАТЬ"))) -> ЗОНА ПОКУПКИ | D46: Слом тезиса — отдельный сигнал, см. ниже
A48: ПЕРЕКРЁСТНАЯ ПРОВЕРКА
A49: Доля ИИ в справедливой цене | B49: =IF($B$39>0,$B$32/$B$39,0) -> 0.21285542 | C49: %
A50: ИИ-прибавка при скидке рынка РФ к США | B50: =IF($B$17>0,$B$32/$B$17*Параметры!$B$24,0) -> 23.314157 | C50: ₽ | D50: Если ИИ-бизнес рынок оценит с той же скидкой к американским аналогам, что и весь Яндекс (~0,2).
A51: Справедливая цена при этой скидке | B51: =$B$28+$B$50 -> 415.73619 | C51: ₽ | D51: Консервативный ориентир.
A52: Прибыль на акцию 2026П | B52: =$B$8/$B$10 -> 86.332846 | C52: ₽
A53: P/E базовой цены (без ИИ) | B53: =IF($B$52>0,$B$28/$B$52,0) -> 4.5454545 | C53: x | D53: Историческая норма Сбера — 4–6x. Выше 6x — модель, скорее всего, слишком оптимистична.
A54: P/E при текущей цене | B54: =IF($B$52>0,$B$40/$B$52,0) -> 3.385965 | C54: x
A55: Дивдоходность к текущей цене | B55: =IF($B$40>0,$B$25/$B$40,0) -> 0.14766839 | C55: %
A56: Базовая цена (без ИИ), если ставка = длинные ОФЗ + премия | B56: =IF(Параметры!$B$8+Параметры!$B$7+$B$12-$B$13>0,$B$25/(Параметры!$B$8+Параметры!$B$7+$B$12-$B$13),0) -> 295.66043 | C56: ₽ | D56: Строгий вариант: рост g прежний, а ставка — по рынку длинных ОФЗ. Если верите рынку, а не прогнозу ЦБ, ориентир для базовой части — эта цифра.
A57: Доходность, которую закладывает текущая цена (D/P + g) | B57: =IF($B$40>0,$B$25/$B$40+$B$13,0) -> 0.22766839 | C57: % | D57: Сравните с длинными ОФЗ 16,6%.
A59: ЧУВСТВИТЕЛЬНОСТЬ СПРАВЕДЛИВОЙ ЦЕНЫ, ₽: строки — рост дивиденда, столбцы — прибыль 2026П, млрд ₽
A60: рост дивиденда \ прибыль 2026П, млрд ₽ | B60: 1800 | C60: 1875 | D60: 1950 | E60: 2025 | F60: 2100
A61: 0.06 | B61: =(B$60*$B$9/$B$10/($B$11+$B$12-$A61)+$B$14*$B$15*$B$16*$B$17/(1+$B$11)^$B$18/$B$10)+$B$19*(($B$21*B$60/$B$10)-(B$60*$B$9/$B$10/($B$11+$B$12-$A61)))*((1+$B$22)/(1+$B$11))^$B$20 -> 475.92034 | C61: =(C$60*$B$9/$B$10/($B$11+$B$12-$A61)+$B$14*$B$15*$B$16*$B$17/(1+$B$11)^$B$18/$B$10)+$B$19*(($B$21*C$60/$B$10)-(C$60*$B$9/$B$10/($B$11+$B$12-$A61)))*((1+$B$22)/(1+$B$11))^$B$20 -> 490.89324 | D61: =(D$60*$B$9/$B$10/($B$11+$B$12-$A61)+$B$14*$B$15*$B$16*$B$17/(1+$B$11)^$B$18/$B$10)+$B$19*(($B$21*D$60/$B$10)-(D$60*$B$9/$B$10/($B$11+$B$12-$A61)))*((1+$B$22)/(1+$B$11))^$B$20 -> 505.86614 | E61: =(E$60*$B$9/$B$10/($B$11+$B$12-$A61)+$B$14*$B$15*$B$16*$B$17/(1+$B$11)^$B$18/$B$10)+$B$19*(($B$21*E$60/$B$10)-(E$60*$B$9/$B$10/($B$11+$B$12-$A61)))*((1+$B$22)/(1+$B$11))^$B$20 -> 520.83903 | F61: =(F$60*$B$9/$B$10/($B$11+$B$12-$A61)+$B$14*$B$15*$B$16*$B$17/(1+$B$11)^$B$18/$B$10)+$B$19*(($B$21*F$60/$B$10)-(F$60*$B$9/$B$10/($B$11+$B$12-$A61)))*((1+$B$22)/(1+$B$11))^$B$20 -> 535.81193
A62: 0.07 | B62: =(B$60*$B$9/$B$10/($B$11+$B$12-$A62)+$B$14*$B$15*$B$16*$B$17/(1+$B$11)^$B$18/$B$10)+$B$19*(($B$21*B$60/$B$10)-(B$60*$B$9/$B$10/($B$11+$B$12-$A62)))*((1+$B$22)/(1+$B$11))^$B$20 -> 493.59915 | C62: =(C$60*$B$9/$B$10/($B$11+$B$12-$A62)+$B$14*$B$15*$B$16*$B$17/(1+$B$11)^$B$18/$B$10)+$B$19*(($B$21*C$60/$B$10)-(C$60*$B$9/$B$10/($B$11+$B$12-$A62)))*((1+$B$22)/(1+$B$11))^$B$20 -> 509.30866 | D62: =(D$60*$B$9/$B$10/($B$11+$B$12-$A62)+$B$14*$B$15*$B$16*$B$17/(1+$B$11)^$B$18/$B$10)+$B$19*(($B$21*D$60/$B$10)-(D$60*$B$9/$B$10/($B$11+$B$12-$A62)))*((1+$B$22)/(1+$B$11))^$B$20 -> 525.01818 | E62: =(E$60*$B$9/$B$10/($B$11+$B$12-$A62)+$B$14*$B$15*$B$16*$B$17/(1+$B$11)^$B$18/$B$10)+$B$19*(($B$21*E$60/$B$10)-(E$60*$B$9/$B$10/($B$11+$B$12-$A62)))*((1+$B$22)/(1+$B$11))^$B$20 -> 540.72769 | F62: =(F$60*$B$9/$B$10/($B$11+$B$12-$A62)+$B$14*$B$15*$B$16*$B$17/(1+$B$11)^$B$18/$B$10)+$B$19*(($B$21*F$60/$B$10)-(F$60*$B$9/$B$10/($B$11+$B$12-$A62)))*((1+$B$22)/(1+$B$11))^$B$20 -> 556.43721
A63: 0.08 | B63: =(B$60*$B$9/$B$10/($B$11+$B$12-$A63)+$B$14*$B$15*$B$16*$B$17/(1+$B$11)^$B$18/$B$10)+$B$19*(($B$21*B$60/$B$10)-(B$60*$B$9/$B$10/($B$11+$B$12-$A63)))*((1+$B$22)/(1+$B$11))^$B$20 -> 514.49229 | C63: =(C$60*$B$9/$B$10/($B$11+$B$12-$A63)+$B$14*$B$15*$B$16*$B$17/(1+$B$11)^$B$18/$B$10)+$B$19*(($B$21*C$60/$B$10)-(C$60*$B$9/$B$10/($B$11+$B$12-$A63)))*((1+$B$22)/(1+$B$11))^$B$20 -> 531.07235 | D63: =(D$60*$B$9/$B$10/($B$11+$B$12-$A63)+$B$14*$B$15*$B$16*$B$17/(1+$B$11)^$B$18/$B$10)+$B$19*(($B$21*D$60/$B$10)-(D$60*$B$9/$B$10/($B$11+$B$12-$A63)))*((1+$B$22)/(1+$B$11))^$B$20 -> 547.65241 | E63: =(E$60*$B$9/$B$10/($B$11+$B$12-$A63)+$B$14*$B$15*$B$16*$B$17/(1+$B$11)^$B$18/$B$10)+$B$19*(($B$21*E$60/$B$10)-(E$60*$B$9/$B$10/($B$11+$B$12-$A63)))*((1+$B$22)/(1+$B$11))^$B$20 -> 564.23247 | F63: =(F$60*$B$9/$B$10/($B$11+$B$12-$A63)+$B$14*$B$15*$B$16*$B$17/(1+$B$11)^$B$18/$B$10)+$B$19*(($B$21*F$60/$B$10)-(F$60*$B$9/$B$10/($B$11+$B$12-$A63)))*((1+$B$22)/(1+$B$11))^$B$20 -> 580.81254
A64: 0.09 | B64: =(B$60*$B$9/$B$10/($B$11+$B$12-$A64)+$B$14*$B$15*$B$16*$B$17/(1+$B$11)^$B$18/$B$10)+$B$19*(($B$21*B$60/$B$10)-(B$60*$B$9/$B$10/($B$11+$B$12-$A64)))*((1+$B$22)/(1+$B$11))^$B$20 -> 539.56405 | C64: =(C$60*$B$9/$B$10/($B$11+$B$12-$A64)+$B$14*$B$15*$B$16*$B$17/(1+$B$11)^$B$18/$B$10)+$B$19*(($B$21*C$60/$B$10)-(C$60*$B$9/$B$10/($B$11+$B$12-$A64)))*((1+$B$22)/(1+$B$11))^$B$20 -> 557.18877 | D64: =(D$60*$B$9/$B$10/($B$11+$B$12-$A64)+$B$14*$B$15*$B$16*$B$17/(1+$B$11)^$B$18/$B$10)+$B$19*(($B$21*D$60/$B$10)-(D$60*$B$9/$B$10/($B$11+$B$12-$A64)))*((1+$B$22)/(1+$B$11))^$B$20 -> 574.81349 | E64: =(E$60*$B$9/$B$10/($B$11+$B$12-$A64)+$B$14*$B$15*$B$16*$B$17/(1+$B$11)^$B$18/$B$10)+$B$19*(($B$21*E$60/$B$10)-(E$60*$B$9/$B$10/($B$11+$B$12-$A64)))*((1+$B$22)/(1+$B$11))^$B$20 -> 592.43821 | F64: =(F$60*$B$9/$B$10/($B$11+$B$12-$A64)+$B$14*$B$15*$B$16*$B$17/(1+$B$11)^$B$18/$B$10)+$B$19*(($B$21*F$60/$B$10)-(F$60*$B$9/$B$10/($B$11+$B$12-$A64)))*((1+$B$22)/(1+$B$11))^$B$20 -> 610.06293
A65: 0.1 | B65: =(B$60*$B$9/$B$10/($B$11+$B$12-$A65)+$B$14*$B$15*$B$16*$B$17/(1+$B$11)^$B$18/$B$10)+$B$19*(($B$21*B$60/$B$10)-(B$60*$B$9/$B$10/($B$11+$B$12-$A65)))*((1+$B$22)/(1+$B$11))^$B$20 -> 570.20732 | C65: =(C$60*$B$9/$B$10/($B$11+$B$12-$A65)+$B$14*$B$15*$B$16*$B$17/(1+$B$11)^$B$18/$B$10)+$B$19*(($B$21*C$60/$B$10)-(C$60*$B$9/$B$10/($B$11+$B$12-$A65)))*((1+$B$22)/(1+$B$11))^$B$20 -> 589.10884 | D65: =(D$60*$B$9/$B$10/($B$11+$B$12-$A65)+$B$14*$B$15*$B$16*$B$17/(1+$B$11)^$B$18/$B$10)+$B$19*(($B$21*D$60/$B$10)-(D$60*$B$9/$B$10/($B$11+$B$12-$A65)))*((1+$B$22)/(1+$B$11))^$B$20 -> 608.01036 | E65: =(E$60*$B$9/$B$10/($B$11+$B$12-$A65)+$B$14*$B$15*$B$16*$B$17/(1+$B$11)^$B$18/$B$10)+$B$19*(($B$21*E$60/$B$10)-(E$60*$B$9/$B$10/($B$11+$B$12-$A65)))*((1+$B$22)/(1+$B$11))^$B$20 -> 626.91189 | F65: =(F$60*$B$9/$B$10/($B$11+$B$12-$A65)+$B$14*$B$15*$B$16*$B$17/(1+$B$11)^$B$18/$B$10)+$B$19*(($B$21*F$60/$B$10)-(F$60*$B$9/$B$10/($B$11+$B$12-$A65)))*((1+$B$22)/(1+$B$11))^$B$20 -> 645.81341
A66: Центр таблицы (жёлтая ячейка) = базовый сценарий; должен совпадать со справедливой ценой.
A68: ЧУВСТВИТЕЛЬНОСТЬ СПРАВЕДЛИВОЙ ЦЕНЫ, ₽: строки — доля Сбера на рынке ИИ, столбцы — рынок генИИ в РФ 2030, млрд ₽
A69: доля Сбера на рынке ИИ \ рынок генИИ в РФ 2030, млрд ₽ | B69: 400 | C69: 590 | D69: 778 | E69: 950 | F69: 1120
A70: 0.2 | B70: =($B$8*$B$9/$B$10/($B$11+$B$12-$B$13)+B$69*$A70*$B$16*$B$17/(1+$B$11)^$B$18/$B$10)+$B$19*(($B$21*$B$8/$B$10)-($B$8*$B$9/$B$10/($B$11+$B$12-$B$13)))*((1+$B$22)/(1+$B$11))^$B$20 -> 461.04841 | C70: =($B$8*$B$9/$B$10/($B$11+$B$12-$B$13)+C$69*$A70*$B$16*$B$17/(1+$B$11)^$B$18/$B$10)+$B$19*(($B$21*$B$8/$B$10)-($B$8*$B$9/$B$10/($B$11+$B$12-$B$13)))*((1+$B$22)/(1+$B$11))^$B$20 -> 475.28263 | D70: =($B$8*$B$9/$B$10/($B$11+$B$12-$B$13)+D$69*$A70*$B$16*$B$17/(1+$B$11)^$B$18/$B$10)+$B$19*(($B$21*$B$8/$B$10)-($B$8*$B$9/$B$10/($B$11+$B$12-$B$13)))*((1+$B$22)/(1+$B$11))^$B$20 -> 489.36702 | E70: =($B$8*$B$9/$B$10/($B$11+$B$12-$B$13)+E$69*$A70*$B$16*$B$17/(1+$B$11)^$B$18/$B$10)+$B$19*(($B$21*$B$8/$B$10)-($B$8*$B$9/$B$10/($B$11+$B$12-$B$13)))*((1+$B$22)/(1+$B$11))^$B$20 -> 502.25274 | F70: =($B$8*$B$9/$B$10/($B$11+$B$12-$B$13)+F$69*$A70*$B$16*$B$17/(1+$B$11)^$B$18/$B$10)+$B$19*(($B$21*$B$8/$B$10)-($B$8*$B$9/$B$10/($B$11+$B$12-$B$13)))*((1+$B$22)/(1+$B$11))^$B$20 -> 514.98862
A71: 0.3 | B71: =($B$8*$B$9/$B$10/($B$11+$B$12-$B$13)+B$69*$A71*$B$16*$B$17/(1+$B$11)^$B$18/$B$10)+$B$19*(($B$21*$B$8/$B$10)-($B$8*$B$9/$B$10/($B$11+$B$12-$B$13)))*((1+$B$22)/(1+$B$11))^$B$20 -> 476.0318 | C71: =($B$8*$B$9/$B$10/($B$11+$B$12-$B$13)+C$69*$A71*$B$16*$B$17/(1+$B$11)^$B$18/$B$10)+$B$19*(($B$21*$B$8/$B$10)-($B$8*$B$9/$B$10/($B$11+$B$12-$B$13)))*((1+$B$22)/(1+$B$11))^$B$20 -> 497.38313 | D71: =($B$8*$B$9/$B$10/($B$11+$B$12-$B$13)+D$69*$A71*$B$16*$B$17/(1+$B$11)^$B$18/$B$10)+$B$19*(($B$21*$B$8/$B$10)-($B$8*$B$9/$B$10/($B$11+$B$12-$B$13)))*((1+$B$22)/(1+$B$11))^$B$20 -> 518.50971 | E71: =($B$8*$B$9/$B$10/($B$11+$B$12-$B$13)+E$69*$A71*$B$16*$B$17/(1+$B$11)^$B$18/$B$10)+$B$19*(($B$21*$B$8/$B$10)-($B$8*$B$9/$B$10/($B$11+$B$12-$B$13)))*((1+$B$22)/(1+$B$11))^$B$20 -> 537.83829 | F71: =($B$8*$B$9/$B$10/($B$11+$B$12-$B$13)+F$69*$A71*$B$16*$B$17/(1+$B$11)^$B$18/$B$10)+$B$19*(($B$21*$B$8/$B$10)-($B$8*$B$9/$B$10/($B$11+$B$12-$B$13)))*((1+$B$22)/(1+$B$11))^$B$20 -> 556.94211
A72: 0.4 | B72: =($B$8*$B$9/$B$10/($B$11+$B$12-$B$13)+B$69*$A72*$B$16*$B$17/(1+$B$11)^$B$18/$B$10)+$B$19*(($B$21*$B$8/$B$10)-($B$8*$B$9/$B$10/($B$11+$B$12-$B$13)))*((1+$B$22)/(1+$B$11))^$B$20 -> 491.01519 | C72: =($B$8*$B$9/$B$10/($B$11+$B$12-$B$13)+C$69*$A72*$B$16*$B$17/(1+$B$11)^$B$18/$B$10)+$B$19*(($B$21*$B$8/$B$10)-($B$8*$B$9/$B$10/($B$11+$B$12-$B$13)))*((1+$B$22)/(1+$B$11))^$B$20 -> 519.48364 | D72: =($B$8*$B$9/$B$10/($B$11+$B$12-$B$13)+D$69*$A72*$B$16*$B$17/(1+$B$11)^$B$18/$B$10)+$B$19*(($B$21*$B$8/$B$10)-($B$8*$B$9/$B$10/($B$11+$B$12-$B$13)))*((1+$B$22)/(1+$B$11))^$B$20 -> 547.65241 | E72: =($B$8*$B$9/$B$10/($B$11+$B$12-$B$13)+E$69*$A72*$B$16*$B$17/(1+$B$11)^$B$18/$B$10)+$B$19*(($B$21*$B$8/$B$10)-($B$8*$B$9/$B$10/($B$11+$B$12-$B$13)))*((1+$B$22)/(1+$B$11))^$B$20 -> 573.42384 | F72: =($B$8*$B$9/$B$10/($B$11+$B$12-$B$13)+F$69*$A72*$B$16*$B$17/(1+$B$11)^$B$18/$B$10)+$B$19*(($B$21*$B$8/$B$10)-($B$8*$B$9/$B$10/($B$11+$B$12-$B$13)))*((1+$B$22)/(1+$B$11))^$B$20 -> 598.89561
A73: 0.5 | B73: =($B$8*$B$9/$B$10/($B$11+$B$12-$B$13)+B$69*$A73*$B$16*$B$17/(1+$B$11)^$B$18/$B$10)+$B$19*(($B$21*$B$8/$B$10)-($B$8*$B$9/$B$10/($B$11+$B$12-$B$13)))*((1+$B$22)/(1+$B$11))^$B$20 -> 505.99858 | C73: =($B$8*$B$9/$B$10/($B$11+$B$12-$B$13)+C$69*$A73*$B$16*$B$17/(1+$B$11)^$B$18/$B$10)+$B$19*(($B$21*$B$8/$B$10)-($B$8*$B$9/$B$10/($B$11+$B$12-$B$13)))*((1+$B$22)/(1+$B$11))^$B$20 -> 541.58414 | D73: =($B$8*$B$9/$B$10/($B$11+$B$12-$B$13)+D$69*$A73*$B$16*$B$17/(1+$B$11)^$B$18/$B$10)+$B$19*(($B$21*$B$8/$B$10)-($B$8*$B$9/$B$10/($B$11+$B$12-$B$13)))*((1+$B$22)/(1+$B$11))^$B$20 -> 576.79511 | E73: =($B$8*$B$9/$B$10/($B$11+$B$12-$B$13)+E$69*$A73*$B$16*$B$17/(1+$B$11)^$B$18/$B$10)+$B$19*(($B$21*$B$8/$B$10)-($B$8*$B$9/$B$10/($B$11+$B$12-$B$13)))*((1+$B$22)/(1+$B$11))^$B$20 -> 609.0094 | F73: =($B$8*$B$9/$B$10/($B$11+$B$12-$B$13)+F$69*$A73*$B$16*$B$17/(1+$B$11)^$B$18/$B$10)+$B$19*(($B$21*$B$8/$B$10)-($B$8*$B$9/$B$10/($B$11+$B$12-$B$13)))*((1+$B$22)/(1+$B$11))^$B$20 -> 640.8491
A74: 0.6 | B74: =($B$8*$B$9/$B$10/($B$11+$B$12-$B$13)+B$69*$A74*$B$16*$B$17/(1+$B$11)^$B$18/$B$10)+$B$19*(($B$21*$B$8/$B$10)-($B$8*$B$9/$B$10/($B$11+$B$12-$B$13)))*((1+$B$22)/(1+$B$11))^$B$20 -> 520.98197 | C74: =($B$8*$B$9/$B$10/($B$11+$B$12-$B$13)+C$69*$A74*$B$16*$B$17/(1+$B$11)^$B$18/$B$10)+$B$19*(($B$21*$B$8/$B$10)-($B$8*$B$9/$B$10/($B$11+$B$12-$B$13)))*((1+$B$22)/(1+$B$11))^$B$20 -> 563.68464 | D74: =($B$8*$B$9/$B$10/($B$11+$B$12-$B$13)+D$69*$A74*$B$16*$B$17/(1+$B$11)^$B$18/$B$10)+$B$19*(($B$21*$B$8/$B$10)-($B$8*$B$9/$B$10/($B$11+$B$12-$B$13)))*((1+$B$22)/(1+$B$11))^$B$20 -> 605.9378 | E74: =($B$8*$B$9/$B$10/($B$11+$B$12-$B$13)+E$69*$A74*$B$16*$B$17/(1+$B$11)^$B$18/$B$10)+$B$19*(($B$21*$B$8/$B$10)-($B$8*$B$9/$B$10/($B$11+$B$12-$B$13)))*((1+$B$22)/(1+$B$11))^$B$20 -> 644.59495 | F74: =($B$8*$B$9/$B$10/($B$11+$B$12-$B$13)+F$69*$A74*$B$16*$B$17/(1+$B$11)^$B$18/$B$10)+$B$19*(($B$21*$B$8/$B$10)-($B$8*$B$9/$B$10/($B$11+$B$12-$B$13)))*((1+$B$22)/(1+$B$11))^$B$20 -> 682.8026
A75: Центр таблицы (жёлтая ячейка) = базовый сценарий; должен совпадать со справедливой ценой.
A77: ТЕЗИС И УСЛОВИЯ ЕГО СЛОМА (сигнал при любой цене)
A78: Тезис: Крупнейший банк страны с ROE 22–24% и выплатой половины прибыли. Рынок оценивает его в 3–3,5 годовые прибыли из‑за высоких ставок и геополитики; по мере снижения ставки оценка нормализуется к 4,5–5 прибылям, а пока вы ждёте — получаете ~14% дивидендами. Сверху — GigaChat: если российский ИИ-рынок достанется своим игрокам и будет оценён как OpenAI и Google, Сбер получает долю монополиста.
A79: • ROE ниже 18% два квартала подряд
A80: • Отказ от выплаты 50% прибыли по МСФО или перенос дивидендов
A81: • Стоимость риска выше 2% (ориентир банка — до 1,4%)
A82: • Допэмиссия или разовые изъятия в бюджет сверх налогов
A84: ЧТО ОТСЛЕЖИВАЕТ БОТ В НОВОСТЯХ
A85: • Ежемесячная РСБУ (прибыль, ROE) → вводная «Чистая прибыль 2026П»
A86: • Квартальная МСФО и прогноз менеджмента на год
A87: • Решения ЦБ по ставке и его прогноз ставки → лист «Параметры»
A88: • Рекомендация набсовета по дивидендам (весна 2027)
... A100: ValueAdd VC — выручка и оценка Anthropic: https://valueaddvc.com/blog/anthropic-revenue-hits-47b-run-rate-how-it-passed-openai-in-just-five-months

Sheet PLZL
A1: PLZL — Полюс: модель справедливой стоимости
A2: Метод: EV/EBITDA 2027 от цены золота, себестоимости и курса, с дисконтом за паузу дивидендов
A3: EBITDA = добыча × (цена золота − денежная себестоимость TCC) − прочие расходы, в рублях по курсу, минус постоянные новые налоги. Стоимость = EBITDA × мультипликатор − чистый долг − разовый налог, минус дисконт за паузу дивидендов до 2030 и урезанную отчётность. Делим на акции в обращении (без 408 млн акций у дочерней компании).
A4: Синий — вводные (меняйте их), чёрный — формулы, зелёный — ссылки на другие листы, жёлтый — главные рычаги модели.
A6: Показатель | B6: Значение | C6: Ед. | D6: Источник / комментарий
A7: ВВОДНЫЕ
A8: Производство золота 2027 | B8: 2550 | C8: тыс. унц | D8: Гайденс 2026 и 2027: 2,5–2,6 млн унций (Коммерсантъ); 2025: 2 529 тыс. унций.
A9: Цена золота | B9: =Параметры!$B$14 -> 3800 | C9: $/унц | D9: Из «Параметров».
A10: Денежная себестоимость TCC | B10: 1000 | C10: $/унц | D10: 2025: $739; 1П 2026: $1 069 (+64%); прогноз 2026: $990–1 040 при золоте $4 000 (растёт вместе с ценой из‑за НДПИ).
A11: Прочие расходы, % выручки | B11: 0.06 | C11: % | D11: 2025: выручка $8 723 млн − TCC × продажи ≈ $6 850 млн против EBITDA $6 347 млн → ~6%.
A12: Курс USD/RUB | B12: =Параметры!$B$13 -> 85 | C12: ₽ | D12: Из «Параметров».
A13: Постоянные новые налоги в год (НДПИ) | B13: 0 | C13: млрд ₽ | D13: Сообщения противоречат друг другу: Т-Инвестиции оценивали рост НДПИ на золото в ~30 млрд за 2 года, Fomag пишет, что повышение не предлагается. Если подтвердится — поставьте ~15.
A14: Разовый налог на сверхдоходы за 2026 | B14: 25 | C14: млрд ₽ | D14: Законопроект Минфина (Интерфакс, 24.09.2026): 20% для золотодобытчиков с доходов 2026 года сверх базы 2025. БКС: ~25 млрд ₽ для Полюса. Разовый — вычитается как долг, а не из EBITDA каждого года.
A15: Справедливый EV/EBITDA | B15: 4.5 | C15: x | D15: Исторически Полюс стоил 6x+ как самый дешёвый производитель в мире; сейчас рынок даёт ~3x.
A16: Чистый долг | B16: 600 | C16: млрд ₽ | D16: 31.12.2025: 554,6 млрд (1,1x); на 30.06.2026 Велес оценивает $7,5 млрд. Капзатраты $2,2–2,5 млрд в год и Сухой Лог (~$6 млрд) не дают долгу снижаться.
A17: Дисконт за паузу дивидендов и прозрачность | B17: 0.35 | C17: % | D17: 08.07.2026 менеджмент рекомендовал не платить дивиденды до 2030 (−25% за день); с 1П 2026 отчётность урезана, EBITDA не раскрывается.
A18: Акций в обращении | B18: 950 | C18: млн шт | D18: Выпущено 1 360,7 млн, из них ~408 млн выкуплены дочерней «Полюс Красноярск» в 2023. Сверка: дивиденд 54 млрд ₽ / 56,8 ₽ = ~951 млн.
A19: Ставка дисконтирования | B19: =Параметры!$B$9 -> 0.19 | C19: % | D19: Из «Параметров».
A20: Мир: вероятность мира и снятия санкций | B20: =Параметры!$B$15 -> 0.5 | C20: % | D20: Из «Параметров».
A21: Мир: лет до снятия санкций | B21: =Параметры!$B$16 -> 5 | C21: лет | D21: Из «Параметров».
A22: Мир: EV/EBITDA как до 2022 года | B22: 7 | C22: x | D22: В 2019–2021 Полюс стоил ~7–9x EBITDA. Дисконт за паузу дивидендов сохраняем — мир его не отменяет.
A23: Мир: рост показателя до года мира, % в год | B23: 0.1 | C23: % | D23: Сухой Лог удваивает добычу к ~2030.
A25: РАСЧЁТ
A26: Выручка 2027П | B26: =$B$8*$B$9*$B$12/1000000 -> 823.65 | C26: млрд ₽
A27: EBITDA до новых налогов | B27: =($B$8*($B$9-$B$10)-$B$11*$B$8*$B$9)*$B$12/1000000 -> 557.481 | C27: млрд ₽
A28: EBITDA 2027П | B28: =$B$27-$B$13 -> 557.481 | C28: млрд ₽
A29: Справедливая стоимость бизнеса (EV) | B29: =$B$28*$B$15 -> 2508.6645 | C29: млрд ₽
A30: Капитал до дисконта | B30: =$B$29-$B$16-$B$14 -> 1883.6645 | C30: млрд ₽
A31: Капитал после дисконта | B31: =$B$30*(1-$B$17) -> 1224.3819 | C31: млрд ₽
A32: Справедливая цена без мира | B32: =IF($B$18>0,$B$31*1000/$B$18,0) -> 1288.8231 | C32: ₽
A33: Мир: цена в мирном режиме на сегодняшних показателях | B33: =((($B$8*($B$9-$B$10)-$B$11*$B$8*$B$9)*$B$12/1000000-$B$13)*$B$22-$B$16-$B$14)*(1-$B$17)*1000/$B$18 -> 2242.409 | C33: ₽ | D33: Если бы рынок уже сегодня оценивал компанию как до 2022 года.
A34: Мир: прибавка к цене сегодня | B34: =$B$20*($B$33-$B$32)*((1+$B$23)/(1+$B$19))^$B$21 -> 321.77956 | C34: ₽ | D34: Вероятность × разница цен × рост показателя до года мира, приведённый к сегодняшнему дню.
A35: Справедливая цена с миром | B35: =$B$32+$B$34 -> 1610.6026 | C35: ₽
A37: РЕЗУЛЬТАТ
A38: Справедливая цена | B38: =$B$35 -> 1610.6026 | C38: ₽ | D38: Главный вывод модели
A39: Текущая цена | B39: =Сводка!$D$6 -> 1098.2 | C39: ₽ | D39: Берётся со «Сводки» (столбец D)
A40: Зона покупки: цена не выше | B40: =$B$38*(1-Параметры!$B$10) -> 1240.164 | C40: ₽ | D40: Справедливая минус скидка из «Параметров»
A41: Цена продажи | B41: =$B$38*(1+Параметры!$B$11) -> 1900.5111 | C41: ₽ | D41: Справедливая плюс премия из «Параметров»
A42: Сигнал «приближается к продаже» от | B42: =$B$41*(1-Параметры!$B$12) -> 1805.4856 | C42: ₽ | D42: За сколько % до цены продажи бот предупреждает
A43: Потенциал до справедливой | B43: =IF($B$39>0,$B$38/$B$39-1,0) -> 0.46658408 | C43: %
A44: До цены продажи | B44: =IF($B$39>0,$B$41/$B$39-1,0) -> 0.73056922 | C44: %
A45: Статус | B45: =IF($B$39<=$B$40,"ЗОНА ПОКУПКИ",IF($B$39>=$B$41,"ЦЕНА ПРОДАЖИ",IF($B$39>=$B$42,"ПРИБЛИЖАЕТСЯ К ПРОДАЖЕ","ДЕРЖАТЬ"))) -> ЗОНА ПОКУПКИ | D45: Слом тезиса — отдельный сигнал, см. ниже
A47: ПЕРЕКРЁСТНАЯ ПРОВЕРКА
A48: EV/EBITDA 2027П при текущей цене | B48: =IF($B$28>0,($B$39*$B$18/1000+$B$16)/$B$28,0) -> 2.9477058 | C48: x | D48: Капитализация считается на акции в обращении.
A49: Чистый долг / EBITDA | B49: =IF($B$28>0,$B$16/$B$28,0) -> 1.0762699 | C49: x
A50: Для сравнения: EBITDA 2025 | B50: =517.8 -> 517.8 | C50: млрд ₽ | D50: $6 347 млн (Полюс, март 2026).
A51: Цель Велес Капитала | B51: =1510 -> 1510 | C51: ₽ | D51: Август–сентябрь 2026, «покупать»; БКС 21.10.2026 — идея на понижение с целью 1 000 ₽.
A53: ЧУВСТВИТЕЛЬНОСТЬ СПРАВЕДЛИВОЙ ЦЕНЫ, ₽: строки — золото, $/унц, столбцы — курс USD/RUB
A54: золото, $/унц \ курс USD/RUB | B54: 75 | C54: 80 | D54: 85 | E54: 90 | F54: 95
A55: 3000 | B55: =(((($B$8*($A55-$B$10)-$B$11*$B$8*$A55)*B$54/1000000-$B$13)*$B$15-$B$16-$B$14)*(1-$B$17)*1000/$B$18)+$B$20*((((($B$8*($A55-$B$10)-$B$11*$B$8*$A55)*B$54/1000000-$B$13)*$B$22-$B$16-$B$14)*(1-$B$17)*1000/$B$18)-(((($B$8*($A55-$B$10)-$B$11*$B$8*$A55)*B$54/1000000-$B$13)*$B$15-$B$16-$B$14)*(1-$B$17)*1000/$B$18))*((1+$B$23)/(1+$B$19))^$B$21 -> 844.98287 | C55: =(((($B$8*($A55-$B$10)-$B$11*$B$8*$A55)*C$54/1000000-$B$13)*$B$15-$B$16-$B$14)*(1-$B$17)*1000/$B$18)+$B$20*((((($B$8*($A55-$B$10)-$B$11*$B$8*$A55)*C$54/1000000-$B$13)*$B$22-$B$16-$B$14)*(1-$B$17)*1000/$B$18)-(((($B$8*($A55-$B$10)-$B$11*$B$8*$A55)*C$54/1000000-$B$13)*$B$15-$B$16-$B$14)*(1-$B$17)*1000/$B$18))*((1+$B$23)/(1+$B$19))^$B$21 -> 929.82383 | D55: =(((($B$8*($A55-$B$10)-$B$11*$B$8*$A55)*D$54/1000000-$B$13)*$B$15-$B$16-$B$14)*(1-$B$17)*1000/$B$18)+$B$20*((((($B$8*($A55-$B$10)-$B$11*$B$8*$A55)*D$54/1000000-$B$13)*$B$22-$B$16-$B$14)*(1-$B$17)*1000/$B$18)-(((($B$8*($A55-$B$10)-$B$11*$B$8*$A55)*D$54/1000000-$B$13)*$B$15-$B$16-$B$14)*(1-$B$17)*1000/$B$18))*((1+$B$23)/(1+$B$19))^$B$21 -> 1014.6648 | E55: =(((($B$8*($A55-$B$10)-$B$11*$B$8*$A55)*E$54/1000000-$B$13)*$B$15-$B$16-$B$14)*(1-$B$17)*1000/$B$18)+$B$20*((((($B$8*($A55-$B$10)-$B$11*$B$8*$A55)*E$54/1000000-$B$13)*$B$22-$B$16-$B$14)*(1-$B$17)*1000/$B$18)-(((($B$8*($A55-$B$10)-$B$11*$B$8*$A55)*E$54/1000000-$B$13)*$B$15-$B$16-$B$14)*(1-$B$17)*1000/$B$18))*((1+$B$23)/(1+$B$19))^$B$21 -> 1099.5058 | F55: =(((($B$8*($A55-$B$10)-$B$11*$B$8*$A55)*F$54/1000000-$B$13)*$B$15-$B$16-$B$14)*(1-$B$17)*1000/$B$18)+$B$20*((((($B$8*($A55-$B$10)-$B$11*$B$8*$A55)*F$54/1000000-$B$13)*$B$22-$B$16-$B$14)*(1-$B$17)*1000/$B$18)-(((($B$8*($A55-$B$10)-$B$11*$B$8*$A55)*F$54/1000000-$B$13)*$B$15-$B$16-$B$14)*(1-$B$17)*1000/$B$18))*((1+$B$23)/(1+$B$19))^$B$21 -> 1184.3467
A56: 3400 | B56: =(((($B$8*($A56-$B$10)-$B$11*$B$8*$A56)*B$54/1000000-$B$13)*$B$15-$B$16-$B$14)*(1-$B$17)*1000/$B$18)+$B$20*((((($B$8*($A56-$B$10)-$B$11*$B$8*$A56)*B$54/1000000-$B$13)*$B$22-$B$16-$B$14)*(1-$B$17)*1000/$B$18)-(((($B$8*($A56-$B$10)-$B$11*$B$8*$A56)*B$54/1000000-$B$13)*$B$15-$B$16-$B$14)*(1-$B$17)*1000/$B$18))*((1+$B$23)/(1+$B$19))^$B$21 -> 1107.8966 | C56: =(((($B$8*($A56-$B$10)-$B$11*$B$8*$A56)*C$54/1000000-$B$13)*$B$15-$B$16-$B$14)*(1-$B$17)*1000/$B$18)+$B$20*((((($B$8*($A56-$B$10)-$B$11*$B$8*$A56)*C$54/1000000-$B$13)*$B$22-$B$16-$B$14)*(1-$B$17)*1000/$B$18)-(((($B$8*($A56-$B$10)-$B$11*$B$8*$A56)*C$54/1000000-$B$13)*$B$15-$B$16-$B$14)*(1-$B$17)*1000/$B$18))*((1+$B$23)/(1+$B$19))^$B$21 -> 1210.2652 | D56: =(((($B$8*($A56-$B$10)-$B$11*$B$8*$A56)*D$54/1000000-$B$13)*$B$15-$B$16-$B$14)*(1-$B$17)*1000/$B$18)+$B$20*((((($B$8*($A56-$B$10)-$B$11*$B$8*$A56)*D$54/1000000-$B$13)*$B$22-$B$16-$B$14)*(1-$B$17)*1000/$B$18)-(((($B$8*($A56-$B$10)-$B$11*$B$8*$A56)*D$54/1000000-$B$13)*$B$15-$B$16-$B$14)*(1-$B$17)*1000/$B$18))*((1+$B$23)/(1+$B$19))^$B$21 -> 1312.6337 | E56: =(((($B$8*($A56-$B$10)-$B$11*$B$8*$A56)*E$54/1000000-$B$13)*$B$15-$B$16-$B$14)*(1-$B$17)*1000/$B$18)+$B$20*((((($B$8*($A56-$B$10)-$B$11*$B$8*$A56)*E$54/1000000-$B$13)*$B$22-$B$16-$B$14)*(1-$B$17)*1000/$B$18)-(((($B$8*($A56-$B$10)-$B$11*$B$8*$A56)*E$54/1000000-$B$13)*$B$15-$B$16-$B$14)*(1-$B$17)*1000/$B$18))*((1+$B$23)/(1+$B$19))^$B$21 -> 1415.0023 | F56: =(((($B$8*($A56-$B$10)-$B$11*$B$8*$A56)*F$54/1000000-$B$13)*$B$15-$B$16-$B$14)*(1-$B$17)*1000/$B$18)+$B$20*((((($B$8*($A56-$B$10)-$B$11*$B$8*$A56)*F$54/1000000-$B$13)*$B$22-$B$16-$B$14)*(1-$B$17)*1000/$B$18)-(((($B$8*($A56-$B$10)-$B$11*$B$8*$A56)*F$54/1000000-$B$13)*$B$15-$B$16-$B$14)*(1-$B$17)*1000/$B$18))*((1+$B$23)/(1+$B$19))^$B$21 -> 1517.3708
A57: 3800 | B57: =(((($B$8*($A57-$B$10)-$B$11*$B$8*$A57)*B$54/1000000-$B$13)*$B$15-$B$16-$B$14)*(1-$B$17)*1000/$B$18)+$B$20*((((($B$8*($A57-$B$10)-$B$11*$B$8*$A57)*B$54/1000000-$B$13)*$B$22-$B$16-$B$14)*(1-$B$17)*1000/$B$18)-(((($B$8*($A57-$B$10)-$B$11*$B$8*$A57)*B$54/1000000-$B$13)*$B$15-$B$16-$B$14)*(1-$B$17)*1000/$B$18))*((1+$B$23)/(1+$B$19))^$B$21 -> 1370.8104 | C57: =(((($B$8*($A57-$B$10)-$B$11*$B$8*$A57)*C$54/1000000-$B$13)*$B$15-$B$16-$B$14)*(1-$B$17)*1000/$B$18)+$B$20*((((($B$8*($A57-$B$10)-$B$11*$B$8*$A57)*C$54/1000000-$B$13)*$B$22-$B$16-$B$14)*(1-$B$17)*1000/$B$18)-(((($B$8*($A57-$B$10)-$B$11*$B$8*$A57)*C$54/1000000-$B$13)*$B$15-$B$16-$B$14)*(1-$B$17)*1000/$B$18))*((1+$B$23)/(1+$B$19))^$B$21 -> 1490.7065 | D57: =(((($B$8*($A57-$B$10)-$B$11*$B$8*$A57)*D$54/1000000-$B$13)*$B$15-$B$16-$B$14)*(1-$B$17)*1000/$B$18)+$B$20*((((($B$8*($A57-$B$10)-$B$11*$B$8*$A57)*D$54/1000000-$B$13)*$B$22-$B$16-$B$14)*(1-$B$17)*1000/$B$18)-(((($B$8*($A57-$B$10)-$B$11*$B$8*$A57)*D$54/1000000-$B$13)*$B$15-$B$16-$B$14)*(1-$B$17)*1000/$B$18))*((1+$B$23)/(1+$B$19))^$B$21 -> 1610.6026 | E57: =(((($B$8*($A57-$B$10)-$B$11*$B$8*$A57)*E$54/1000000-$B$13)*$B$15-$B$16-$B$14)*(1-$B$17)*1000/$B$18)+$B$20*((((($B$8*($A57-$B$10)-$B$11*$B$8*$A57)*E$54/1000000-$B$13)*$B$22-$B$16-$B$14)*(1-$B$17)*1000/$B$18)-(((($B$8*($A57-$B$10)-$B$11*$B$8*$A57)*E$54/1000000-$B$13)*$B$15-$B$16-$B$14)*(1-$B$17)*1000/$B$18))*((1+$B$23)/(1+$B$19))^$B$21 -> 1730.4988 | F57: =(((($B$8*($A57-$B$10)-$B$11*$B$8*$A57)*F$54/1000000-$B$13)*$B$15-$B$16-$B$14)*(1-$B$17)*1000/$B$18)+$B$20*((((($B$8*($A57-$B$10)-$B$11*$B$8*$A57)*F$54/1000000-$B$13)*$B$22-$B$16-$B$14)*(1-$B$17)*1000/$B$18)-(((($B$8*($A57-$B$10)-$B$11*$B$8*$A57)*F$54/1000000-$B$13)*$B$15-$B$16-$B$14)*(1-$B$17)*1000/$B$18))*((1+$B$23)/(1+$B$19))^$B$21 -> 1850.3949
A58: 4200 | B58: =(((($B$8*($A58-$B$10)-$B$11*$B$8*$A58)*B$54/1000000-$B$13)*$B$15-$B$16-$B$14)*(1-$B$17)*1000/$B$18)+$B$20*((((($B$8*($A58-$B$10)-$B$11*$B$8*$A58)*B$54/1000000-$B$13)*$B$22-$B$16-$B$14)*(1-$B$17)*1000/$B$18)-(((($B$8*($A58-$B$10)-$B$11*$B$8*$A58)*B$54/1000000-$B$13)*$B$15-$B$16-$B$14)*(1-$B$17)*1000/$B$18))*((1+$B$23)/(1+$B$19))^$B$21 -> 1633.7241 | C58: =(((($B$8*($A58-$B$10)-$B$11*$B$8*$A58)*C$54/1000000-$B$13)*$B$15-$B$16-$B$14)*(1-$B$17)*1000/$B$18)+$B$20*((((($B$8*($A58-$B$10)-$B$11*$B$8*$A58)*C$54/1000000-$B$13)*$B$22-$B$16-$B$14)*(1-$B$17)*1000/$B$18)-(((($B$8*($A58-$B$10)-$B$11*$B$8*$A58)*C$54/1000000-$B$13)*$B$15-$B$16-$B$14)*(1-$B$17)*1000/$B$18))*((1+$B$23)/(1+$B$19))^$B$21 -> 1771.1478 | D58: =(((($B$8*($A58-$B$10)-$B$11*$B$8*$A58)*D$54/1000000-$B$13)*$B$15-$B$16-$B$14)*(1-$B$17)*1000/$B$18)+$B$20*((((($B$8*($A58-$B$10)-$B$11*$B$8*$A58)*D$54/1000000-$B$13)*$B$22-$B$16-$B$14)*(1-$B$17)*1000/$B$18)-(((($B$8*($A58-$B$10)-$B$11*$B$8*$A58)*D$54/1000000-$B$13)*$B$15-$B$16-$B$14)*(1-$B$17)*1000/$B$18))*((1+$B$23)/(1+$B$19))^$B$21 -> 1908.5716 | E58: =(((($B$8*($A58-$B$10)-$B$11*$B$8*$A58)*E$54/1000000-$B$13)*$B$15-$B$16-$B$14)*(1-$B$17)*1000/$B$18)+$B$20*((((($B$8*($A58-$B$10)-$B$11*$B$8*$A58)*E$54/1000000-$B$13)*$B$22-$B$16-$B$14)*(1-$B$17)*1000/$B$18)-(((($B$8*($A58-$B$10)-$B$11*$B$8*$A58)*E$54/1000000-$B$13)*$B$15-$B$16-$B$14)*(1-$B$17)*1000/$B$18))*((1+$B$23)/(1+$B$19))^$B$21 -> 2045.9953 | F58: =(((($B$8*($A58-$B$10)-$B$11*$B$8*$A58)*F$54/1000000-$B$13)*$B$15-$B$16-$B$14)*(1-$B$17)*1000/$B$18)+$B$20*((((($B$8*($A58-$B$10)-$B$11*$B$8*$A58)*F$54/1000000-$B$13)*$B$22-$B$16-$B$14)*(1-$B$17)*1000/$B$18)-(((($B$8*($A58-$B$10)-$B$11*$B$8*$A58)*F$54/1000000-$B$13)*$B$15-$B$16-$B$14)*(1-$B$17)*1000/$B$18))*((1+$B$23)/(1+$B$19))^$B$21 -> 2183.419
A59: 4600 | B59: =(((($B$8*($A59-$B$10)-$B$11*$B$8*$A59)*B$54/1000000-$B$13)*$B$15-$B$16-$B$14)*(1-$B$17)*1000/$B$18)+$B$20*((((($B$8*($A59-$B$10)-$B$11*$B$8*$A59)*B$54/1000000-$B$13)*$B$22-$B$16-$B$14)*(1-$B$17)*1000/$B$18)-(((($B$8*($A59-$B$10)-$B$11*$B$8*$A59)*B$54/1000000-$B$13)*$B$15-$B$16-$B$14)*(1-$B$17)*1000/$B$18))*((1+$B$23)/(1+$B$19))^$B$21 -> 1896.6379 | C59: =(((($B$8*($A59-$B$10)-$B$11*$B$8*$A59)*C$54/1000000-$B$13)*$B$15-$B$16-$B$14)*(1-$B$17)*1000/$B$18)+$B$20*((((($B$8*($A59-$B$10)-$B$11*$B$8*$A59)*C$54/1000000-$B$13)*$B$22-$B$16-$B$14)*(1-$B$17)*1000/$B$18)-(((($B$8*($A59-$B$10)-$B$11*$B$8*$A59)*C$54/1000000-$B$13)*$B$15-$B$16-$B$14)*(1-$B$17)*1000/$B$18))*((1+$B$23)/(1+$B$19))^$B$21 -> 2051.5892 | D59: =(((($B$8*($A59-$B$10)-$B$11*$B$8*$A59)*D$54/1000000-$B$13)*$B$15-$B$16-$B$14)*(1-$B$17)*1000/$B$18)+$B$20*((((($B$8*($A59-$B$10)-$B$11*$B$8*$A59)*D$54/1000000-$B$13)*$B$22-$B$16-$B$14)*(1-$B$17)*1000/$B$18)-(((($B$8*($A59-$B$10)-$B$11*$B$8*$A59)*D$54/1000000-$B$13)*$B$15-$B$16-$B$14)*(1-$B$17)*1000/$B$18))*((1+$B$23)/(1+$B$19))^$B$21 -> 2206.5405 | E59: =(((($B$8*($A59-$B$10)-$B$11*$B$8*$A59)*E$54/1000000-$B$13)*$B$15-$B$16-$B$14)*(1-$B$17)*1000/$B$18)+$B$20*((((($B$8*($A59-$B$10)-$B$11*$B$8*$A59)*E$54/1000000-$B$13)*$B$22-$B$16-$B$14)*(1-$B$17)*1000/$B$18)-(((($B$8*($A59-$B$10)-$B$11*$B$8*$A59)*E$54/1000000-$B$13)*$B$15-$B$16-$B$14)*(1-$B$17)*1000/$B$18))*((1+$B$23)/(1+$B$19))^$B$21 -> 2361.4918 | F59: =(((($B$8*($A59-$B$10)-$B$11*$B$8*$A59)*F$54/1000000-$B$13)*$B$15-$B$16-$B$14)*(1-$B$17)*1000/$B$18)+$B$20*((((($B$8*($A59-$B$10)-$B$11*$B$8*$A59)*F$54/1000000-$B$13)*$B$22-$B$16-$B$14)*(1-$B$17)*1000/$B$18)-(((($B$8*($A59-$B$10)-$B$11*$B$8*$A59)*F$54/1000000-$B$13)*$B$15-$B$16-$B$14)*(1-$B$17)*1000/$B$18))*((1+$B$23)/(1+$B$19))^$B$21 -> 2516.4431
A60: Центр таблицы (жёлтая ячейка) = базовый сценарий; должен совпадать со справедливой ценой.
A62: ТЕЗИС И УСЛОВИЯ ЕГО СЛОМА (сигнал при любой цене)
A63: Тезис: Самый дешёвый крупный производитель золота в мире, Сухой Лог к 2030 удвоит добычу. Защита портфеля от ослабления рубля и обесценения денег. Но в 2026 кейс испорчен: дивиденды заморожены до 2030, отчётность урезана, золото откатилось от январского пика, растут налоги — отсюда −54% с начала года.
A64: • Формальная отмена дивполитики или оферта/выкуп миноритариев ниже справедливой цены
A65: • Запуск Сухого Лога сдвигается за 2030 год
A66: • TCC выше $1 300/унц при золоте ниже $4 000
A67: • Постоянное повышение налогов (НДПИ) больше 30 млрд ₽ в год или ЧД/EBITDA выше 2,5x
A69: ЧТО ОТСЛЕЖИВАЕТ БОТ В НОВОСТЯХ
A70: • Цена золота и курс рубля (меняйте на листе «Параметры»)
A71: • Налог на сверхдоходы горняков и НДПИ на золото: итоговые ставки
A72: • Операционные результаты за 9М 2026 и годовая МСФО (ожидается 05.03.2027)
A73: • Любые решения по дивидендам и структуре акционеров
... A81: investmint — дивиденды и новости: https://investmint.ru/plzl/divs/

Sheet POSI
A1: POSI — Группа Позитив: модель справедливой стоимости
A2: Метод: P/E на прогноз скорректированной прибыли (NIC) 2027 года
A3: Positive платит дивиденды из NIC — чистой прибыли с поправкой на капитализированные расходы. Стоимость = NIC 2027 × справедливый P/E / число акций. NIC строим от оплаченных отгрузок — главного показателя компании.
A4: Синий — вводные (меняйте их), чёрный — формулы, зелёный — ссылки на другие листы, жёлтый — главные рычаги модели.
A6: Показатель | B6: Значение | C6: Ед. | D6: Источник / комментарий
A7: ВВОДНЫЕ
A8: Оплаченные отгрузки 2026П | B8: 41 | C8: млрд ₽ | D8: Гайденс 40–45 млрд (подтверждён 27.07 и 16.10.2026); 1П: 10,7 млрд (+45%), прогноз 3К 6,75 млрд → на 4 кв. для 41 млрд нужно 23,6 млрд (57% года; в 2025 было ~65%). Берём нижнюю половину: в 2025 предварительные 35 млрд стали 33,6.
A9: Рост отгрузок 2027 | B9: 0.2 | C9: % | D9: Рынок ИБ растёт в 3–4 раза быстрее ИТ; воронка продаж >60 млрд ₽ (июль 2026). Берём 20% — ниже роста 2025 (+40%).
A10: Маржа NIC к отгрузкам | B10: 0.2 | C10: % | D10: 2025: 8% (2,7 / 33,6 млрд); цель компании — приблизиться к 30%; расходы 2026 заморожены на уровне 2025. Берём 20%.
A11: Справедливый P/E | B11: 10 | C11: x | D11: Требуемая доходность 19% и выплата 50–100% NIC дают ~8x для зрелого бизнеса; +2x за рост 20% в ближайшие годы.
A12: Акций в обращении | B12: 71.214 | C12: млн шт | D12: Сверка: дивиденд 1 999,7 млн ₽ / 28,08 ₽ = 71,214 млн акций; × 1176 ₽ = 83,8 млрд ₽.
A13: Чистый долг (для проверки) | B13: 12.5 | C13: млрд ₽ | D13: На 30.06.2026, ЧД/EBITDA LTM 0,8x (год назад 2,33x); весь долг — облигации.
A14: Ставка дисконтирования | B14: =Параметры!$B$9 -> 0.19 | C14: % | D14: Из «Параметров».
A15: Мир: вероятность мира и снятия санкций | B15: =Параметры!$B$15 -> 0.5 | C15: % | D15: Из «Параметров».
A16: Мир: лет до снятия санкций | B16: =Параметры!$B$16 -> 5 | C16: лет | D16: Из «Параметров».
A17: Мир: P/E после снятия санкций | B17: 15 | C17: x | D17: До 2022 российские IT-компании стоили 20–30x прибыли, мировые лидеры кибербезопасности — 40x+. Берём 15x: после снятия санкций могут вернуться иностранные вендоры.
A18: Мир: рост показателя до года мира, % в год | B18: 0.15 | C18: % | D18: Рост отгрузок и NIC в среднем за 5 лет.
A20: РАСЧЁТ
A21: Оплаченные отгрузки 2027П | B21: =$B$8*(1+$B$9) -> 49.2 | C21: млрд ₽
A22: NIC 2027П | B22: =$B$21*$B$10 -> 9.84 | C22: млрд ₽
A23: Стоимость акционерного капитала | B23: =$B$22*$B$11 -> 98.4 | C23: млрд ₽
A24: Справедливая цена без мира | B24: =IF($B$12>0,$B$23*1000/$B$12,0) -> 1381.7508 | C24: ₽
A25: Мир: цена в мирном режиме на сегодняшних показателях | B25: =$B$8*(1+$B$9)*$B$10*$B$17*1000/$B$12 -> 2072.6262 | C25: ₽ | D25: Если бы рынок уже сегодня оценивал компанию как до 2022 года.
A26: Мир: прибавка к цене сегодня | B26: =$B$15*($B$25-$B$24)*((1+$B$18)/(1+$B$14))^$B$16 -> 291.15491 | C26: ₽ | D26: Вероятность × разница цен × рост показателя до года мира, приведённый к сегодняшнему дню.
A27: Справедливая цена с миром | B27: =$B$24+$B$26 -> 1672.9057 | C27: ₽
A29: РЕЗУЛЬТАТ
A30: Справедливая цена | B30: =$B$27 -> 1672.9057 | C30: ₽ | D30: Главный вывод модели
A31: Текущая цена | B31: =Сводка!$D$7 -> 1176.8 | C31: ₽ | D31: Берётся со «Сводки» (столбец D)
A32: Зона покупки: цена не выше | B32: =$B$30*(1-Параметры!$B$10) -> 1288.1374 | C32: ₽ | D32: Справедливая минус скидка из «Параметров»
A33: Цена продажи | B33: =$B$30*(1+Параметры!$B$11) -> 1974.0287 | C33: ₽ | D33: Справедливая плюс премия из «Параметров»
A34: Сигнал «приближается к продаже» от | B34: =$B$33*(1-Параметры!$B$12) -> 1875.3273 | C34: ₽ | D34: За сколько % до цены продажи бот предупреждает
A35: Потенциал до справедливой | B35: =IF($B$31>0,$B$30/$B$31-1,0) -> 0.4215718 | C35: %
A36: До цены продажи | B36: =IF($B$31>0,$B$33/$B$31-1,0) -> 0.67745472 | C36: %
A37: Статус | B37: =IF($B$31<=$B$32,"ЗОНА ПОКУПКИ",IF($B$31>=$B$33,"ЦЕНА ПРОДАЖИ",IF($B$31>=$B$34,"ПРИБЛИЖАЕТСЯ К ПРОДАЖЕ","ДЕРЖАТЬ"))) -> ЗОНА ПОКУПКИ | D37: Слом тезиса — отдельный сигнал, см. ниже
A39: ПЕРЕКРЁСТНАЯ ПРОВЕРКА
A40: P/E на NIC 2027П при текущей цене | B40: =IF($B$22>0,$B$31*$B$12/1000/$B$22,0) -> 8.5167312 | C40: x
A41: Потенциальный дивиденд за 2027 (50% NIC) | B41: =$B$22*0.5*1000/$B$12 -> 69.087539 | C41: ₽ | D41: Политика: 50–100% NIC при ЧД/EBITDA ≤ 2,5x.
A42: Медиана целей 6 брокеров | B42: =1475 -> 1475 | C42: ₽ | D42: 1300–2000 ₽: Эйлер 2000, Альфа 1990, ПСБ 1550, Freedom 1400, Сбер CIB 1350, Т-Инвестиции ~1300.
A44: ЧУВСТВИТЕЛЬНОСТЬ СПРАВЕДЛИВОЙ ЦЕНЫ, ₽: строки — P/E, столбцы — маржа NIC
A45: P/E \ маржа NIC | B45: 0.12 | C45: 0.16 | D45: 0.2 | E45: 0.24 | F45: 0.28
A46: 8 | B46: =($B$8*(1+$B$9)*B$45*$A46*1000/$B$12)+$B$15*(($B$8*(1+$B$9)*B$45*$B$17*1000/$B$12)-($B$8*(1+$B$9)*B$45*$A46*1000/$B$12))*((1+$B$18)/(1+$B$14))^$B$16 -> 907.8105 | C46: =($B$8*(1+$B$9)*C$45*$A46*1000/$B$12)+$B$15*(($B$8*(1+$B$9)*C$45*$B$17*1000/$B$12)-($B$8*(1+$B$9)*C$45*$A46*1000/$B$12))*((1+$B$18)/(1+$B$14))^$B$16 -> 1210.414 | D46: =($B$8*(1+$B$9)*D$45*$A46*1000/$B$12)+$B$15*(($B$8*(1+$B$9)*D$45*$B$17*1000/$B$12)-($B$8*(1+$B$9)*D$45*$A46*1000/$B$12))*((1+$B$18)/(1+$B$14))^$B$16 -> 1513.0175 | E46: =($B$8*(1+$B$9)*E$45*$A46*1000/$B$12)+$B$15*(($B$8*(1+$B$9)*E$45*$B$17*1000/$B$12)-($B$8*(1+$B$9)*E$45*$A46*1000/$B$12))*((1+$B$18)/(1+$B$14))^$B$16 -> 1815.621 | F46: =($B$8*(1+$B$9)*F$45*$A46*1000/$B$12)+$B$15*(($B$8*(1+$B$9)*F$45*$B$17*1000/$B$12)-($B$8*(1+$B$9)*F$45*$A46*1000/$B$12))*((1+$B$18)/(1+$B$14))^$B$16 -> 2118.2245
A47: 9 | B47: =($B$8*(1+$B$9)*B$45*$A47*1000/$B$12)+$B$15*(($B$8*(1+$B$9)*B$45*$B$17*1000/$B$12)-($B$8*(1+$B$9)*B$45*$A47*1000/$B$12))*((1+$B$18)/(1+$B$14))^$B$16 -> 955.77696 | C47: =($B$8*(1+$B$9)*C$45*$A47*1000/$B$12)+$B$15*(($B$8*(1+$B$9)*C$45*$B$17*1000/$B$12)-($B$8*(1+$B$9)*C$45*$A47*1000/$B$12))*((1+$B$18)/(1+$B$14))^$B$16 -> 1274.3693 | D47: =($B$8*(1+$B$9)*D$45*$A47*1000/$B$12)+$B$15*(($B$8*(1+$B$9)*D$45*$B$17*1000/$B$12)-($B$8*(1+$B$9)*D$45*$A47*1000/$B$12))*((1+$B$18)/(1+$B$14))^$B$16 -> 1592.9616 | E47: =($B$8*(1+$B$9)*E$45*$A47*1000/$B$12)+$B$15*(($B$8*(1+$B$9)*E$45*$B$17*1000/$B$12)-($B$8*(1+$B$9)*E$45*$A47*1000/$B$12))*((1+$B$18)/(1+$B$14))^$B$16 -> 1911.5539 | F47: =($B$8*(1+$B$9)*F$45*$A47*1000/$B$12)+$B$15*(($B$8*(1+$B$9)*F$45*$B$17*1000/$B$12)-($B$8*(1+$B$9)*F$45*$A47*1000/$B$12))*((1+$B$18)/(1+$B$14))^$B$16 -> 2230.1462
A48: 10 | B48: =($B$8*(1+$B$9)*B$45*$A48*1000/$B$12)+$B$15*(($B$8*(1+$B$9)*B$45*$B$17*1000/$B$12)-($B$8*(1+$B$9)*B$45*$A48*1000/$B$12))*((1+$B$18)/(1+$B$14))^$B$16 -> 1003.7434 | C48: =($B$8*(1+$B$9)*C$45*$A48*1000/$B$12)+$B$15*(($B$8*(1+$B$9)*C$45*$B$17*1000/$B$12)-($B$8*(1+$B$9)*C$45*$A48*1000/$B$12))*((1+$B$18)/(1+$B$14))^$B$16 -> 1338.3246 | D48: =($B$8*(1+$B$9)*D$45*$A48*1000/$B$12)+$B$15*(($B$8*(1+$B$9)*D$45*$B$17*1000/$B$12)-($B$8*(1+$B$9)*D$45*$A48*1000/$B$12))*((1+$B$18)/(1+$B$14))^$B$16 -> 1672.9057 | E48: =($B$8*(1+$B$9)*E$45*$A48*1000/$B$12)+$B$15*(($B$8*(1+$B$9)*E$45*$B$17*1000/$B$12)-($B$8*(1+$B$9)*E$45*$A48*1000/$B$12))*((1+$B$18)/(1+$B$14))^$B$16 -> 2007.4868 | F48: =($B$8*(1+$B$9)*F$45*$A48*1000/$B$12)+$B$15*(($B$8*(1+$B$9)*F$45*$B$17*1000/$B$12)-($B$8*(1+$B$9)*F$45*$A48*1000/$B$12))*((1+$B$18)/(1+$B$14))^$B$16 -> 2342.068
A49: 11 | B49: =($B$8*(1+$B$9)*B$45*$A49*1000/$B$12)+$B$15*(($B$8*(1+$B$9)*B$45*$B$17*1000/$B$12)-($B$8*(1+$B$9)*B$45*$A49*1000/$B$12))*((1+$B$18)/(1+$B$14))^$B$16 -> 1051.7099 | C49: =($B$8*(1+$B$9)*C$45*$A49*1000/$B$12)+$B$15*(($B$8*(1+$B$9)*C$45*$B$17*1000/$B$12)-($B$8*(1+$B$9)*C$45*$A49*1000/$B$12))*((1+$B$18)/(1+$B$14))^$B$16 -> 1402.2798 | D49: =($B$8*(1+$B$9)*D$45*$A49*1000/$B$12)+$B$15*(($B$8*(1+$B$9)*D$45*$B$17*1000/$B$12)-($B$8*(1+$B$9)*D$45*$A49*1000/$B$12))*((1+$B$18)/(1+$B$14))^$B$16 -> 1752.8498 | E49: =($B$8*(1+$B$9)*E$45*$A49*1000/$B$12)+$B$15*(($B$8*(1+$B$9)*E$45*$B$17*1000/$B$12)-($B$8*(1+$B$9)*E$45*$A49*1000/$B$12))*((1+$B$18)/(1+$B$14))^$B$16 -> 2103.4197 | F49: =($B$8*(1+$B$9)*F$45*$A49*1000/$B$12)+$B$15*(($B$8*(1+$B$9)*F$45*$B$17*1000/$B$12)-($B$8*(1+$B$9)*F$45*$A49*1000/$B$12))*((1+$B$18)/(1+$B$14))^$B$16 -> 2453.9897
A50: 12 | B50: =($B$8*(1+$B$9)*B$45*$A50*1000/$B$12)+$B$15*(($B$8*(1+$B$9)*B$45*$B$17*1000/$B$12)-($B$8*(1+$B$9)*B$45*$A50*1000/$B$12))*((1+$B$18)/(1+$B$14))^$B$16 -> 1099.6763 | C50: =($B$8*(1+$B$9)*C$45*$A50*1000/$B$12)+$B$15*(($B$8*(1+$B$9)*C$45*$B$17*1000/$B$12)-($B$8*(1+$B$9)*C$45*$A50*1000/$B$12))*((1+$B$18)/(1+$B$14))^$B$16 -> 1466.2351 | D50: =($B$8*(1+$B$9)*D$45*$A50*1000/$B$12)+$B$15*(($B$8*(1+$B$9)*D$45*$B$17*1000/$B$12)-($B$8*(1+$B$9)*D$45*$A50*1000/$B$12))*((1+$B$18)/(1+$B$14))^$B$16 -> 1832.7939 | E50: =($B$8*(1+$B$9)*E$45*$A50*1000/$B$12)+$B$15*(($B$8*(1+$B$9)*E$45*$B$17*1000/$B$12)-($B$8*(1+$B$9)*E$45*$A50*1000/$B$12))*((1+$B$18)/(1+$B$14))^$B$16 -> 2199.3527 | F50: =($B$8*(1+$B$9)*F$45*$A50*1000/$B$12)+$B$15*(($B$8*(1+$B$9)*F$45*$B$17*1000/$B$12)-($B$8*(1+$B$9)*F$45*$A50*1000/$B$12))*((1+$B$18)/(1+$B$14))^$B$16 -> 2565.9114
A51: Центр таблицы (жёлтая ячейка) = базовый сценарий; должен совпадать со справедливой ценой.
A53: ТЕЗИС И УСЛОВИЯ ЕГО СЛОМА (сигнал при любой цене)
A54: Тезис: Лидер российской кибербезопасности (~17% рынка). Рынок ИБ растёт быстрее ИТ из‑за импортозамещения и атак, включая ИИ-угрозы. 2026 — год восстановления после провала 2024: расходы заморожены, долг упал до 0,8x EBITDA, отгрузки за 1П +45%. Если маржа NIC выйдет к 20%+, акция дешёвая.
A55: • Отгрузки 2026 ниже 38 млрд ₽ (второй срыв гайденса за три года)
A56: • NIC 2026 отрицательный
A57: • Новая допэмиссия (последняя была в 2024)
A58: • ЧД/EBITDA выше 2x или расходы растут быстрее отгрузок
A60: ЧТО ОТСЛЕЖИВАЕТ БОТ В НОВОСТЯХ
A61: • Отчёт за 9М 2026 (ожидается ~10.11.2026) и прогноз 3 квартала 6,75 млрд
A62: • Предварительные отгрузки за 2026 год (февраль 2027) — ключевая проверка
A63: • Дивидендная рекомендация весной 2027
A64: • Сделки M&A (CyberOK) и новые выпуски облигаций
... A72: investmint — цели аналитиков и новости: https://investmint.ru/posi/

Sheet PRMD
A1: PRMD — Промомед: модель справедливой стоимости
A2: Метод: EV/EBITDA на прогноз 2027 года
A3: Компания роста без значимых дивидендов: стоимость бизнеса = EBITDA 2027 × справедливый мультипликатор, минус чистый долг, делим на число акций. Проверка — P/E при справедливой цене и сравнение с консенсусом аналитиков.
A4: Синий — вводные (меняйте их), чёрный — формулы, зелёный — ссылки на другие листы, жёлтый — главные рычаги модели.
A6: Показатель | B6: Значение | C6: Ед. | D6: Источник / комментарий
A7: ВВОДНЫЕ
A8: Выручка 2026П | B8: 60.2 | C8: млрд ₽ | D8: Гайденс: рост не ниже 60% к 37,6 млрд за 2025 (подтверждён 31.08 и в октябре 2026). 1П 2026: 22,8 млрд (+76%). АТОН, Ведомости, ABN 06.10.2026.
A9: Рост выручки 2027 | B9: 0.35 | C9: % | D9: CFO ждёт ~40% в год в 2027–2029 (ABN, 06.10.2026). Берём 35%: тирзепатид в РФ не защищён патентом, на рынок выходят Герофарм и ПСК Фарма.
A10: Рентабельность EBITDA 2027 | B10: 0.4 | C10: % | D10: 2025: 41%; 1П 2026: 34%; гайденс 2026 ~45%. Берём середину 40%.
A11: Справедливый EV/EBITDA | B11: 5 | C11: x | D11: Сейчас рынок даёт ~3,7x на 2027П. 5x — умеренная оценка для роста 35%+ с дисконтом за концентрацию на одном препарате и free-float 8,5%.
A12: Чистый долг на конец 2026П | B12: 38.3 | C12: млрд ₽ | D12: 30.06.2026: 33,3 млрд, ЧД/EBITDA 1,79x (АТОН); FCF 1П ≈ −5 млрд (Т-Инвестиции), во 2П ждём столько же → ~38 млрд к концу года. Положительный FCF компания ждёт в 2027.
A13: Акций в обращении | B13: 212.5 | C13: млн шт | D13: 212,5 млн обыкн. акций (investfunds); 212,5 × 407 ₽ = 86,5 млрд ₽ капитализации.
A14: Чистая рентабельность 2027 (для проверки) | B14: 0.16 | C14: % | D14: 2025: 19% (7,2 / 37,6 млрд); 1П 2026: 11% из‑за процентов. Берём 16%.
A15: Ставка дисконтирования | B15: =Параметры!$B$9 -> 0.19 | C15: % | D15: Из «Параметров».
A16: Мир: вероятность мира и снятия санкций | B16: =Параметры!$B$15 -> 0.5 | C16: % | D16: Из «Параметров».
A17: Мир: лет до снятия санкций | B17: =Параметры!$B$16 -> 5 | C17: лет | D17: Из «Параметров».
A18: Мир: EV/EBITDA после снятия санкций | B18: 7 | C18: x | D18: Мировые производители дженериков ~8–10x EBITDA; истории до 2022 нет (IPO 2024). Берём 7x.
A19: Мир: рост показателя до года мира, % в год | B19: 0.15 | C19: % | D19: Рост 35%+ не продлится 5 лет; берём 15% в среднем.
A21: РАСЧЁТ
A22: Выручка 2027П | B22: =$B$8*(1+$B$9) -> 81.27 | C22: млрд ₽
A23: EBITDA 2027П | B23: =$B$22*$B$10 -> 32.508 | C23: млрд ₽
A24: Справедливая стоимость бизнеса (EV) | B24: =$B$23*$B$11 -> 162.54 | C24: млрд ₽
A25: Стоимость акционерного капитала | B25: =$B$24-$B$12 -> 124.24 | C25: млрд ₽
A26: Справедливая цена без мира | B26: =IF($B$13>0,$B$25*1000/$B$13,0) -> 584.65882 | C26: ₽
A27: Мир: цена в мирном режиме на сегодняшних показателях | B27: =($B$8*(1+$B$9)*$B$10*$B$18-$B$12)*1000/$B$13 -> 890.61647 | C27: ₽ | D27: Если бы рынок уже сегодня оценивал компанию как до 2022 года.
A28: Мир: прибавка к цене сегодня | B28: =$B$16*($B$27-$B$26)*((1+$B$19)/(1+$B$15))^$B$17 -> 128.93942 | C28: ₽ | D28: Вероятность × разница цен × рост показателя до года мира, приведённый к сегодняшнему дню.
A29: Справедливая цена с миром | B29: =$B$26+$B$28 -> 713.59824 | C29: ₽
A31: РЕЗУЛЬТАТ
A32: Справедливая цена | B32: =$B$29 -> 713.59824 | C32: ₽ | D32: Главный вывод модели
A33: Текущая цена | B33: =Сводка!$D$8 -> 407 | C33: ₽ | D33: Берётся со «Сводки» (столбец D)
A34: Зона покупки: цена не выше | B34: =$B$32*(1-Параметры!$B$10) -> 549.47065 | C34: ₽ | D34: Справедливая минус скидка из «Параметров»
A35: Цена продажи | B35: =$B$32*(1+Параметры!$B$11) -> 842.04593 | C35: ₽ | D35: Справедливая плюс премия из «Параметров»
A36: Сигнал «приближается к продаже» от | B36: =$B$35*(1-Параметры!$B$12) -> 799.94363 | C36: ₽ | D36: За сколько % до цены продажи бот предупреждает
A37: Потенциал до справедливой | B37: =IF($B$33>0,$B$32/$B$33-1,0) -> 0.75331264 | C37: %
A38: До цены продажи | B38: =IF($B$33>0,$B$35/$B$33-1,0) -> 1.0689089 | C38: %
A39: Статус | B39: =IF($B$33<=$B$34,"ЗОНА ПОКУПКИ",IF($B$33>=$B$35,"ЦЕНА ПРОДАЖИ",IF($B$33>=$B$36,"ПРИБЛИЖАЕТСЯ К ПРОДАЖЕ","ДЕРЖАТЬ"))) -> ЗОНА ПОКУПКИ | D39: Слом тезиса — отдельный сигнал, см. ниже
A41: ПЕРЕКРЁСТНАЯ ПРОВЕРКА
A42: Чистая прибыль 2027П | B42: =$B$22*$B$14 -> 13.0032 | C42: млрд ₽
A43: P/E 2027П при справедливой цене | B43: =IF($B$42>0,$B$32*$B$13/1000/$B$42,0) -> 11.661716 | C43: x | D43: Для роста 35% разумно 8–12x.
A44: EV/EBITDA 2027П при текущей цене | B44: =IF($B$23>0,($B$33*$B$13/1000+$B$12)/$B$23,0) -> 3.8386705 | C44: x
A45: Консенсус-цель аналитиков (6 домов) | B45: =657.87 -> 657.87 | C45: ₽ | D45: beststocks.ru, 23.10.2026: 600–730 ₽; Т-Инвестиции 640 ₽ (16.09.2026).
A47: ЧУВСТВИТЕЛЬНОСТЬ СПРАВЕДЛИВОЙ ЦЕНЫ, ₽: строки — EV/EBITDA, столбцы — рост выручки 2027
A48: EV/EBITDA \ рост выручки 2027 | B48: 0.2 | C48: 0.275 | D48: 0.35 | E48: 0.425 | F48: 0.5
A49: 4 | B49: =(($B$8*(1+B$48)*$B$10*$A49-$B$12)*1000/$B$13)+$B$16*((($B$8*(1+B$48)*$B$10*$B$18-$B$12)*1000/$B$13)-(($B$8*(1+B$48)*$B$10*$A49-$B$12)*1000/$B$13))*((1+$B$19)/(1+$B$15))^$B$17 -> 535.60864 | C49: =(($B$8*(1+C$48)*$B$10*$A49-$B$12)*1000/$B$13)+$B$16*((($B$8*(1+C$48)*$B$10*$B$18-$B$12)*1000/$B$13)-(($B$8*(1+C$48)*$B$10*$A49-$B$12)*1000/$B$13))*((1+$B$19)/(1+$B$15))^$B$17 -> 580.34888 | D49: =(($B$8*(1+D$48)*$B$10*$A49-$B$12)*1000/$B$13)+$B$16*((($B$8*(1+D$48)*$B$10*$B$18-$B$12)*1000/$B$13)-(($B$8*(1+D$48)*$B$10*$A49-$B$12)*1000/$B$13))*((1+$B$19)/(1+$B$15))^$B$17 -> 625.08913 | E49: =(($B$8*(1+E$48)*$B$10*$A49-$B$12)*1000/$B$13)+$B$16*((($B$8*(1+E$48)*$B$10*$B$18-$B$12)*1000/$B$13)-(($B$8*(1+E$48)*$B$10*$A49-$B$12)*1000/$B$13))*((1+$B$19)/(1+$B$15))^$B$17 -> 669.82938 | F49: =(($B$8*(1+F$48)*$B$10*$A49-$B$12)*1000/$B$13)+$B$16*((($B$8*(1+F$48)*$B$10*$B$18-$B$12)*1000/$B$13)-(($B$8*(1+F$48)*$B$10*$A49-$B$12)*1000/$B$13))*((1+$B$19)/(1+$B$15))^$B$17 -> 714.56962
A50: 4.5 | B50: =(($B$8*(1+B$48)*$B$10*$A50-$B$12)*1000/$B$13)+$B$16*((($B$8*(1+B$48)*$B$10*$B$18-$B$12)*1000/$B$13)-(($B$8*(1+B$48)*$B$10*$A50-$B$12)*1000/$B$13))*((1+$B$19)/(1+$B$15))^$B$17 -> 574.94602 | C50: =(($B$8*(1+C$48)*$B$10*$A50-$B$12)*1000/$B$13)+$B$16*((($B$8*(1+C$48)*$B$10*$B$18-$B$12)*1000/$B$13)-(($B$8*(1+C$48)*$B$10*$A50-$B$12)*1000/$B$13))*((1+$B$19)/(1+$B$15))^$B$17 -> 622.14485 | D50: =(($B$8*(1+D$48)*$B$10*$A50-$B$12)*1000/$B$13)+$B$16*((($B$8*(1+D$48)*$B$10*$B$18-$B$12)*1000/$B$13)-(($B$8*(1+D$48)*$B$10*$A50-$B$12)*1000/$B$13))*((1+$B$19)/(1+$B$15))^$B$17 -> 669.34369 | E50: =(($B$8*(1+E$48)*$B$10*$A50-$B$12)*1000/$B$13)+$B$16*((($B$8*(1+E$48)*$B$10*$B$18-$B$12)*1000/$B$13)-(($B$8*(1+E$48)*$B$10*$A50-$B$12)*1000/$B$13))*((1+$B$19)/(1+$B$15))^$B$17 -> 716.54252 | F50: =(($B$8*(1+F$48)*$B$10*$A50-$B$12)*1000/$B$13)+$B$16*((($B$8*(1+F$48)*$B$10*$B$18-$B$12)*1000/$B$13)-(($B$8*(1+F$48)*$B$10*$A50-$B$12)*1000/$B$13))*((1+$B$19)/(1+$B$15))^$B$17 -> 763.74135
A51: 5 | B51: =(($B$8*(1+B$48)*$B$10*$A51-$B$12)*1000/$B$13)+$B$16*((($B$8*(1+B$48)*$B$10*$B$18-$B$12)*1000/$B$13)-(($B$8*(1+B$48)*$B$10*$A51-$B$12)*1000/$B$13))*((1+$B$19)/(1+$B$15))^$B$17 -> 614.28341 | C51: =(($B$8*(1+C$48)*$B$10*$A51-$B$12)*1000/$B$13)+$B$16*((($B$8*(1+C$48)*$B$10*$B$18-$B$12)*1000/$B$13)-(($B$8*(1+C$48)*$B$10*$A51-$B$12)*1000/$B$13))*((1+$B$19)/(1+$B$15))^$B$17 -> 663.94082 | D51: =(($B$8*(1+D$48)*$B$10*$A51-$B$12)*1000/$B$13)+$B$16*((($B$8*(1+D$48)*$B$10*$B$18-$B$12)*1000/$B$13)-(($B$8*(1+D$48)*$B$10*$A51-$B$12)*1000/$B$13))*((1+$B$19)/(1+$B$15))^$B$17 -> 713.59824 | E51: =(($B$8*(1+E$48)*$B$10*$A51-$B$12)*1000/$B$13)+$B$16*((($B$8*(1+E$48)*$B$10*$B$18-$B$12)*1000/$B$13)-(($B$8*(1+E$48)*$B$10*$A51-$B$12)*1000/$B$13))*((1+$B$19)/(1+$B$15))^$B$17 -> 763.25566 | F51: =(($B$8*(1+F$48)*$B$10*$A51-$B$12)*1000/$B$13)+$B$16*((($B$8*(1+F$48)*$B$10*$B$18-$B$12)*1000/$B$13)-(($B$8*(1+F$48)*$B$10*$A51-$B$12)*1000/$B$13))*((1+$B$19)/(1+$B$15))^$B$17 -> 812.91308
A52: 5.5 | B52: =(($B$8*(1+B$48)*$B$10*$A52-$B$12)*1000/$B$13)+$B$16*((($B$8*(1+B$48)*$B$10*$B$18-$B$12)*1000/$B$13)-(($B$8*(1+B$48)*$B$10*$A52-$B$12)*1000/$B$13))*((1+$B$19)/(1+$B$15))^$B$17 -> 653.62079 | C52: =(($B$8*(1+C$48)*$B$10*$A52-$B$12)*1000/$B$13)+$B$16*((($B$8*(1+C$48)*$B$10*$B$18-$B$12)*1000/$B$13)-(($B$8*(1+C$48)*$B$10*$A52-$B$12)*1000/$B$13))*((1+$B$19)/(1+$B$15))^$B$17 -> 705.73679 | D52: =(($B$8*(1+D$48)*$B$10*$A52-$B$12)*1000/$B$13)+$B$16*((($B$8*(1+D$48)*$B$10*$B$18-$B$12)*1000/$B$13)-(($B$8*(1+D$48)*$B$10*$A52-$B$12)*1000/$B$13))*((1+$B$19)/(1+$B$15))^$B$17 -> 757.8528 | E52: =(($B$8*(1+E$48)*$B$10*$A52-$B$12)*1000/$B$13)+$B$16*((($B$8*(1+E$48)*$B$10*$B$18-$B$12)*1000/$B$13)-(($B$8*(1+E$48)*$B$10*$A52-$B$12)*1000/$B$13))*((1+$B$19)/(1+$B$15))^$B$17 -> 809.96881 | F52: =(($B$8*(1+F$48)*$B$10*$A52-$B$12)*1000/$B$13)+$B$16*((($B$8*(1+F$48)*$B$10*$B$18-$B$12)*1000/$B$13)-(($B$8*(1+F$48)*$B$10*$A52-$B$12)*1000/$B$13))*((1+$B$19)/(1+$B$15))^$B$17 -> 862.08481
A53: 6 | B53: =(($B$8*(1+B$48)*$B$10*$A53-$B$12)*1000/$B$13)+$B$16*((($B$8*(1+B$48)*$B$10*$B$18-$B$12)*1000/$B$13)-(($B$8*(1+B$48)*$B$10*$A53-$B$12)*1000/$B$13))*((1+$B$19)/(1+$B$15))^$B$17 -> 692.95817 | C53: =(($B$8*(1+C$48)*$B$10*$A53-$B$12)*1000/$B$13)+$B$16*((($B$8*(1+C$48)*$B$10*$B$18-$B$12)*1000/$B$13)-(($B$8*(1+C$48)*$B$10*$A53-$B$12)*1000/$B$13))*((1+$B$19)/(1+$B$15))^$B$17 -> 747.53277 | D53: =(($B$8*(1+D$48)*$B$10*$A53-$B$12)*1000/$B$13)+$B$16*((($B$8*(1+D$48)*$B$10*$B$18-$B$12)*1000/$B$13)-(($B$8*(1+D$48)*$B$10*$A53-$B$12)*1000/$B$13))*((1+$B$19)/(1+$B$15))^$B$17 -> 802.10736 | E53: =(($B$8*(1+E$48)*$B$10*$A53-$B$12)*1000/$B$13)+$B$16*((($B$8*(1+E$48)*$B$10*$B$18-$B$12)*1000/$B$13)-(($B$8*(1+E$48)*$B$10*$A53-$B$12)*1000/$B$13))*((1+$B$19)/(1+$B$15))^$B$17 -> 856.68195 | F53: =(($B$8*(1+F$48)*$B$10*$A53-$B$12)*1000/$B$13)+$B$16*((($B$8*(1+F$48)*$B$10*$B$18-$B$12)*1000/$B$13)-(($B$8*(1+F$48)*$B$10*$A53-$B$12)*1000/$B$13))*((1+$B$19)/(1+$B$15))^$B$17 -> 911.25654
A54: Центр таблицы (жёлтая ячейка) = базовый сценарий; должен совпадать со справедливой ценой.
A56: ТЕЗИС И УСЛОВИЯ ЕГО СЛОМА (сигнал при любой цене)
A57: Тезис: Лидер российского рынка препаратов от ожирения: доля 73% в тирзепатиде, 43% в семаглутиде; выручка растёт на 60%+ в 2026 и, по плану, ~40% в год до 2029. Второй двигатель — онкология (около 25 новых препаратов в 2027–2028). Рынок оценивает компанию дёшево из‑за долга и малого free-float.
A58: • Рост выручки 2027 ниже 20% или срыв гайденса 2026 (выручка ниже 55 млрд ₽)
A59: • Доля «Тирзетты» падает ниже 50% из‑за дженериков и ценовой войны
A60: • ЧД/EBITDA выше 2,5x (предел дивполитики и ковенант)
A61: • SPO или допэмиссия (менеджмент обещал не размещаться два года, июнь 2026)
A63: ЧТО ОТСЛЕЖИВАЕТ БОТ В НОВОСТЯХ
A64: • Отчёт за 9М 2026 (ожидается ~20.11.2026) → выручка и маржа
A65: • Ежемесячные продажи по DSM / RNC Pharma (доля в GLP‑1)
A66: • Регистрации конкурентов по тирзепатиду и семаглутиду
A67: • Гайденс на 2027 год, госзакупки онкологии во 2П 2026
... A75: Коммерсантъ — патентная защита тирзепатида: https://www.kommersant.ru/doc/8799945

Sheet YDEX
A1: YDEX — Яндекс: модель справедливой стоимости
A2: Метод: EV/EBITDA на прогноз 2027 года
A3: Компания роста с крупными капзатратами на ИИ и дата-центры. Стоимость бизнеса = (скорр. EBITDA 2027 − выплаты сотрудникам акциями) × мультипликатор; вычитаем чистый долг и разовый ущерб от атак на ЦОДы, делим на акции в обращении. Выплаты акциями вычтены из EBITDA, поэтому новые акции для сотрудников второй раз не учитываются.
A4: Синий — вводные (меняйте их), чёрный — формулы, зелёный — ссылки на другие листы, жёлтый — главные рычаги модели.
A6: Показатель | B6: Значение | C6: Ед. | D6: Источник / комментарий
A7: ВВОДНЫЕ
A8: Скорр. EBITDA 2026П | B8: 350 | C8: млрд ₽ | D8: Гайденс ~350 млрд, подтверждён 29.07.2026; 1П 2026: 162,2 млрд (маржа 21,4%), менеджмент ждёт ускорения во 2П.
A9: Рост EBITDA 2027 | B9: 0.15 | C9: % | D9: Гайденса на 2027 нет; выручка 2026 растёт ~20%, Совкомбанк ждёт замедления до ~12%. Берём 15%.
A10: Выплаты сотрудникам акциями в год | B10: 40 | C10: млрд ₽ | D10: Скорр. EBITDA их не включает, а расход постоянный: 18,3 млрд за 1П 2026 → ~37 млрд за 2026, ~40 млрд в 2027.
A11: Справедливый EV/(EBITDA − выплаты акциями) 2027П | B11: 4.5 | C11: x | D11: Рынок сейчас даёт ~3,6x на ту же базу 2027 года. 4,5x — премия ~25% за рост 15%+ и снижение ставки к 2028 (ЦБ: 9–10%). Меньше, чем у Промомеда (рост 35%).
A12: Скорр. чистый долг | B12: 7 | C12: млрд ₽ | D12: По данным компании на 30.06.2026 (0,02x LTM EBITDA): деньги 296 млрд, долг 277 млрд плюс долгосрочная аренда, которую компания включает в скорр. долг.
A13: Разовый ущерб от атак на ЦОДы | B13: 20 | C13: млрд ₽ | D13: По оценке пользователя: ~20 млрд ₽. Атаки 8–11.10.2026 (Сасово, Владимир, Калуга); компания ущерб не раскрыла, облако — 2–4% выручки. Уточнится в отчёте за 3К (29.10.2026).
A14: Акций в обращении | B14: 383 | C14: млн шт | D14: Выпущено 396,9 млн, из них ~15 млн у компании (выкуп и пул для сотрудников); в обращении 382,1 млн (средневзвешенно за 1П 2026, пресс-релиз 2К26). 11 млн новых акций (ноябрь 2026) — это и есть выплаты сотрудникам, они уже вычтены из EBITDA.
A15: Скорр. чистая прибыль 2027П (для проверки) | B15: 205 | C15: млрд ₽ | D15: 1П 2026: 82,2 млрд; 2026П ~180 млрд, +15% в 2027.
A16: Ставка дисконтирования | B16: =Параметры!$B$9 -> 0.19 | C16: % | D16: Из «Параметров».
A17: ИИ: рынок генеративного ИИ в РФ в 2030 | B17: =Параметры!$B$17 -> 778 | C17: млрд ₽ | D17: Из «Параметров».
A18: ИИ: доля компании на рынке в 2030 | B18: 0.4 | C18: % | D18: Алиса и YandexGPT — лидер в потребительском ИИ, Yandex Cloud — крупнейшее облако с ИИ-сервисами. Вместе со Сбером делят большую часть рынка. Оценка модели. Пересечение с базой: сегодняшняя ИИ-выручка уже есть в EBITDA, но она мала относительно рынка 2030.
A19: ИИ: мультипликатор лидеров (оценка / выручка) | B19: =Параметры!$B$22 -> 16.966667 | C19: x | D19: Из «Параметров»: среднее OpenAI, Anthropic, Alphabet.
A20: ИИ: поправка на стоимость денег в РФ | B20: =Параметры!$B$23 -> 1 | C20: x | D20: Из «Параметров»: 1,0 — как у американских лидеров.
A21: ИИ: лет до 2030 | B21: =Параметры!$B$18 -> 4 | C21: лет | D21: Из «Параметров».
A22: Мир: вероятность мира и снятия санкций | B22: =Параметры!$B$15 -> 0.5 | C22: % | D22: Из «Параметров».
A23: Мир: лет до снятия санкций | B23: =Параметры!$B$16 -> 5 | C23: лет | D23: Из «Параметров».
A24: Мир: EV/(EBITDA − выплаты акциями) после снятия санкций | B24: 10 | C24: x | D24: До 2022 Яндекс стоил 15–20x скорр. EBITDA (листинг в США); мировые интернет-компании ~12–15x. Берём 10x. ИИ-блок не переоцениваем — он уже по мультипликаторам США.
A25: Мир: рост показателя до года мира, % в год | B25: 0.12 | C25: % | D25: Рост EBITDA в среднем за 5 лет.
A27: РАСЧЁТ
A28: Скорр. EBITDA 2027П | B28: =$B$8*(1+$B$9) -> 402.5 | C28: млрд ₽
A29: EBITDA 2027П после выплат акциями | B29: =$B$28-$B$10 -> 362.5 | C29: млрд ₽
A30: Справедливая стоимость бизнеса (EV) | B30: =$B$29*$B$11 -> 1631.25 | C30: млрд ₽
A31: Стоимость акционерного капитала | B31: =$B$30-$B$12-$B$13 -> 1604.25 | C31: млрд ₽
A32: Базовая цена (без отдельной оценки ИИ) | B32: =IF($B$14>0,$B$31*1000/$B$14,0) -> 4188.6423 | C32: ₽
A33: ИИ: выручка компании в 2030 | B33: =$B$17*$B$18 -> 311.2 | C33: млрд ₽
A34: ИИ: стоимость ИИ-бизнеса в 2030 | B34: =$B$33*$B$19*$B$20 -> 5280.0267 | C34: млрд ₽ | D34: Выручка × мультипликатор лидеров × поправка РФ.
A35: ИИ: стоимость сегодня (дисконт до 2030) | B35: =$B$34/(1+$B$16)^$B$21 -> 2632.9843 | C35: млрд ₽
A36: ИИ: прибавка к цене акции | B36: =IF($B$14>0,$B$35*1000/$B$14,0) -> 6874.6327 | C36: ₽
A37: Справедливая цена без мира | B37: =$B$32+$B$36 -> 11063.275 | C37: ₽
A38: Мир: цена в мирном режиме на сегодняшних показателях | B38: =(($B$8*(1+$B$9)-$B$10)*$B$24-$B$12-$B$13)*1000/$B$14 -> 9394.2559 | C38: ₽ | D38: Если бы рынок уже сегодня оценивал компанию как до 2022 года. Без ИИ-блока.
A39: Мир: прибавка к цене сегодня | B39: =$B$22*($B$38-$B$32)*((1+$B$25)/(1+$B$16))^$B$23 -> 1922.1941 | C39: ₽ | D39: Вероятность × разница цен × рост показателя до года мира, приведённый к сегодняшнему дню.
A40: Справедливая цена с миром | B40: =$B$37+$B$39 -> 12985.469 | C40: ₽
A42: РЕЗУЛЬТАТ
A43: Справедливая цена | B43: =$B$40 -> 12985.469 | C43: ₽ | D43: Главный вывод модели
A44: Текущая цена | B44: =Сводка!$D$9 -> 3400 | C44: ₽ | D44: Берётся со «Сводки» (столбец D)
A45: Зона покупки: цена не выше | B45: =$B$43*(1-Параметры!$B$10) -> 9998.8112 | C45: ₽ | D45: Справедливая минус скидка из «Параметров»
A46: Цена продажи | B46: =$B$43*(1+Параметры!$B$11) -> 15322.853 | C46: ₽ | D46: Справедливая плюс премия из «Параметров»
A47: Сигнал «приближается к продаже» от | B47: =$B$46*(1-Параметры!$B$12) -> 14556.711 | C47: ₽ | D47: За сколько % до цены продажи бот предупреждает
A48: Потенциал до справедливой | B48: =IF($B$44>0,$B$43/$B$44-1,0) -> 2.8192556 | C48: %
A49: До цены продажи | B49: =IF($B$44>0,$B$46/$B$44-1,0) -> 3.5067216 | C49: %
A50: Статус | B50: =IF($B$44<=$B$45,"ЗОНА ПОКУПКИ",IF($B$44>=$B$46,"ЦЕНА ПРОДАЖИ",IF($B$44>=$B$47,"ПРИБЛИЖАЕТСЯ К ПРОДАЖЕ","ДЕРЖАТЬ"))) -> ЗОНА ПОКУПКИ | D50: Слом тезиса — отдельный сигнал, см. ниже
A52: ПЕРЕКРЁСТНАЯ ПРОВЕРКА
A53: Доля ИИ в справедливой цене | B53: =IF($B$43>0,$B$36/$B$43,0) -> 0.52940965 | C53: %
A54: ИИ-прибавка при скидке рынка РФ к США | B54: =IF($B$20>0,$B$36/$B$20*Параметры!$B$24,0) -> 1374.9265 | C54: ₽ | D54: Если ИИ-бизнес рынок оценит с той же скидкой к американским аналогам, что и весь Яндекс (~0,2).
A55: Справедливая цена при этой скидке | B55: =$B$32+$B$54 -> 5563.5688 | C55: ₽ | D55: Консервативный ориентир.
A56: P/E 2027П базовой цены (без ИИ) | B56: =IF($B$15>0,$B$32*$B$14/1000/$B$15,0) -> 7.8256098 | C56: x | D56: Для роста 15% разумно 8–12x.
A57: EV/скорр. EBITDA 2026П при текущей цене | B57: =IF($B$8>0,($B$44*$B$14/1000+$B$12)/$B$8,0) -> 3.7405714 | C57: x | D57: Так считают рынок и брокеры.
A58: EV/(EBITDA − выплаты акциями) 2027П при текущей цене | B58: =IF($B$29>0,($B$44*$B$14/1000+$B$12)/$B$29,0) -> 3.6115862 | C58: x | D58: Та же база, что у справедливого мультипликатора.
A59: Дивдоходность (2 × 110 ₽ в год) | B59: =IF($B$44>0,220/$B$44,0) -> 0.064705882 | C59: % | D59: В 2026 выплачено 110 ₽ за 2025 и 110 ₽ за 1П 2026.
A60: Среднее 3 целей после атак | B60: =5034 -> 5034 | C60: ₽ | D60: Freedom 5000, Цифра брокер 4978, Финам 5125 (октябрь 2026); до атак — 5000–6856 ₽.
A62: ЧУВСТВИТЕЛЬНОСТЬ СПРАВЕДЛИВОЙ ЦЕНЫ, ₽: строки — EV/EBITDA, столбцы — рост EBITDA 2027
A63: EV/EBITDA \ рост EBITDA 2027 | B63: 0.05 | C63: 0.1 | D63: 0.15 | E63: 0.2 | F63: 0.25
A64: 3.5 | B64: =((($B$8*(1+B$63)-$B$10)*$A64-$B$12-$B$13+$B$17*$B$18*$B$19*$B$20/(1+$B$16)^$B$21)*1000/$B$14)+$B$22*(((($B$8*(1+B$63)-$B$10)*$B$24-$B$12-$B$13)*1000/$B$14)-((($B$8*(1+B$63)-$B$10)*$A64-$B$12-$B$13)*1000/$B$14))*((1+$B$25)/(1+$B$16))^$B$23 -> 11849.305 | C64: =((($B$8*(1+C$63)-$B$10)*$A64-$B$12-$B$13+$B$17*$B$18*$B$19*$B$20/(1+$B$16)^$B$21)*1000/$B$14)+$B$22*(((($B$8*(1+C$63)-$B$10)*$B$24-$B$12-$B$13)*1000/$B$14)-((($B$8*(1+C$63)-$B$10)*$A64-$B$12-$B$13)*1000/$B$14))*((1+$B$25)/(1+$B$16))^$B$23 -> 12118.895 | D64: =((($B$8*(1+D$63)-$B$10)*$A64-$B$12-$B$13+$B$17*$B$18*$B$19*$B$20/(1+$B$16)^$B$21)*1000/$B$14)+$B$22*(((($B$8*(1+D$63)-$B$10)*$B$24-$B$12-$B$13)*1000/$B$14)-((($B$8*(1+D$63)-$B$10)*$A64-$B$12-$B$13)*1000/$B$14))*((1+$B$25)/(1+$B$16))^$B$23 -> 12388.484 | E64: =((($B$8*(1+E$63)-$B$10)*$A64-$B$12-$B$13+$B$17*$B$18*$B$19*$B$20/(1+$B$16)^$B$21)*1000/$B$14)+$B$22*(((($B$8*(1+E$63)-$B$10)*$B$24-$B$12-$B$13)*1000/$B$14)-((($B$8*(1+E$63)-$B$10)*$A64-$B$12-$B$13)*1000/$B$14))*((1+$B$25)/(1+$B$16))^$B$23 -> 12658.073 | F64: =((($B$8*(1+F$63)-$B$10)*$A64-$B$12-$B$13+$B$17*$B$18*$B$19*$B$20/(1+$B$16)^$B$21)*1000/$B$14)+$B$22*(((($B$8*(1+F$63)-$B$10)*$B$24-$B$12-$B$13)*1000/$B$14)-((($B$8*(1+F$63)-$B$10)*$A64-$B$12-$B$13)*1000/$B$14))*((1+$B$25)/(1+$B$16))^$B$23 -> 12927.662
A65: 4 | B65: =((($B$8*(1+B$63)-$B$10)*$A65-$B$12-$B$13+$B$17*$B$18*$B$19*$B$20/(1+$B$16)^$B$21)*1000/$B$14)+$B$22*(((($B$8*(1+B$63)-$B$10)*$B$24-$B$12-$B$13)*1000/$B$14)-((($B$8*(1+B$63)-$B$10)*$A65-$B$12-$B$13)*1000/$B$14))*((1+$B$25)/(1+$B$16))^$B$23 -> 12118.978 | C65: =((($B$8*(1+C$63)-$B$10)*$A65-$B$12-$B$13+$B$17*$B$18*$B$19*$B$20/(1+$B$16)^$B$21)*1000/$B$14)+$B$22*(((($B$8*(1+C$63)-$B$10)*$B$24-$B$12-$B$13)*1000/$B$14)-((($B$8*(1+C$63)-$B$10)*$A65-$B$12-$B$13)*1000/$B$14))*((1+$B$25)/(1+$B$16))^$B$23 -> 12402.977 | D65: =((($B$8*(1+D$63)-$B$10)*$A65-$B$12-$B$13+$B$17*$B$18*$B$19*$B$20/(1+$B$16)^$B$21)*1000/$B$14)+$B$22*(((($B$8*(1+D$63)-$B$10)*$B$24-$B$12-$B$13)*1000/$B$14)-((($B$8*(1+D$63)-$B$10)*$A65-$B$12-$B$13)*1000/$B$14))*((1+$B$25)/(1+$B$16))^$B$23 -> 12686.976 | E65: =((($B$8*(1+E$63)-$B$10)*$A65-$B$12-$B$13+$B$17*$B$18*$B$19*$B$20/(1+$B$16)^$B$21)*1000/$B$14)+$B$22*(((($B$8*(1+E$63)-$B$10)*$B$24-$B$12-$B$13)*1000/$B$14)-((($B$8*(1+E$63)-$B$10)*$A65-$B$12-$B$13)*1000/$B$14))*((1+$B$25)/(1+$B$16))^$B$23 -> 12970.976 | F65: =((($B$8*(1+F$63)-$B$10)*$A65-$B$12-$B$13+$B$17*$B$18*$B$19*$B$20/(1+$B$16)^$B$21)*1000/$B$14)+$B$22*(((($B$8*(1+F$63)-$B$10)*$B$24-$B$12-$B$13)*1000/$B$14)-((($B$8*(1+F$63)-$B$10)*$A65-$B$12-$B$13)*1000/$B$14))*((1+$B$25)/(1+$B$16))^$B$23 -> 13254.975
A66: 4.5 | B66: =((($B$8*(1+B$63)-$B$10)*$A66-$B$12-$B$13+$B$17*$B$18*$B$19*$B$20/(1+$B$16)^$B$21)*1000/$B$14)+$B$22*(((($B$8*(1+B$63)-$B$10)*$B$24-$B$12-$B$13)*1000/$B$14)-((($B$8*(1+B$63)-$B$10)*$A66-$B$12-$B$13)*1000/$B$14))*((1+$B$25)/(1+$B$16))^$B$23 -> 12388.651 | C66: =((($B$8*(1+C$63)-$B$10)*$A66-$B$12-$B$13+$B$17*$B$18*$B$19*$B$20/(1+$B$16)^$B$21)*1000/$B$14)+$B$22*(((($B$8*(1+C$63)-$B$10)*$B$24-$B$12-$B$13)*1000/$B$14)-((($B$8*(1+C$63)-$B$10)*$A66-$B$12-$B$13)*1000/$B$14))*((1+$B$25)/(1+$B$16))^$B$23 -> 12687.06 | D66: =((($B$8*(1+D$63)-$B$10)*$A66-$B$12-$B$13+$B$17*$B$18*$B$19*$B$20/(1+$B$16)^$B$21)*1000/$B$14)+$B$22*(((($B$8*(1+D$63)-$B$10)*$B$24-$B$12-$B$13)*1000/$B$14)-((($B$8*(1+D$63)-$B$10)*$A66-$B$12-$B$13)*1000/$B$14))*((1+$B$25)/(1+$B$16))^$B$23 -> 12985.469 | E66: =((($B$8*(1+E$63)-$B$10)*$A66-$B$12-$B$13+$B$17*$B$18*$B$19*$B$20/(1+$B$16)^$B$21)*1000/$B$14)+$B$22*(((($B$8*(1+E$63)-$B$10)*$B$24-$B$12-$B$13)*1000/$B$14)-((($B$8*(1+E$63)-$B$10)*$A66-$B$12-$B$13)*1000/$B$14))*((1+$B$25)/(1+$B$16))^$B$23 -> 13283.878 | F66: =((($B$8*(1+F$63)-$B$10)*$A66-$B$12-$B$13+$B$17*$B$18*$B$19*$B$20/(1+$B$16)^$B$21)*1000/$B$14)+$B$22*(((($B$8*(1+F$63)-$B$10)*$B$24-$B$12-$B$13)*1000/$B$14)-((($B$8*(1+F$63)-$B$10)*$A66-$B$12-$B$13)*1000/$B$14))*((1+$B$25)/(1+$B$16))^$B$23 -> 13582.287
A67: 5 | B67: =((($B$8*(1+B$63)-$B$10)*$A67-$B$12-$B$13+$B$17*$B$18*$B$19*$B$20/(1+$B$16)^$B$21)*1000/$B$14)+$B$22*(((($B$8*(1+B$63)-$B$10)*$B$24-$B$12-$B$13)*1000/$B$14)-((($B$8*(1+B$63)-$B$10)*$A67-$B$12-$B$13)*1000/$B$14))*((1+$B$25)/(1+$B$16))^$B$23 -> 12658.323 | C67: =((($B$8*(1+C$63)-$B$10)*$A67-$B$12-$B$13+$B$17*$B$18*$B$19*$B$20/(1+$B$16)^$B$21)*1000/$B$14)+$B$22*(((($B$8*(1+C$63)-$B$10)*$B$24-$B$12-$B$13)*1000/$B$14)-((($B$8*(1+C$63)-$B$10)*$A67-$B$12-$B$13)*1000/$B$14))*((1+$B$25)/(1+$B$16))^$B$23 -> 12971.143 | D67: =((($B$8*(1+D$63)-$B$10)*$A67-$B$12-$B$13+$B$17*$B$18*$B$19*$B$20/(1+$B$16)^$B$21)*1000/$B$14)+$B$22*(((($B$8*(1+D$63)-$B$10)*$B$24-$B$12-$B$13)*1000/$B$14)-((($B$8*(1+D$63)-$B$10)*$A67-$B$12-$B$13)*1000/$B$14))*((1+$B$25)/(1+$B$16))^$B$23 -> 13283.962 | E67: =((($B$8*(1+E$63)-$B$10)*$A67-$B$12-$B$13+$B$17*$B$18*$B$19*$B$20/(1+$B$16)^$B$21)*1000/$B$14)+$B$22*(((($B$8*(1+E$63)-$B$10)*$B$24-$B$12-$B$13)*1000/$B$14)-((($B$8*(1+E$63)-$B$10)*$A67-$B$12-$B$13)*1000/$B$14))*((1+$B$25)/(1+$B$16))^$B$23 -> 13596.781 | F67: =((($B$8*(1+F$63)-$B$10)*$A67-$B$12-$B$13+$B$17*$B$18*$B$19*$B$20/(1+$B$16)^$B$21)*1000/$B$14)+$B$22*(((($B$8*(1+F$63)-$B$10)*$B$24-$B$12-$B$13)*1000/$B$14)-((($B$8*(1+F$63)-$B$10)*$A67-$B$12-$B$13)*1000/$B$14))*((1+$B$25)/(1+$B$16))^$B$23 -> 13909.6
A68: 5.5 | B68: =((($B$8*(1+B$63)-$B$10)*$A68-$B$12-$B$13+$B$17*$B$18*$B$19*$B$20/(1+$B$16)^$B$21)*1000/$B$14)+$B$22*(((($B$8*(1+B$63)-$B$10)*$B$24-$B$12-$B$13)*1000/$B$14)-((($B$8*(1+B$63)-$B$10)*$A68-$B$12-$B$13)*1000/$B$14))*((1+$B$25)/(1+$B$16))^$B$23 -> 12927.996 | C68: =((($B$8*(1+C$63)-$B$10)*$A68-$B$12-$B$13+$B$17*$B$18*$B$19*$B$20/(1+$B$16)^$B$21)*1000/$B$14)+$B$22*(((($B$8*(1+C$63)-$B$10)*$B$24-$B$12-$B$13)*1000/$B$14)-((($B$8*(1+C$63)-$B$10)*$A68-$B$12-$B$13)*1000/$B$14))*((1+$B$25)/(1+$B$16))^$B$23 -> 13255.225 | D68: =((($B$8*(1+D$63)-$B$10)*$A68-$B$12-$B$13+$B$17*$B$18*$B$19*$B$20/(1+$B$16)^$B$21)*1000/$B$14)+$B$22*(((($B$8*(1+D$63)-$B$10)*$B$24-$B$12-$B$13)*1000/$B$14)-((($B$8*(1+D$63)-$B$10)*$A68-$B$12-$B$13)*1000/$B$14))*((1+$B$25)/(1+$B$16))^$B$23 -> 13582.454 | E68: =((($B$8*(1+E$63)-$B$10)*$A68-$B$12-$B$13+$B$17*$B$18*$B$19*$B$20/(1+$B$16)^$B$21)*1000/$B$14)+$B$22*(((($B$8*(1+E$63)-$B$10)*$B$24-$B$12-$B$13)*1000/$B$14)-((($B$8*(1+E$63)-$B$10)*$A68-$B$12-$B$13)*1000/$B$14))*((1+$B$25)/(1+$B$16))^$B$23 -> 13909.684 | F68: =((($B$8*(1+F$63)-$B$10)*$A68-$B$12-$B$13+$B$17*$B$18*$B$19*$B$20/(1+$B$16)^$B$21)*1000/$B$14)+$B$22*(((($B$8*(1+F$63)-$B$10)*$B$24-$B$12-$B$13)*1000/$B$14)-((($B$8*(1+F$63)-$B$10)*$A68-$B$12-$B$13)*1000/$B$14))*((1+$B$25)/(1+$B$16))^$B$23 -> 14236.913
A69: Центр таблицы (жёлтая ячейка) = базовый сценарий; должен совпадать со справедливой ценой.
A71: ЧУВСТВИТЕЛЬНОСТЬ СПРАВЕДЛИВОЙ ЦЕНЫ, ₽: строки — доля Яндекса на рынке ИИ, столбцы — рынок генИИ в РФ 2030, млрд ₽
A72: доля Яндекса на рынке ИИ \ рынок генИИ в РФ 2030, млрд ₽ | B72: 400 | C72: 590 | D72: 778 | E72: 950 | F72: 1120
A73: 0.2 | B73: =((($B$8*(1+$B$9)-$B$10)*$B$11-$B$12-$B$13+B$72*$A73*$B$19*$B$20/(1+$B$16)^$B$21)*1000/$B$14)+$B$22*(((($B$8*(1+$B$9)-$B$10)*$B$24-$B$12-$B$13)*1000/$B$14)-((($B$8*(1+$B$9)-$B$10)*$B$11-$B$12-$B$13)*1000/$B$14))*((1+$B$25)/(1+$B$16))^$B$23 -> 7878.0941 | C73: =((($B$8*(1+$B$9)-$B$10)*$B$11-$B$12-$B$13+C$72*$A73*$B$19*$B$20/(1+$B$16)^$B$21)*1000/$B$14)+$B$22*(((($B$8*(1+$B$9)-$B$10)*$B$24-$B$12-$B$13)*1000/$B$14)-((($B$8*(1+$B$9)-$B$10)*$B$11-$B$12-$B$13)*1000/$B$14))*((1+$B$25)/(1+$B$16))^$B$23 -> 8717.5416 | D73: =((($B$8*(1+$B$9)-$B$10)*$B$11-$B$12-$B$13+D$72*$A73*$B$19*$B$20/(1+$B$16)^$B$21)*1000/$B$14)+$B$22*(((($B$8*(1+$B$9)-$B$10)*$B$24-$B$12-$B$13)*1000/$B$14)-((($B$8*(1+$B$9)-$B$10)*$B$11-$B$12-$B$13)*1000/$B$14))*((1+$B$25)/(1+$B$16))^$B$23 -> 9548.1527 | E73: =((($B$8*(1+$B$9)-$B$10)*$B$11-$B$12-$B$13+E$72*$A73*$B$19*$B$20/(1+$B$16)^$B$21)*1000/$B$14)+$B$22*(((($B$8*(1+$B$9)-$B$10)*$B$24-$B$12-$B$13)*1000/$B$14)-((($B$8*(1+$B$9)-$B$10)*$B$11-$B$12-$B$13)*1000/$B$14))*((1+$B$25)/(1+$B$16))^$B$23 -> 10308.074 | F73: =((($B$8*(1+$B$9)-$B$10)*$B$11-$B$12-$B$13+F$72*$A73*$B$19*$B$20/(1+$B$16)^$B$21)*1000/$B$14)+$B$22*(((($B$8*(1+$B$9)-$B$10)*$B$24-$B$12-$B$13)*1000/$B$14)-((($B$8*(1+$B$9)-$B$10)*$B$11-$B$12-$B$13)*1000/$B$14))*((1+$B$25)/(1+$B$16))^$B$23 -> 11059.158
A74: 0.3 | B74: =((($B$8*(1+$B$9)-$B$10)*$B$11-$B$12-$B$13+B$72*$A74*$B$19*$B$20/(1+$B$16)^$B$21)*1000/$B$14)+$B$22*(((($B$8*(1+$B$9)-$B$10)*$B$24-$B$12-$B$13)*1000/$B$14)-((($B$8*(1+$B$9)-$B$10)*$B$11-$B$12-$B$13)*1000/$B$14))*((1+$B$25)/(1+$B$16))^$B$23 -> 8761.723 | C74: =((($B$8*(1+$B$9)-$B$10)*$B$11-$B$12-$B$13+C$72*$A74*$B$19*$B$20/(1+$B$16)^$B$21)*1000/$B$14)+$B$22*(((($B$8*(1+$B$9)-$B$10)*$B$24-$B$12-$B$13)*1000/$B$14)-((($B$8*(1+$B$9)-$B$10)*$B$11-$B$12-$B$13)*1000/$B$14))*((1+$B$25)/(1+$B$16))^$B$23 -> 10020.894 | D74: =((($B$8*(1+$B$9)-$B$10)*$B$11-$B$12-$B$13+D$72*$A74*$B$19*$B$20/(1+$B$16)^$B$21)*1000/$B$14)+$B$22*(((($B$8*(1+$B$9)-$B$10)*$B$24-$B$12-$B$13)*1000/$B$14)-((($B$8*(1+$B$9)-$B$10)*$B$11-$B$12-$B$13)*1000/$B$14))*((1+$B$25)/(1+$B$16))^$B$23 -> 11266.811 | E74: =((($B$8*(1+$B$9)-$B$10)*$B$11-$B$12-$B$13+E$72*$A74*$B$19*$B$20/(1+$B$16)^$B$21)*1000/$B$14)+$B$22*(((($B$8*(1+$B$9)-$B$10)*$B$24-$B$12-$B$13)*1000/$B$14)-((($B$8*(1+$B$9)-$B$10)*$B$11-$B$12-$B$13)*1000/$B$14))*((1+$B$25)/(1+$B$16))^$B$23 -> 12406.692 | F74: =((($B$8*(1+$B$9)-$B$10)*$B$11-$B$12-$B$13+F$72*$A74*$B$19*$B$20/(1+$B$16)^$B$21)*1000/$B$14)+$B$22*(((($B$8*(1+$B$9)-$B$10)*$B$24-$B$12-$B$13)*1000/$B$14)-((($B$8*(1+$B$9)-$B$10)*$B$11-$B$12-$B$13)*1000/$B$14))*((1+$B$25)/(1+$B$16))^$B$23 -> 13533.319
A75: 0.4 | B75: =((($B$8*(1+$B$9)-$B$10)*$B$11-$B$12-$B$13+B$72*$A75*$B$19*$B$20/(1+$B$16)^$B$21)*1000/$B$14)+$B$22*(((($B$8*(1+$B$9)-$B$10)*$B$24-$B$12-$B$13)*1000/$B$14)-((($B$8*(1+$B$9)-$B$10)*$B$11-$B$12-$B$13)*1000/$B$14))*((1+$B$25)/(1+$B$16))^$B$23 -> 9645.3519 | C75: =((($B$8*(1+$B$9)-$B$10)*$B$11-$B$12-$B$13+C$72*$A75*$B$19*$B$20/(1+$B$16)^$B$21)*1000/$B$14)+$B$22*(((($B$8*(1+$B$9)-$B$10)*$B$24-$B$12-$B$13)*1000/$B$14)-((($B$8*(1+$B$9)-$B$10)*$B$11-$B$12-$B$13)*1000/$B$14))*((1+$B$25)/(1+$B$16))^$B$23 -> 11324.247 | D75: =((($B$8*(1+$B$9)-$B$10)*$B$11-$B$12-$B$13+D$72*$A75*$B$19*$B$20/(1+$B$16)^$B$21)*1000/$B$14)+$B$22*(((($B$8*(1+$B$9)-$B$10)*$B$24-$B$12-$B$13)*1000/$B$14)-((($B$8*(1+$B$9)-$B$10)*$B$11-$B$12-$B$13)*1000/$B$14))*((1+$B$25)/(1+$B$16))^$B$23 -> 12985.469 | E75: =((($B$8*(1+$B$9)-$B$10)*$B$11-$B$12-$B$13+E$72*$A75*$B$19*$B$20/(1+$B$16)^$B$21)*1000/$B$14)+$B$22*(((($B$8*(1+$B$9)-$B$10)*$B$24-$B$12-$B$13)*1000/$B$14)-((($B$8*(1+$B$9)-$B$10)*$B$11-$B$12-$B$13)*1000/$B$14))*((1+$B$25)/(1+$B$16))^$B$23 -> 14505.311 | F75: =((($B$8*(1+$B$9)-$B$10)*$B$11-$B$12-$B$13+F$72*$A75*$B$19*$B$20/(1+$B$16)^$B$21)*1000/$B$14)+$B$22*(((($B$8*(1+$B$9)-$B$10)*$B$24-$B$12-$B$13)*1000/$B$14)-((($B$8*(1+$B$9)-$B$10)*$B$11-$B$12-$B$13)*1000/$B$14))*((1+$B$25)/(1+$B$16))^$B$23 -> 16007.48
A76: 0.5 | B76: =((($B$8*(1+$B$9)-$B$10)*$B$11-$B$12-$B$13+B$72*$A76*$B$19*$B$20/(1+$B$16)^$B$21)*1000/$B$14)+$B$22*(((($B$8*(1+$B$9)-$B$10)*$B$24-$B$12-$B$13)*1000/$B$14)-((($B$8*(1+$B$9)-$B$10)*$B$11-$B$12-$B$13)*1000/$B$14))*((1+$B$25)/(1+$B$16))^$B$23 -> 10528.981 | C76: =((($B$8*(1+$B$9)-$B$10)*$B$11-$B$12-$B$13+C$72*$A76*$B$19*$B$20/(1+$B$16)^$B$21)*1000/$B$14)+$B$22*(((($B$8*(1+$B$9)-$B$10)*$B$24-$B$12-$B$13)*1000/$B$14)-((($B$8*(1+$B$9)-$B$10)*$B$11-$B$12-$B$13)*1000/$B$14))*((1+$B$25)/(1+$B$16))^$B$23 -> 12627.599 | D76: =((($B$8*(1+$B$9)-$B$10)*$B$11-$B$12-$B$13+D$72*$A76*$B$19*$B$20/(1+$B$16)^$B$21)*1000/$B$14)+$B$22*(((($B$8*(1+$B$9)-$B$10)*$B$24-$B$12-$B$13)*1000/$B$14)-((($B$8*(1+$B$9)-$B$10)*$B$11-$B$12-$B$13)*1000/$B$14))*((1+$B$25)/(1+$B$16))^$B$23 -> 14704.127 | E76: =((($B$8*(1+$B$9)-$B$10)*$B$11-$B$12-$B$13+E$72*$A76*$B$19*$B$20/(1+$B$16)^$B$21)*1000/$B$14)+$B$22*(((($B$8*(1+$B$9)-$B$10)*$B$24-$B$12-$B$13)*1000/$B$14)-((($B$8*(1+$B$9)-$B$10)*$B$11-$B$12-$B$13)*1000/$B$14))*((1+$B$25)/(1+$B$16))^$B$23 -> 16603.929 | F76: =((($B$8*(1+$B$9)-$B$10)*$B$11-$B$12-$B$13+F$72*$A76*$B$19*$B$20/(1+$B$16)^$B$21)*1000/$B$14)+$B$22*(((($B$8*(1+$B$9)-$B$10)*$B$24-$B$12-$B$13)*1000/$B$14)-((($B$8*(1+$B$9)-$B$10)*$B$11-$B$12-$B$13)*1000/$B$14))*((1+$B$25)/(1+$B$16))^$B$23 -> 18481.641
A77: 0.6 | B77: =((($B$8*(1+$B$9)-$B$10)*$B$11-$B$12-$B$13+B$72*$A77*$B$19*$B$20/(1+$B$16)^$B$21)*1000/$B$14)+$B$22*(((($B$8*(1+$B$9)-$B$10)*$B$24-$B$12-$B$13)*1000/$B$14)-((($B$8*(1+$B$9)-$B$10)*$B$11-$B$12-$B$13)*1000/$B$14))*((1+$B$25)/(1+$B$16))^$B$23 -> 11412.61 | C77: =((($B$8*(1+$B$9)-$B$10)*$B$11-$B$12-$B$13+C$72*$A77*$B$19*$B$20/(1+$B$16)^$B$21)*1000/$B$14)+$B$22*(((($B$8*(1+$B$9)-$B$10)*$B$24-$B$12-$B$13)*1000/$B$14)-((($B$8*(1+$B$9)-$B$10)*$B$11-$B$12-$B$13)*1000/$B$14))*((1+$B$25)/(1+$B$16))^$B$23 -> 13930.952 | D77: =((($B$8*(1+$B$9)-$B$10)*$B$11-$B$12-$B$13+D$72*$A77*$B$19*$B$20/(1+$B$16)^$B$21)*1000/$B$14)+$B$22*(((($B$8*(1+$B$9)-$B$10)*$B$24-$B$12-$B$13)*1000/$B$14)-((($B$8*(1+$B$9)-$B$10)*$B$11-$B$12-$B$13)*1000/$B$14))*((1+$B$25)/(1+$B$16))^$B$23 -> 16422.785 | E77: =((($B$8*(1+$B$9)-$B$10)*$B$11-$B$12-$B$13+E$72*$A77*$B$19*$B$20/(1+$B$16)^$B$21)*1000/$B$14)+$B$22*(((($B$8*(1+$B$9)-$B$10)*$B$24-$B$12-$B$13)*1000/$B$14)-((($B$8*(1+$B$9)-$B$10)*$B$11-$B$12-$B$13)*1000/$B$14))*((1+$B$25)/(1+$B$16))^$B$23 -> 18702.548 | F77: =((($B$8*(1+$B$9)-$B$10)*$B$11-$B$12-$B$13+F$72*$A77*$B$19*$B$20/(1+$B$16)^$B$21)*1000/$B$14)+$B$22*(((($B$8*(1+$B$9)-$B$10)*$B$24-$B$12-$B$13)*1000/$B$14)-((($B$8*(1+$B$9)-$B$10)*$B$11-$B$12-$B$13)*1000/$B$14))*((1+$B$25)/(1+$B$16))^$B$23 -> 20955.801
A78: Центр таблицы (жёлтая ячейка) = базовый сценарий; должен совпадать со справедливой ценой.
A80: ТЕЗИС И УСЛОВИЯ ЕГО СЛОМА (сигнал при любой цене)
A81: Тезис: Главная технологическая компания страны: поиск, такси и доставка, реклама, облако и собственные ИИ-модели. EBITDA растёт на 20%+ в год, долга нет, дивиденды 220 ₽ в год. Главный рычаг стоимости — ИИ: иностранные модели в РФ ограничены, и Яндекс вместе со Сбером может занять рынок, как когда-то вытеснил Uber. Рынок пока дисконтирует компанию из‑за ставки, капзатрат на ИИ и атак на дата-центры.
A82: • Скорр. EBITDA 2026 ниже 320 млрд ₽ (срыв гайденса 350)
A83: • Ущерб от атак на ЦОДы больше 100 млрд ₽ или новые атаки с остановкой сервисов
A84: • Доля Яндекса в генеративном ИИ падает ниже 25% или в РФ возвращаются иностранные модели
A85: • Допэмиссии сверх программы мотивации или отмена выплат по 110 ₽
A86: • Регуляторное изъятие: налог на ИТ-сверхприбыль, госконтроль над сервисами
A88: ЧТО ОТСЛЕЖИВАЕТ БОТ В НОВОСТЯХ
A89: • Отчёт за 3К 2026 (ожидается 29.10.2026): ущерб от атак, подтверждение гайденса
A90: • Гайденс на 2027 год (обычно в феврале–марте)
A91: • Ход восстановления ЦОДов, новые атаки
... A105: ValueAdd VC — выручка и оценка Anthropic: https://valueaddvc.com/blog/anthropic-revenue-hits-47b-run-rate-how-it-passed-openai-in-just-five-months

Sheet MTSS
A1: MTSS — МТС: модель справедливой стоимости
A2: Метод: модель денежных выплат акционерам (Гордон: дивиденды + выкуп акций)
A3: С 2027 года МТС возвращает акционерам не меньше 70 млрд ₽ в год: 70% дивидендами, 30% выкупом акций. Стоимость акции = выплаты на акцию / (требуемая доходность − рост). Требуемая доходность выше, чем у Сбера: большой долг и политика только на два года.
A4: Синий — вводные (меняйте их), чёрный — формулы, зелёный — ссылки на другие листы, жёлтый — главные рычаги модели.
A6: Показатель | B6: Значение | C6: Ед. | D6: Источник / комментарий
A7: ВВОДНЫЕ
A8: Выплаты акционерам в год (2027–2028) | B8: 70 | C8: млрд ₽ | D8: Политика от 15.09.2026: до 20% OIBDA, цель не менее 70 млрд ₽ в год; 70% дивиденды, 30% байбек; выплаты 3 раза в год, первая — январь 2027 за 9М 2026.
A9: Доля дивидендов в выплатах | B9: 0.7 | C9: % | D9: Остальные 30% — выкуп акций.
A10: Акций выпущено | B10: 1.9984 | C10: млрд шт | D10: 1 998 381 575 акций; дивиденд 35 ₽ = 69,9 млрд ₽ выплачивался на весь выпуск.
A11: Базовая требуемая доходность | B11: =Параметры!$B$9 -> 0.19 | C11: % | D11: Из «Параметров».
A12: Премия за специфический риск | B12: 0.02 | C12: % | D12: Чистый долг с арендой ~645 млрд ₽ (2,1x OIBDA), политика выплат только на 2027–2028, зависимость АФК «Система» от дивидендов.
A13: Долгосрочный рост выплат | B13: 0.04 | C13: % | D13: OIBDA растёт на 13–17%, но выплаты привязаны к фиксированной цели и съедаются капзатратами и процентами; берём 4%.
A14: Чистый долг с арендой (для проверки) | B14: 645.2 | C14: млрд ₽ | D14: На 30.06.2026 (Market Power, 2,13x OIBDA).
A15: OIBDA 2026П (для проверки) | B15: 325 | C15: млрд ₽ | D15: 1П 2026: 159,3 млрд (+17%); второе полугодие сезонно сильнее.
A16: ИИ: рынок генеративного ИИ в РФ в 2030 | B16: =Параметры!$B$17 -> 778 | C16: млрд ₽ | D16: Из «Параметров».
A17: ИИ: доля компании на рынке в 2030 | B17: 0.05 | C17: % | D17: MWS AI: цель ~1 млрд ₽ выручки в 2026 (~2% рынка генИИ); MWS (облака и ИИ) — 63,8 млрд ₽ выручки в 2025, рост MWS AI +60%. Оценка модели.
A18: ИИ: мультипликатор лидеров (оценка / выручка) | B18: =Параметры!$B$22 -> 16.966667 | C18: x | D18: Из «Параметров»: среднее OpenAI, Anthropic, Alphabet.
A19: ИИ: поправка на стоимость денег в РФ | B19: =Параметры!$B$23 -> 1 | C19: x | D19: Из «Параметров»: 1,0 — как у американских лидеров.
A20: ИИ: лет до 2030 | B20: =Параметры!$B$18 -> 4 | C20: лет | D20: Из «Параметров».
A21: Мир: вероятность мира и снятия санкций | B21: =Параметры!$B$15 -> 0.5 | C21: % | D21: Из «Параметров».
A22: Мир: лет до снятия санкций | B22: =Параметры!$B$16 -> 5 | C22: лет | D22: Из «Параметров».
A23: Мир: EV/OIBDA как до 2022 года | B23: 4.5 | C23: x | D23: МТС в 2017–2021 стоил ~4,5–5x OIBDA (акция 250–350 ₽). Применяется к OIBDA 2026П с нынешним долгом.
A24: Мир: рост показателя до года мира, % в год | B24: 0.07 | C24: % | D24: OIBDA сейчас растёт на 13–17%, к 2031 рост замедлится.
A26: РАСЧЁТ
A27: Выплаты на акцию в год | B27: =$B$8/$B$10 -> 35.028022 | C27: ₽/акц.
A28: из них дивиденд | B28: =$B$27*$B$9 -> 24.519616 | C28: ₽/акц.
A29: Требуемая доходность | B29: =$B$11+$B$12 -> 0.21 | C29: %
A30: Справедливая доходность выплат (r − g) | B30: =$B$29-$B$13 -> 0.17 | C30: %
A31: Базовая цена = выплаты / (r − g) | B31: =IF($B$30>0,$B$27/$B$30,0) -> 206.04719 | C31: ₽ | D31: Телеком без отдельной оценки ИИ.
A32: ИИ: выручка компании в 2030 | B32: =$B$16*$B$17 -> 38.9 | C32: млрд ₽
A33: ИИ: стоимость ИИ-бизнеса в 2030 | B33: =$B$32*$B$18*$B$19 -> 660.00333 | C33: млрд ₽ | D33: Выручка × мультипликатор лидеров × поправка РФ.
A34: ИИ: стоимость сегодня (дисконт до 2030) | B34: =$B$33/(1+$B$11)^$B$20 -> 329.12304 | C34: млрд ₽
A35: ИИ: прибавка к цене акции | B35: =IF($B$10>0,$B$34/$B$10,0) -> 164.69327 | C35: ₽
A36: Справедливая цена без мира | B36: =$B$31+$B$35 -> 370.74046 | C36: ₽
A37: Мир: цена в мирном режиме на сегодняшних показателях | B37: =($B$23*$B$15-$B$14)/$B$10 -> 408.97718 | C37: ₽ | D37: Если бы рынок уже сегодня оценивал компанию как до 2022 года. Без ИИ-блока.
A38: Мир: прибавка к цене сегодня | B38: =$B$21*($B$37-$B$31)*((1+$B$24)/(1+$B$11))^$B$22 -> 59.634876 | C38: ₽ | D38: Вероятность × разница цен × рост показателя до года мира, приведённый к сегодняшнему дню.
A39: Справедливая цена с миром | B39: =$B$36+$B$38 -> 430.37534 | C39: ₽
A41: РЕЗУЛЬТАТ
A42: Справедливая цена | B42: =$B$39 -> 430.37534 | C42: ₽ | D42: Главный вывод модели
A43: Текущая цена | B43: =Сводка!$D$10 -> 176.45 | C43: ₽ | D43: Берётся со «Сводки» (столбец D)
A44: Зона покупки: цена не выше | B44: =$B$42*(1-Параметры!$B$10) -> 331.38901 | C44: ₽ | D44: Справедливая минус скидка из «Параметров»
A45: Цена продажи | B45: =$B$42*(1+Параметры!$B$11) -> 507.8429 | C45: ₽ | D45: Справедливая плюс премия из «Параметров»
A46: Сигнал «приближается к продаже» от | B46: =$B$45*(1-Параметры!$B$12) -> 482.45076 | C46: ₽ | D46: За сколько % до цены продажи бот предупреждает
A47: Потенциал до справедливой | B47: =IF($B$43>0,$B$42/$B$43-1,0) -> 1.4390782 | C47: %
A48: До цены продажи | B48: =IF($B$43>0,$B$45/$B$43-1,0) -> 1.8781122 | C48: %
A49: Статус | B49: =IF($B$43<=$B$44,"ЗОНА ПОКУПКИ",IF($B$43>=$B$45,"ЦЕНА ПРОДАЖИ",IF($B$43>=$B$46,"ПРИБЛИЖАЕТСЯ К ПРОДАЖЕ","ДЕРЖАТЬ"))) -> ЗОНА ПОКУПКИ | D49: Слом тезиса — отдельный сигнал, см. ниже
A51: ПЕРЕКРЁСТНАЯ ПРОВЕРКА
A52: Доля ИИ в справедливой цене | B52: =IF($B$42>0,$B$35/$B$42,0) -> 0.38267358 | C52: %
A53: ИИ-прибавка при скидке рынка РФ к США | B53: =IF($B$19>0,$B$35/$B$19*Параметры!$B$24,0) -> 32.938655 | C53: ₽ | D53: Если ИИ-бизнес рынок оценит с той же скидкой к американским аналогам, что и весь Яндекс (~0,2).
A54: Справедливая цена при этой скидке | B54: =$B$31+$B$53 -> 238.98585 | C54: ₽ | D54: Консервативный ориентир.
A55: Дивдоходность к текущей цене | B55: =IF($B$43>0,$B$28/$B$43,0) -> 0.1389607 | C55: %
A56: Полная доходность выплат к текущей цене | B56: =IF($B$43>0,$B$27/$B$43,0) -> 0.19851529 | C56: %
A57: EV/OIBDA 2026П при базовой цене (без ИИ) | B57: =IF($B$15>0,($B$31*$B$10+$B$14)/$B$15,0) -> 3.2521991 | C57: x | D57: Историческая норма для телекома РФ — 3,5–4,5x.
A58: EV/OIBDA 2026П при текущей цене | B58: =IF($B$15>0,($B$43*$B$10+$B$14)/$B$15,0) -> 3.0702082 | C58: x
A59: Базовая цена (без ИИ), если ставка = длинные ОФЗ + премия | B59: =IF(Параметры!$B$8+Параметры!$B$7+$B$12-$B$13>0,$B$27/(Параметры!$B$8+Параметры!$B$7+$B$12-$B$13),0) -> 170.03894 | C59: ₽ | D59: Строгий вариант: ставка по рынку длинных ОФЗ, рост прежний.
A60: Средняя цель 6 брокеров | B60: =248 -> 248 | C60: ₽ | D60: 215–289 ₽: Финам 243, Велес 289, БрокерКФ 230, Freedom 270, БКС 240, Т-Инвестиции 215; часть — до новой политики.
A62: ЧУВСТВИТЕЛЬНОСТЬ СПРАВЕДЛИВОЙ ЦЕНЫ, ₽: строки — премия за риск, столбцы — выплаты в год, млрд ₽
A63: премия за риск \ выплаты в год, млрд ₽ | B63: 55 | C63: 62.5 | D63: 70 | E63: 77.5 | F63: 85
A64: 0 | B64: =(B$63/$B$10/($B$11+$A64-$B$13)+$B$16*$B$17*$B$18*$B$19/(1+$B$11)^$B$20/$B$10)+$B$21*((($B$23*$B$15-$B$14)/$B$10)-(B$63/$B$10/($B$11+$A64-$B$13)))*((1+$B$24)/(1+$B$11))^$B$22 -> 414.44004 | C64: =(C$63/$B$10/($B$11+$A64-$B$13)+$B$16*$B$17*$B$18*$B$19/(1+$B$11)^$B$20/$B$10)+$B$21*((($B$23*$B$15-$B$14)/$B$10)-(C$63/$B$10/($B$11+$A64-$B$13)))*((1+$B$24)/(1+$B$11))^$B$22 -> 432.10744 | D64: =(D$63/$B$10/($B$11+$A64-$B$13)+$B$16*$B$17*$B$18*$B$19/(1+$B$11)^$B$20/$B$10)+$B$21*((($B$23*$B$15-$B$14)/$B$10)-(D$63/$B$10/($B$11+$A64-$B$13)))*((1+$B$24)/(1+$B$11))^$B$22 -> 449.77484 | E64: =(E$63/$B$10/($B$11+$A64-$B$13)+$B$16*$B$17*$B$18*$B$19/(1+$B$11)^$B$20/$B$10)+$B$21*((($B$23*$B$15-$B$14)/$B$10)-(E$63/$B$10/($B$11+$A64-$B$13)))*((1+$B$24)/(1+$B$11))^$B$22 -> 467.44225 | F64: =(F$63/$B$10/($B$11+$A64-$B$13)+$B$16*$B$17*$B$18*$B$19/(1+$B$11)^$B$20/$B$10)+$B$21*((($B$23*$B$15-$B$14)/$B$10)-(F$63/$B$10/($B$11+$A64-$B$13)))*((1+$B$24)/(1+$B$11))^$B$22 -> 485.10965
A65: 0.01 | B65: =(B$63/$B$10/($B$11+$A65-$B$13)+$B$16*$B$17*$B$18*$B$19/(1+$B$11)^$B$20/$B$10)+$B$21*((($B$23*$B$15-$B$14)/$B$10)-(B$63/$B$10/($B$11+$A65-$B$13)))*((1+$B$24)/(1+$B$11))^$B$22 -> 406.34248 | C65: =(C$63/$B$10/($B$11+$A65-$B$13)+$B$16*$B$17*$B$18*$B$19/(1+$B$11)^$B$20/$B$10)+$B$21*((($B$23*$B$15-$B$14)/$B$10)-(C$63/$B$10/($B$11+$A65-$B$13)))*((1+$B$24)/(1+$B$11))^$B$22 -> 422.90567 | D65: =(D$63/$B$10/($B$11+$A65-$B$13)+$B$16*$B$17*$B$18*$B$19/(1+$B$11)^$B$20/$B$10)+$B$21*((($B$23*$B$15-$B$14)/$B$10)-(D$63/$B$10/($B$11+$A65-$B$13)))*((1+$B$24)/(1+$B$11))^$B$22 -> 439.46886 | E65: =(E$63/$B$10/($B$11+$A65-$B$13)+$B$16*$B$17*$B$18*$B$19/(1+$B$11)^$B$20/$B$10)+$B$21*((($B$23*$B$15-$B$14)/$B$10)-(E$63/$B$10/($B$11+$A65-$B$13)))*((1+$B$24)/(1+$B$11))^$B$22 -> 456.03205 | F65: =(F$63/$B$10/($B$11+$A65-$B$13)+$B$16*$B$17*$B$18*$B$19/(1+$B$11)^$B$20/$B$10)+$B$21*((($B$23*$B$15-$B$14)/$B$10)-(F$63/$B$10/($B$11+$A65-$B$13)))*((1+$B$24)/(1+$B$11))^$B$22 -> 472.59524
A66: 0.02 | B66: =(B$63/$B$10/($B$11+$A66-$B$13)+$B$16*$B$17*$B$18*$B$19/(1+$B$11)^$B$20/$B$10)+$B$21*((($B$23*$B$15-$B$14)/$B$10)-(B$63/$B$10/($B$11+$A66-$B$13)))*((1+$B$24)/(1+$B$11))^$B$22 -> 399.19757 | C66: =(C$63/$B$10/($B$11+$A66-$B$13)+$B$16*$B$17*$B$18*$B$19/(1+$B$11)^$B$20/$B$10)+$B$21*((($B$23*$B$15-$B$14)/$B$10)-(C$63/$B$10/($B$11+$A66-$B$13)))*((1+$B$24)/(1+$B$11))^$B$22 -> 414.78646 | D66: =(D$63/$B$10/($B$11+$A66-$B$13)+$B$16*$B$17*$B$18*$B$19/(1+$B$11)^$B$20/$B$10)+$B$21*((($B$23*$B$15-$B$14)/$B$10)-(D$63/$B$10/($B$11+$A66-$B$13)))*((1+$B$24)/(1+$B$11))^$B$22 -> 430.37534 | E66: =(E$63/$B$10/($B$11+$A66-$B$13)+$B$16*$B$17*$B$18*$B$19/(1+$B$11)^$B$20/$B$10)+$B$21*((($B$23*$B$15-$B$14)/$B$10)-(E$63/$B$10/($B$11+$A66-$B$13)))*((1+$B$24)/(1+$B$11))^$B$22 -> 445.96423 | F66: =(F$63/$B$10/($B$11+$A66-$B$13)+$B$16*$B$17*$B$18*$B$19/(1+$B$11)^$B$20/$B$10)+$B$21*((($B$23*$B$15-$B$14)/$B$10)-(F$63/$B$10/($B$11+$A66-$B$13)))*((1+$B$24)/(1+$B$11))^$B$22 -> 461.55311
A67: 0.03 | B67: =(B$63/$B$10/($B$11+$A67-$B$13)+$B$16*$B$17*$B$18*$B$19/(1+$B$11)^$B$20/$B$10)+$B$21*((($B$23*$B$15-$B$14)/$B$10)-(B$63/$B$10/($B$11+$A67-$B$13)))*((1+$B$24)/(1+$B$11))^$B$22 -> 392.84654 | C67: =(C$63/$B$10/($B$11+$A67-$B$13)+$B$16*$B$17*$B$18*$B$19/(1+$B$11)^$B$20/$B$10)+$B$21*((($B$23*$B$15-$B$14)/$B$10)-(C$63/$B$10/($B$11+$A67-$B$13)))*((1+$B$24)/(1+$B$11))^$B$22 -> 407.56938 | D67: =(D$63/$B$10/($B$11+$A67-$B$13)+$B$16*$B$17*$B$18*$B$19/(1+$B$11)^$B$20/$B$10)+$B$21*((($B$23*$B$15-$B$14)/$B$10)-(D$63/$B$10/($B$11+$A67-$B$13)))*((1+$B$24)/(1+$B$11))^$B$22 -> 422.29221 | E67: =(E$63/$B$10/($B$11+$A67-$B$13)+$B$16*$B$17*$B$18*$B$19/(1+$B$11)^$B$20/$B$10)+$B$21*((($B$23*$B$15-$B$14)/$B$10)-(E$63/$B$10/($B$11+$A67-$B$13)))*((1+$B$24)/(1+$B$11))^$B$22 -> 437.01505 | F67: =(F$63/$B$10/($B$11+$A67-$B$13)+$B$16*$B$17*$B$18*$B$19/(1+$B$11)^$B$20/$B$10)+$B$21*((($B$23*$B$15-$B$14)/$B$10)-(F$63/$B$10/($B$11+$A67-$B$13)))*((1+$B$24)/(1+$B$11))^$B$22 -> 451.73789
A68: 0.04 | B68: =(B$63/$B$10/($B$11+$A68-$B$13)+$B$16*$B$17*$B$18*$B$19/(1+$B$11)^$B$20/$B$10)+$B$21*((($B$23*$B$15-$B$14)/$B$10)-(B$63/$B$10/($B$11+$A68-$B$13)))*((1+$B$24)/(1+$B$11))^$B$22 -> 387.16404 | C68: =(C$63/$B$10/($B$11+$A68-$B$13)+$B$16*$B$17*$B$18*$B$19/(1+$B$11)^$B$20/$B$10)+$B$21*((($B$23*$B$15-$B$14)/$B$10)-(C$63/$B$10/($B$11+$A68-$B$13)))*((1+$B$24)/(1+$B$11))^$B$22 -> 401.11199 | D68: =(D$63/$B$10/($B$11+$A68-$B$13)+$B$16*$B$17*$B$18*$B$19/(1+$B$11)^$B$20/$B$10)+$B$21*((($B$23*$B$15-$B$14)/$B$10)-(D$63/$B$10/($B$11+$A68-$B$13)))*((1+$B$24)/(1+$B$11))^$B$22 -> 415.05994 | E68: =(E$63/$B$10/($B$11+$A68-$B$13)+$B$16*$B$17*$B$18*$B$19/(1+$B$11)^$B$20/$B$10)+$B$21*((($B$23*$B$15-$B$14)/$B$10)-(E$63/$B$10/($B$11+$A68-$B$13)))*((1+$B$24)/(1+$B$11))^$B$22 -> 429.00789 | F68: =(F$63/$B$10/($B$11+$A68-$B$13)+$B$16*$B$17*$B$18*$B$19/(1+$B$11)^$B$20/$B$10)+$B$21*((($B$23*$B$15-$B$14)/$B$10)-(F$63/$B$10/($B$11+$A68-$B$13)))*((1+$B$24)/(1+$B$11))^$B$22 -> 442.95584
A69: Центр таблицы (жёлтая ячейка) = базовый сценарий; должен совпадать со справедливой ценой.
A71: ЧУВСТВИТЕЛЬНОСТЬ СПРАВЕДЛИВОЙ ЦЕНЫ, ₽: строки — доля МТС на рынке ИИ, столбцы — рынок генИИ в РФ 2030, млрд ₽
A72: доля МТС на рынке ИИ \ рынок генИИ в РФ 2030, млрд ₽ | B72: 400 | C72: 590 | D72: 778 | E72: 950 | F72: 1120
A73: 0.01 | B73: =($B$8/$B$10/($B$11+$B$12-$B$13)+B$72*$A73*$B$18*$B$19/(1+$B$11)^$B$20/$B$10)+$B$21*((($B$23*$B$15-$B$14)/$B$10)-($B$8/$B$10/($B$11+$B$12-$B$13)))*((1+$B$24)/(1+$B$11))^$B$22 -> 282.61711 | C73: =($B$8/$B$10/($B$11+$B$12-$B$13)+C$72*$A73*$B$18*$B$19/(1+$B$11)^$B$20/$B$10)+$B$21*((($B$23*$B$15-$B$14)/$B$10)-($B$8/$B$10/($B$11+$B$12-$B$13)))*((1+$B$24)/(1+$B$11))^$B$22 -> 290.66125 | D73: =($B$8/$B$10/($B$11+$B$12-$B$13)+D$72*$A73*$B$18*$B$19/(1+$B$11)^$B$20/$B$10)+$B$21*((($B$23*$B$15-$B$14)/$B$10)-($B$8/$B$10/($B$11+$B$12-$B$13)))*((1+$B$24)/(1+$B$11))^$B$22 -> 298.62072 | E73: =($B$8/$B$10/($B$11+$B$12-$B$13)+E$72*$A73*$B$18*$B$19/(1+$B$11)^$B$20/$B$10)+$B$21*((($B$23*$B$15-$B$14)/$B$10)-($B$8/$B$10/($B$11+$B$12-$B$13)))*((1+$B$24)/(1+$B$11))^$B$22 -> 305.90279 | F73: =($B$8/$B$10/($B$11+$B$12-$B$13)+F$72*$A73*$B$18*$B$19/(1+$B$11)^$B$20/$B$10)+$B$21*((($B$23*$B$15-$B$14)/$B$10)-($B$8/$B$10/($B$11+$B$12-$B$13)))*((1+$B$24)/(1+$B$11))^$B$22 -> 313.10018
A74: 0.03 | B74: =($B$8/$B$10/($B$11+$B$12-$B$13)+B$72*$A74*$B$18*$B$19/(1+$B$11)^$B$20/$B$10)+$B$21*((($B$23*$B$15-$B$14)/$B$10)-($B$8/$B$10/($B$11+$B$12-$B$13)))*((1+$B$24)/(1+$B$11))^$B$22 -> 316.48719 | C74: =($B$8/$B$10/($B$11+$B$12-$B$13)+C$72*$A74*$B$18*$B$19/(1+$B$11)^$B$20/$B$10)+$B$21*((($B$23*$B$15-$B$14)/$B$10)-($B$8/$B$10/($B$11+$B$12-$B$13)))*((1+$B$24)/(1+$B$11))^$B$22 -> 340.61962 | D74: =($B$8/$B$10/($B$11+$B$12-$B$13)+D$72*$A74*$B$18*$B$19/(1+$B$11)^$B$20/$B$10)+$B$21*((($B$23*$B$15-$B$14)/$B$10)-($B$8/$B$10/($B$11+$B$12-$B$13)))*((1+$B$24)/(1+$B$11))^$B$22 -> 364.49803 | E74: =($B$8/$B$10/($B$11+$B$12-$B$13)+E$72*$A74*$B$18*$B$19/(1+$B$11)^$B$20/$B$10)+$B$21*((($B$23*$B$15-$B$14)/$B$10)-($B$8/$B$10/($B$11+$B$12-$B$13)))*((1+$B$24)/(1+$B$11))^$B$22 -> 386.34423 | F74: =($B$8/$B$10/($B$11+$B$12-$B$13)+F$72*$A74*$B$18*$B$19/(1+$B$11)^$B$20/$B$10)+$B$21*((($B$23*$B$15-$B$14)/$B$10)-($B$8/$B$10/($B$11+$B$12-$B$13)))*((1+$B$24)/(1+$B$11))^$B$22 -> 407.93641
A75: 0.05 | B75: =($B$8/$B$10/($B$11+$B$12-$B$13)+B$72*$A75*$B$18*$B$19/(1+$B$11)^$B$20/$B$10)+$B$21*((($B$23*$B$15-$B$14)/$B$10)-($B$8/$B$10/($B$11+$B$12-$B$13)))*((1+$B$24)/(1+$B$11))^$B$22 -> 350.35727 | C75: =($B$8/$B$10/($B$11+$B$12-$B$13)+C$72*$A75*$B$18*$B$19/(1+$B$11)^$B$20/$B$10)+$B$21*((($B$23*$B$15-$B$14)/$B$10)-($B$8/$B$10/($B$11+$B$12-$B$13)))*((1+$B$24)/(1+$B$11))^$B$22 -> 390.57799 | D75: =($B$8/$B$10/($B$11+$B$12-$B$13)+D$72*$A75*$B$18*$B$19/(1+$B$11)^$B$20/$B$10)+$B$21*((($B$23*$B$15-$B$14)/$B$10)-($B$8/$B$10/($B$11+$B$12-$B$13)))*((1+$B$24)/(1+$B$11))^$B$22 -> 430.37534 | E75: =($B$8/$B$10/($B$11+$B$12-$B$13)+E$72*$A75*$B$18*$B$19/(1+$B$11)^$B$20/$B$10)+$B$21*((($B$23*$B$15-$B$14)/$B$10)-($B$8/$B$10/($B$11+$B$12-$B$13)))*((1+$B$24)/(1+$B$11))^$B$22 -> 466.78568 | F75: =($B$8/$B$10/($B$11+$B$12-$B$13)+F$72*$A75*$B$18*$B$19/(1+$B$11)^$B$20/$B$10)+$B$21*((($B$23*$B$15-$B$14)/$B$10)-($B$8/$B$10/($B$11+$B$12-$B$13)))*((1+$B$24)/(1+$B$11))^$B$22 -> 502.77264
A76: 0.075 | B76: =($B$8/$B$10/($B$11+$B$12-$B$13)+B$72*$A76*$B$18*$B$19/(1+$B$11)^$B$20/$B$10)+$B$21*((($B$23*$B$15-$B$14)/$B$10)-($B$8/$B$10/($B$11+$B$12-$B$13)))*((1+$B$24)/(1+$B$11))^$B$22 -> 392.69487 | C76: =($B$8/$B$10/($B$11+$B$12-$B$13)+C$72*$A76*$B$18*$B$19/(1+$B$11)^$B$20/$B$10)+$B$21*((($B$23*$B$15-$B$14)/$B$10)-($B$8/$B$10/($B$11+$B$12-$B$13)))*((1+$B$24)/(1+$B$11))^$B$22 -> 453.02596 | D76: =($B$8/$B$10/($B$11+$B$12-$B$13)+D$72*$A76*$B$18*$B$19/(1+$B$11)^$B$20/$B$10)+$B$21*((($B$23*$B$15-$B$14)/$B$10)-($B$8/$B$10/($B$11+$B$12-$B$13)))*((1+$B$24)/(1+$B$11))^$B$22 -> 512.72198 | E76: =($B$8/$B$10/($B$11+$B$12-$B$13)+E$72*$A76*$B$18*$B$19/(1+$B$11)^$B$20/$B$10)+$B$21*((($B$23*$B$15-$B$14)/$B$10)-($B$8/$B$10/($B$11+$B$12-$B$13)))*((1+$B$24)/(1+$B$11))^$B$22 -> 567.33748 | F76: =($B$8/$B$10/($B$11+$B$12-$B$13)+F$72*$A76*$B$18*$B$19/(1+$B$11)^$B$20/$B$10)+$B$21*((($B$23*$B$15-$B$14)/$B$10)-($B$8/$B$10/($B$11+$B$12-$B$13)))*((1+$B$24)/(1+$B$11))^$B$22 -> 621.31793
A77: 0.1 | B77: =($B$8/$B$10/($B$11+$B$12-$B$13)+B$72*$A77*$B$18*$B$19/(1+$B$11)^$B$20/$B$10)+$B$21*((($B$23*$B$15-$B$14)/$B$10)-($B$8/$B$10/($B$11+$B$12-$B$13)))*((1+$B$24)/(1+$B$11))^$B$22 -> 435.03248 | C77: =($B$8/$B$10/($B$11+$B$12-$B$13)+C$72*$A77*$B$18*$B$19/(1+$B$11)^$B$20/$B$10)+$B$21*((($B$23*$B$15-$B$14)/$B$10)-($B$8/$B$10/($B$11+$B$12-$B$13)))*((1+$B$24)/(1+$B$11))^$B$22 -> 515.47392 | D77: =($B$8/$B$10/($B$11+$B$12-$B$13)+D$72*$A77*$B$18*$B$19/(1+$B$11)^$B$20/$B$10)+$B$21*((($B$23*$B$15-$B$14)/$B$10)-($B$8/$B$10/($B$11+$B$12-$B$13)))*((1+$B$24)/(1+$B$11))^$B$22 -> 595.06861 | E77: =($B$8/$B$10/($B$11+$B$12-$B$13)+E$72*$A77*$B$18*$B$19/(1+$B$11)^$B$20/$B$10)+$B$21*((($B$23*$B$15-$B$14)/$B$10)-($B$8/$B$10/($B$11+$B$12-$B$13)))*((1+$B$24)/(1+$B$11))^$B$22 -> 667.88929 | F77: =($B$8/$B$10/($B$11+$B$12-$B$13)+F$72*$A77*$B$18*$B$19/(1+$B$11)^$B$20/$B$10)+$B$21*((($B$23*$B$15-$B$14)/$B$10)-($B$8/$B$10/($B$11+$B$12-$B$13)))*((1+$B$24)/(1+$B$11))^$B$22 -> 739.86321
A78: Центр таблицы (жёлтая ячейка) = базовый сценарий; должен совпадать со справедливой ценой.
A80: ТЕЗИС И УСЛОВИЯ ЕГО СЛОМА (сигнал при любой цене)
A81: Тезис: Крупнейший оператор связи с растущей экосистемой (финтех, реклама, облака MWS). Для акционера главное — деньги: около 20% цены в год возвращается дивидендами и выкупом. При снижении ставки дешевеет обслуживание огромного долга, и оценка растёт. Сверху — MWS AI и облака: небольшая, но растущая доля российского ИИ-рынка.
A82: • Выплаты акционерам за 2027 год ниже 70 млрд ₽ или отказ от выкупа акций
A83: • Чистый долг без аренды выше 2,0x OIBDA
A84: • Допэмиссия или выкуп активов у АФК «Система» в долг
A85: • Ставка ЦБ снова растёт выше 16% (большая часть долга — плавающая)
A87: ЧТО ОТСЛЕЖИВАЕТ БОТ В НОВОСТЯХ
A88: • Отчёт за 3К 2026 (ожидается ~16.11.2026): OIBDA, долг, FCF
A89: • Решение совета о первой выплате по новой политике (за 9М 2026, январь 2027)
A90: • Параметры выкупа акций, IPO дочерних компаний
A91: • Ставка ЦБ — она определяет процентные расходы МТС
... A106: ValueAdd VC — выручка и оценка Anthropic: https://valueaddvc.com/blog/anthropic-revenue-hits-47b-run-rate-how-it-passed-openai-in-just-five-months

Sheet GAZP
A1: GAZP — Газпром: модель справедливой стоимости
A2: Метод: EV/EBITDA на нормализованную EBITDA + два опциона: «Северные потоки» и «Сила Байкала»
A3: База: нормализованная EBITDA × мультипликатор минус чистый долг (дивидендов нет четвёртый год). Сверху — два опциона: вероятность × (стоимость дополнительного денежного потока − капзатраты). Маржа опционов собрана из явных вводных: цена − экспортная пошлина − добыча и НДПИ − транспорт. Долгосрочные долларовые потоки дисконтируются ставкой, очищенной от ожидаемого ослабления рубля.
A4: Синий — вводные (меняйте их), чёрный — формулы, зелёный — ссылки на другие листы, жёлтый — главные рычаги модели.
A6: Показатель | B6: Значение | C6: Ед. | D6: Источник / комментарий
A7: ВВОДНЫЕ
A8: Нормализованная EBITDA (без опционов) | B8: 3350 | C8: млрд ₽ | D8: LTM на 30.06.2026: 3 348 млрд; 2025: 2 920 млрд; 1П 2026: 1 977 млрд, но 1П сезонно сильнее (53% EBITDA 2025). В июне 2026 компания ждала +6–7% за 2026 (~3,1 трлн). Берём LTM.
A9: Справедливый EV/EBITDA | B9: 2.5 | C9: x | D9: Исторически 2,5–3,5x, но при дивидендах. Без выплат и с убыточным газовым сегментом — нижняя граница.
A10: Скорр. чистый долг | B10: 6055 | C10: млрд ₽ | D10: На 30.06.2026, ЧД/EBITDA 1,81x (The Moscow Times, Fomag).
A11: Акций выпущено | B11: 23.674 | C11: млрд шт | D11: 23,674 млрд; × 114,75 ₽ = 2 716 млрд ₽ капитализации; казначейских акций на 31.12.2025 не было.
A12: Доли меньшинства в «дочках» (рыночная оценка) | B12: 360 | C12: млрд ₽ | D12: EBITDA консолидированная, поэтому чужие доли вычитаем: 4,3% «Газпром нефти» (~117 млрд по рынку), 22,5% «Сахалинской Энерджи» (~205 млрд на дату покупки), миноритарии Мосэнерго, ТГК-1, ОГК-2 (~40 млрд). Оценка модели — уточнить по МСФО.
A13: Доли в ассоциированных компаниях и СП | B13: 520 | C13: млрд ₽ | D13: Их прибыли нет в EBITDA: «Славнефть», «Арктикгаз», «Мессояха» и др. Балансовая стоимость 1 297 млрд (30.09.2024, МСФО); берём 0,4 баланса — дисконт, как у самой «Газпром нефти» (~0,6x). Оценка модели.
A14: Ставка дисконтирования (рубли) | B14: =Параметры!$B$9 -> 0.19 | C14: % | D14: Из «Параметров».
A15: Курс USD/RUB | B15: =Параметры!$B$13 -> 85 | C15: ₽ | D15: Из «Параметров».
A16: Ослабление рубля в год (долгосрочно) | B16: 0.04 | C16: % | D16: Разница инфляций РФ и США. Без неё 30-летние долларовые потоки по постоянному курсу дисконтировались бы рублёвой ставкой — это занижало опционы.
A17: Налог на прибыль | B17: 0.25 | C17: % | D17: С 2025 года 25%.
A18: Экспортная пошлина на трубопроводный газ | B18: 0.3 | C18: % | D18: 30% от цены — для Европы и Китая (льгота для поставок в Китай была только по НДПИ восточных месторождений).
A19: Добыча + НДПИ, $/тыс. м³ | B19: 40 | C19: $ | D19: Западная Сибирь, стандартный НДПИ ~2 400 ₽/тыс. м³ (~$28) + подъём газа ~$10–12. Оценка модели.
A20: «Северные потоки»: вероятность перезапуска | B20: 0.15 | C20: % | D20: NYT 17.10.2026: США видят перезапуск частью мирного плана; европейские переговорщики против, запрет на российский газ закреплён в законе ЕС (вступил 03.02.2026). Оценка модели — 15%.
A21: «Северные потоки»: объём, млрд м³ в год | B21: 27.5 | C21: млрд м³ | D21: Цела одна нитка «Северного потока — 2» (27,5 млрд м³); обе нитки СП-1 и нитка A СП-2 повреждены в 2022.
A22: «Северные потоки»: цена в Европе, $/тыс. м³ | B22: 300 | C22: $ | D22: Материалы бюджета: прочие покупатели $562 в 2026 (пик TTF), $362 в 2028, $323 в 2029. После возврата российского газа цены снизятся — берём $300.
A23: «Северные потоки»: транспорт до Балтики, $/тыс. м³ | B23: 20 | C23: $ | D23: Существующая ГТС ~3 000 км и своя труба: только операционные расходы и топливный газ.
A24: «Северные потоки»: лет до запуска | B24: 2 | C24: лет | D24: Нужны мирное соглашение, отмена запрета ЕС и проверка трубы.
A25: «Северные потоки»: капзатраты на ввод | B25: 50 | C25: млрд ₽ | D25: Инспекция и подключение уцелевшей нитки; оценка модели.
A26: «Северные потоки»: когда тратить, лет | B26: 1 | C26: лет
A27: «Сила Байкала»: вероятность подписания контракта | B27: 0.5 | C27: % | D27: Бывшая «Сила Сибири-2», переименована в 2026. Новак 21.10.2026: Газпром и CNPC могут согласовать коммерческие условия до конца года; цена и финансирование не решены.
A28: «Сила Байкала»: объём, млрд м³ в год | B28: 50 | C28: млрд м³ | D28: Проектная мощность 50 млрд м³ в год, маршрут через Монголию.
A29: «Сила Байкала»: цена для Китая, $/тыс. м³ | B29: 247.9 | C29: $ | D29: Как по «Силе Сибири» (решение пользователя). Материалы бюджета (ТАСС, 02.10.2026): 2025 — $240,3; 2026 — $247,9; 2027 — $251,3; 2028 — $247,8; 2029 — $246,4. Риск: по FT, Китай добивается намного более низкой цены.
A30: «Сила Байкала»: транспорт и транзит Монголии, $/тыс. м³ | B30: 25 | C30: $ | D30: ~3 500 км новой трубы: топливный газ и обслуживание ~$10–15 + транзит через Монголию ~$10–15 (тариф не раскрыт). Стройка трубы — отдельно, в капзатратах.
A31: «Сила Байкала»: срок контракта, лет | B31: 30 | C31: лет | D31: Как у «Силы Сибири-1» (30 лет).
A32: «Сила Байкала»: лет до полных объёмов | B32: 7.5 | C32: лет | D32: Первый газ ~2031, плато не раньше 2034–2035 (The Moscow Times, 24.04.2026); с учётом разгона — эквивалент полных объёмов с ~2033.
A33: «Сила Байкала»: капзатраты | B33: 1000 | C33: млрд ₽ | D33: Предварительная официальная оценка ~1 трлн ₽; критики (Крутихин, The Moscow Times 18.09.2026) считают её заниженной. См. точку окупаемости ниже.
A34: «Сила Байкала»: середина стройки, лет | B34: 4 | C34: лет | D34: Строительство ~2028–2032.
A35: Мир: вероятность мира и снятия санкций | B35: =Параметры!$B$15 -> 0.5 | C35: % | D35: Из «Параметров».
A36: Мир: лет до снятия санкций | B36: =Параметры!$B$16 -> 5 | C36: лет | D36: Из «Параметров».
A37: Мир: EV/EBITDA как до 2022 года | B37: 3.2 | C37: x | D37: Газпром в 2017–2021 стоил ~3–3,5x EBITDA (при дивидендах).
A38: Мир: вероятность запуска «Северных потоков» после мира | B38: 0.6 | C38: % | D38: Если санкции сняты, снят и запрет ЕС на российский газ. Но Европа перешла на СПГ и решение политическое — берём 60%.
A39: Мир: рост показателя до года мира, % в год | B39: 0.04 | C39: % | D39: Рост EBITDA в среднем за 5 лет.
A41: РАСЧЁТ
A42: Справедливая стоимость бизнеса (EV), база | B42: =$B$8*$B$9 -> 8375 | C42: млрд ₽
A43: Стоимость акционерного капитала, база | B43: =$B$42-$B$10-$B$12+$B$13 -> 2480 | C43: млрд ₽
A44: Справедливая цена без опционов | B44: =IF($B$11>0,$B$43/$B$11,0) -> 104.75627 | C44: ₽
A45: Ставка для долгосрочных долларовых потоков | B45: =((1+$B$14)/(1+$B$16)-1) -> 0.14423077 | C45: % | D45: Рублёвая ставка за вычетом ожидаемого ослабления рубля.
A46: «Северные потоки»: EBITDA на 1 000 м³ | B46: =($B$22*(1-$B$18)-$B$19-$B$23) -> 150 | C46: $ | D46: Цена × (1 − пошлина) − добыча и НДПИ − транспорт.
A47: «Северные потоки»: доп. EBITDA в год | B47: =$B$21*$B$46*$B$15/1000 -> 350.625 | C47: млрд ₽
A48: «Северные потоки»: стоимость, если перезапуск | B48: =$B$47*$B$9/(1+$B$45)^$B$24-$B$25/(1+$B$45)^$B$26 -> 625.81032 | C48: млрд ₽ | D48: Тем же мультипликатором, что и база: без долгого контракта поставки могут снова прекратиться.
A49: «Северные потоки»: вклад в цену (× вероятность) | B49: =$B$20*$B$48/$B$11 -> 3.9651748 | C49: ₽
A50: «Сила Байкала»: EBITDA на 1 000 м³ | B50: =($B$29*(1-$B$18)-$B$19-$B$30) -> 108.53 | C50: $ | D50: Цена × (1 − пошлина) − добыча и НДПИ − транспорт и транзит.
A51: «Сила Байкала»: доп. EBITDA в год на плато | B51: =$B$28*$B$50*$B$15/1000 -> 461.2525 | C51: млрд ₽
A52: «Сила Байкала»: денежный поток после налога на прибыль | B52: =$B$51*(1-$B$17)+$B$17*$B$33/$B$31 -> 354.27271 | C52: млрд ₽ | D52: Налог с EBITDA минус амортизация трубы.
A53: «Сила Байкала»: коэффициент аннуитета контракта | B53: =(1-(1+$B$45)^(-$B$31))/$B$45 -> 6.8115653 | C53: x
A54: «Сила Байкала»: стоимость, если контракт подписан | B54: =$B$52*$B$53/(1+$B$45)^$B$32-$B$33/(1+$B$45)^$B$34 -> 295.10926 | C54: млрд ₽
A55: «Сила Байкала»: вклад в цену (× вероятность) | B55: =$B$27*$B$54/$B$11 -> 6.2327713 | C55: ₽
A56: Справедливая цена без мира | B56: =$B$44+$B$49+$B$55 -> 114.95422 | C56: ₽
A57: Мир: цена в мирном режиме на сегодняшних показателях | B57: =($B$8*$B$37-$B$10-$B$12+$B$13)/$B$11 -> 203.81009 | C57: ₽ | D57: Если бы рынок уже сегодня оценивал компанию как до 2022 года. Без опционов — они считаются отдельно.
A58: Мир: прибавка к цене сегодня | B58: =$B$35*($B$57-$B$44)*((1+$B$39)/(1+$B$14))^$B$36 -> 25.250681 | C58: ₽ | D58: Вероятность × разница цен × рост показателя до года мира, приведённый к сегодняшнему дню.
A59: Мир: «Северные потоки» после мира, вклад в цену | B59: =$B$35*(1-$B$20)*$B$38*($B$47*$B$9/(1+$B$45)^$B$36-$B$25/(1+$B$45)^($B$36-1))/$B$11 -> 4.4995636 | C59: ₽ | D59: Запуск в год мира, если до этого не запустили раньше.
A60: Справедливая цена с миром | B60: =$B$56+$B$58+$B$59 -> 144.70446 | C60: ₽
A62: РЕЗУЛЬТАТ
A63: Справедливая цена | B63: =$B$60 -> 144.70446 | C63: ₽ | D63: Главный вывод модели
A64: Текущая цена | B64: =Сводка!$D$11 -> 114.75 | C64: ₽ | D64: Берётся со «Сводки» (столбец D)
A65: Зона покупки: цена не выше | B65: =$B$63*(1-Параметры!$B$10) -> 111.42244 | C65: ₽ | D65: Справедливая минус скидка из «Параметров»
A66: Цена продажи | B66: =$B$63*(1+Параметры!$B$11) -> 170.75127 | C66: ₽ | D66: Справедливая плюс премия из «Параметров»
A67: Сигнал «приближается к продаже» от | B67: =$B$66*(1-Параметры!$B$12) -> 162.2137 | C67: ₽ | D67: За сколько % до цены продажи бот предупреждает
A68: Потенциал до справедливой | B68: =IF($B$64>0,$B$63/$B$64-1,0) -> 0.26104108 | C68: %
A69: До цены продажи | B69: =IF($B$64>0,$B$66/$B$64-1,0) -> 0.48802847 | C69: %
A70: Статус | B70: =IF($B$64<=$B$65,"ЗОНА ПОКУПКИ",IF($B$64>=$B$66,"ЦЕНА ПРОДАЖИ",IF($B$64>=$B$67,"ПРИБЛИЖАЕТСЯ К ПРОДАЖЕ","ДЕРЖАТЬ"))) -> ДЕРЖАТЬ | D70: Слом тезиса — отдельный сигнал, см. ниже
A72: ПЕРЕКРЁСТНАЯ ПРОВЕРКА
A73: «Северные потоки»: прибавка к цене при 100% перезапуске | B73: =$B$48/$B$11 -> 26.434499 | C73: ₽ | D73: Сколько добавит перезапуск, если он точно случится.
A74: «Сила Байкала»: прибавка к цене при подписании | B74: =$B$54/$B$11 -> 12.465543 | C74: ₽ | D74: Минус означал бы, что проект уничтожает стоимость для акционеров.
A75: «Сила Байкала»: маржа окупаемости, $/тыс. м³ | B75: =IF($B$53>0,(($B$33/(1+$B$45)^$B$34)*(1+$B$45)^$B$32/$B$53-$B$17*$B$33/$B$31)/(1-$B$17)*1000/($B$28*$B$15),0) -> 71.193132 | C75: $ | D75: При марже ниже этой проект не окупает капзатраты.
A76: «Сила Байкала»: цена для Китая для окупаемости, $/тыс. м³ | B76: =($B$75+$B$19+$B$30)/(1-$B$18) -> 194.56162 | C76: $ | D76: Если по контракту цена выйдет ниже этой — подписание будет плохой новостью для акционеров.
A77: EV/EBITDA при текущей цене | B77: =IF($B$8>0,($B$64*$B$11+$B$10+$B$12-$B$13)/$B$8,0) -> 2.5706243 | C77: x
A78: Средняя цель 12 аналитиков | B78: =141.33 -> 141.33 | C78: ₽ | D78: etpinvest, 23.10.2026: 100–185 ₽; 6 «покупать», 6 «держать».
A80: ЧУВСТВИТЕЛЬНОСТЬ СПРАВЕДЛИВОЙ ЦЕНЫ, ₽: строки — EV/EBITDA, столбцы — EBITDA, млрд ₽
A81: EV/EBITDA \ EBITDA, млрд ₽ | B81: 2850 | C81: 3100 | D81: 3350 | E81: 3600 | F81: 3850
A82: 2 | B82: =((B$81*$A82-$B$10-$B$12+$B$13)/$B$11+$B$20*($B$21*($B$22*(1-$B$18)-$B$19-$B$23)*$B$15/1000*$A82/(1+((1+$B$14)/(1+$B$16)-1))^$B$24-$B$25/(1+((1+$B$14)/(1+$B$16)-1))^$B$26)/$B$11+$B$27*((($B$28*($B$29*(1-$B$18)-$B$19-$B$30)*$B$15/1000)*(1-$B$17)+$B$17*$B$33/$B$31)*(1-(1+((1+$B$14)/(1+$B$16)-1))^(-$B$31))/((1+$B$14)/(1+$B$16)-1)/(1+((1+$B$14)/(1+$B$16)-1))^$B$32-$B$33/(1+((1+$B$14)/(1+$B$16)-1))^$B$34)/$B$11)+$B$35*(((B$81*$B$37-$B$10-$B$12+$B$13)/$B$11)-((B$81*$A82-$B$10-$B$12+$B$13)/$B$11))*((1+$B$39)/(1+$B$14))^$B$36+$B$35*(1-$B$20)*$B$38*($B$21*($B$22*(1-$B$18)-$B$19-$B$23)*$B$15/1000*$A82/(1+((1+$B$14)/(1+$B$16)-1))^$B$36-$B$25/(1+((1+$B$14)/(1+$B$16)-1))^($B$36-1))/$B$11 -> 41.47562 | C82: =((C$81*$A82-$B$10-$B$12+$B$13)/$B$11+$B$20*($B$21*($B$22*(1-$B$18)-$B$19-$B$23)*$B$15/1000*$A82/(1+((1+$B$14)/(1+$B$16)-1))^$B$24-$B$25/(1+((1+$B$14)/(1+$B$16)-1))^$B$26)/$B$11+$B$27*((($B$28*($B$29*(1-$B$18)-$B$19-$B$30)*$B$15/1000)*(1-$B$17)+$B$17*$B$33/$B$31)*(1-(1+((1+$B$14)/(1+$B$16)-1))^(-$B$31))/((1+$B$14)/(1+$B$16)-1)/(1+((1+$B$14)/(1+$B$16)-1))^$B$32-$B$33/(1+((1+$B$14)/(1+$B$16)-1))^$B$34)/$B$11)+$B$35*(((C$81*$B$37-$B$10-$B$12+$B$13)/$B$11)-((C$81*$A82-$B$10-$B$12+$B$13)/$B$11))*((1+$B$39)/(1+$B$14))^$B$36+$B$35*(1-$B$20)*$B$38*($B$21*($B$22*(1-$B$18)-$B$19-$B$23)*$B$15/1000*$A82/(1+((1+$B$14)/(1+$B$16)-1))^$B$36-$B$25/(1+((1+$B$14)/(1+$B$16)-1))^($B$36-1))/$B$11 -> 65.826201 | D82: =((D$81*$A82-$B$10-$B$12+$B$13)/$B$11+$B$20*($B$21*($B$22*(1-$B$18)-$B$19-$B$23)*$B$15/1000*$A82/(1+((1+$B$14)/(1+$B$16)-1))^$B$24-$B$25/(1+((1+$B$14)/(1+$B$16)-1))^$B$26)/$B$11+$B$27*((($B$28*($B$29*(1-$B$18)-$B$19-$B$30)*$B$15/1000)*(1-$B$17)+$B$17*$B$33/$B$31)*(1-(1+((1+$B$14)/(1+$B$16)-1))^(-$B$31))/((1+$B$14)/(1+$B$16)-1)/(1+((1+$B$14)/(1+$B$16)-1))^$B$32-$B$33/(1+((1+$B$14)/(1+$B$16)-1))^$B$34)/$B$11)+$B$35*(((D$81*$B$37-$B$10-$B$12+$B$13)/$B$11)-((D$81*$A82-$B$10-$B$12+$B$13)/$B$11))*((1+$B$39)/(1+$B$14))^$B$36+$B$35*(1-$B$20)*$B$38*($B$21*($B$22*(1-$B$18)-$B$19-$B$23)*$B$15/1000*$A82/(1+((1+$B$14)/(1+$B$16)-1))^$B$36-$B$25/(1+((1+$B$14)/(1+$B$16)-1))^($B$36-1))/$B$11 -> 90.176781 | E82: =((E$81*$A82-$B$10-$B$12+$B$13)/$B$11+$B$20*($B$21*($B$22*(1-$B$18)-$B$19-$B$23)*$B$15/1000*$A82/(1+((1+$B$14)/(1+$B$16)-1))^$B$24-$B$25/(1+((1+$B$14)/(1+$B$16)-1))^$B$26)/$B$11+$B$27*((($B$28*($B$29*(1-$B$18)-$B$19-$B$30)*$B$15/1000)*(1-$B$17)+$B$17*$B$33/$B$31)*(1-(1+((1+$B$14)/(1+$B$16)-1))^(-$B$31))/((1+$B$14)/(1+$B$16)-1)/(1+((1+$B$14)/(1+$B$16)-1))^$B$32-$B$33/(1+((1+$B$14)/(1+$B$16)-1))^$B$34)/$B$11)+$B$35*(((E$81*$B$37-$B$10-$B$12+$B$13)/$B$11)-((E$81*$A82-$B$10-$B$12+$B$13)/$B$11))*((1+$B$39)/(1+$B$14))^$B$36+$B$35*(1-$B$20)*$B$38*($B$21*($B$22*(1-$B$18)-$B$19-$B$23)*$B$15/1000*$A82/(1+((1+$B$14)/(1+$B$16)-1))^$B$36-$B$25/(1+((1+$B$14)/(1+$B$16)-1))^($B$36-1))/$B$11 -> 114.52736 | F82: =((F$81*$A82-$B$10-$B$12+$B$13)/$B$11+$B$20*($B$21*($B$22*(1-$B$18)-$B$19-$B$23)*$B$15/1000*$A82/(1+((1+$B$14)/(1+$B$16)-1))^$B$24-$B$25/(1+((1+$B$14)/(1+$B$16)-1))^$B$26)/$B$11+$B$27*((($B$28*($B$29*(1-$B$18)-$B$19-$B$30)*$B$15/1000)*(1-$B$17)+$B$17*$B$33/$B$31)*(1-(1+((1+$B$14)/(1+$B$16)-1))^(-$B$31))/((1+$B$14)/(1+$B$16)-1)/(1+((1+$B$14)/(1+$B$16)-1))^$B$32-$B$33/(1+((1+$B$14)/(1+$B$16)-1))^$B$34)/$B$11)+$B$35*(((F$81*$B$37-$B$10-$B$12+$B$13)/$B$11)-((F$81*$A82-$B$10-$B$12+$B$13)/$B$11))*((1+$B$39)/(1+$B$14))^$B$36+$B$35*(1-$B$20)*$B$38*($B$21*($B$22*(1-$B$18)-$B$19-$B$23)*$B$15/1000*$A82/(1+((1+$B$14)/(1+$B$16)-1))^$B$36-$B$25/(1+((1+$B$14)/(1+$B$16)-1))^($B$36-1))/$B$11 -> 138.87794
A83: 2.25 | B83: =((B$81*$A83-$B$10-$B$12+$B$13)/$B$11+$B$20*($B$21*($B$22*(1-$B$18)-$B$19-$B$23)*$B$15/1000*$A83/(1+((1+$B$14)/(1+$B$16)-1))^$B$24-$B$25/(1+((1+$B$14)/(1+$B$16)-1))^$B$26)/$B$11+$B$27*((($B$28*($B$29*(1-$B$18)-$B$19-$B$30)*$B$15/1000)*(1-$B$17)+$B$17*$B$33/$B$31)*(1-(1+((1+$B$14)/(1+$B$16)-1))^(-$B$31))/((1+$B$14)/(1+$B$16)-1)/(1+((1+$B$14)/(1+$B$16)-1))^$B$32-$B$33/(1+((1+$B$14)/(1+$B$16)-1))^$B$34)/$B$11)+$B$35*(((B$81*$B$37-$B$10-$B$12+$B$13)/$B$11)-((B$81*$A83-$B$10-$B$12+$B$13)/$B$11))*((1+$B$39)/(1+$B$14))^$B$36+$B$35*(1-$B$20)*$B$38*($B$21*($B$22*(1-$B$18)-$B$19-$B$23)*$B$15/1000*$A83/(1+((1+$B$14)/(1+$B$16)-1))^$B$36-$B$25/(1+((1+$B$14)/(1+$B$16)-1))^($B$36-1))/$B$11 -> 64.805392 | C83: =((C$81*$A83-$B$10-$B$12+$B$13)/$B$11+$B$20*($B$21*($B$22*(1-$B$18)-$B$19-$B$23)*$B$15/1000*$A83/(1+((1+$B$14)/(1+$B$16)-1))^$B$24-$B$25/(1+((1+$B$14)/(1+$B$16)-1))^$B$26)/$B$11+$B$27*((($B$28*($B$29*(1-$B$18)-$B$19-$B$30)*$B$15/1000)*(1-$B$17)+$B$17*$B$33/$B$31)*(1-(1+((1+$B$14)/(1+$B$16)-1))^(-$B$31))/((1+$B$14)/(1+$B$16)-1)/(1+((1+$B$14)/(1+$B$16)-1))^$B$32-$B$33/(1+((1+$B$14)/(1+$B$16)-1))^$B$34)/$B$11)+$B$35*(((C$81*$B$37-$B$10-$B$12+$B$13)/$B$11)-((C$81*$A83-$B$10-$B$12+$B$13)/$B$11))*((1+$B$39)/(1+$B$14))^$B$36+$B$35*(1-$B$20)*$B$38*($B$21*($B$22*(1-$B$18)-$B$19-$B$23)*$B$15/1000*$A83/(1+((1+$B$14)/(1+$B$16)-1))^$B$36-$B$25/(1+((1+$B$14)/(1+$B$16)-1))^($B$36-1))/$B$11 -> 91.123007 | D83: =((D$81*$A83-$B$10-$B$12+$B$13)/$B$11+$B$20*($B$21*($B$22*(1-$B$18)-$B$19-$B$23)*$B$15/1000*$A83/(1+((1+$B$14)/(1+$B$16)-1))^$B$24-$B$25/(1+((1+$B$14)/(1+$B$16)-1))^$B$26)/$B$11+$B$27*((($B$28*($B$29*(1-$B$18)-$B$19-$B$30)*$B$15/1000)*(1-$B$17)+$B$17*$B$33/$B$31)*(1-(1+((1+$B$14)/(1+$B$16)-1))^(-$B$31))/((1+$B$14)/(1+$B$16)-1)/(1+((1+$B$14)/(1+$B$16)-1))^$B$32-$B$33/(1+((1+$B$14)/(1+$B$16)-1))^$B$34)/$B$11)+$B$35*(((D$81*$B$37-$B$10-$B$12+$B$13)/$B$11)-((D$81*$A83-$B$10-$B$12+$B$13)/$B$11))*((1+$B$39)/(1+$B$14))^$B$36+$B$35*(1-$B$20)*$B$38*($B$21*($B$22*(1-$B$18)-$B$19-$B$23)*$B$15/1000*$A83/(1+((1+$B$14)/(1+$B$16)-1))^$B$36-$B$25/(1+((1+$B$14)/(1+$B$16)-1))^($B$36-1))/$B$11 -> 117.44062 | E83: =((E$81*$A83-$B$10-$B$12+$B$13)/$B$11+$B$20*($B$21*($B$22*(1-$B$18)-$B$19-$B$23)*$B$15/1000*$A83/(1+((1+$B$14)/(1+$B$16)-1))^$B$24-$B$25/(1+((1+$B$14)/(1+$B$16)-1))^$B$26)/$B$11+$B$27*((($B$28*($B$29*(1-$B$18)-$B$19-$B$30)*$B$15/1000)*(1-$B$17)+$B$17*$B$33/$B$31)*(1-(1+((1+$B$14)/(1+$B$16)-1))^(-$B$31))/((1+$B$14)/(1+$B$16)-1)/(1+((1+$B$14)/(1+$B$16)-1))^$B$32-$B$33/(1+((1+$B$14)/(1+$B$16)-1))^$B$34)/$B$11)+$B$35*(((E$81*$B$37-$B$10-$B$12+$B$13)/$B$11)-((E$81*$A83-$B$10-$B$12+$B$13)/$B$11))*((1+$B$39)/(1+$B$14))^$B$36+$B$35*(1-$B$20)*$B$38*($B$21*($B$22*(1-$B$18)-$B$19-$B$23)*$B$15/1000*$A83/(1+((1+$B$14)/(1+$B$16)-1))^$B$36-$B$25/(1+((1+$B$14)/(1+$B$16)-1))^($B$36-1))/$B$11 -> 143.75824 | F83: =((F$81*$A83-$B$10-$B$12+$B$13)/$B$11+$B$20*($B$21*($B$22*(1-$B$18)-$B$19-$B$23)*$B$15/1000*$A83/(1+((1+$B$14)/(1+$B$16)-1))^$B$24-$B$25/(1+((1+$B$14)/(1+$B$16)-1))^$B$26)/$B$11+$B$27*((($B$28*($B$29*(1-$B$18)-$B$19-$B$30)*$B$15/1000)*(1-$B$17)+$B$17*$B$33/$B$31)*(1-(1+((1+$B$14)/(1+$B$16)-1))^(-$B$31))/((1+$B$14)/(1+$B$16)-1)/(1+((1+$B$14)/(1+$B$16)-1))^$B$32-$B$33/(1+((1+$B$14)/(1+$B$16)-1))^$B$34)/$B$11)+$B$35*(((F$81*$B$37-$B$10-$B$12+$B$13)/$B$11)-((F$81*$A83-$B$10-$B$12+$B$13)/$B$11))*((1+$B$39)/(1+$B$14))^$B$36+$B$35*(1-$B$20)*$B$38*($B$21*($B$22*(1-$B$18)-$B$19-$B$23)*$B$15/1000*$A83/(1+((1+$B$14)/(1+$B$16)-1))^$B$36-$B$25/(1+((1+$B$14)/(1+$B$16)-1))^($B$36-1))/$B$11 -> 170.07585
A84: 2.5 | B84: =((B$81*$A84-$B$10-$B$12+$B$13)/$B$11+$B$20*($B$21*($B$22*(1-$B$18)-$B$19-$B$23)*$B$15/1000*$A84/(1+((1+$B$14)/(1+$B$16)-1))^$B$24-$B$25/(1+((1+$B$14)/(1+$B$16)-1))^$B$26)/$B$11+$B$27*((($B$28*($B$29*(1-$B$18)-$B$19-$B$30)*$B$15/1000)*(1-$B$17)+$B$17*$B$33/$B$31)*(1-(1+((1+$B$14)/(1+$B$16)-1))^(-$B$31))/((1+$B$14)/(1+$B$16)-1)/(1+((1+$B$14)/(1+$B$16)-1))^$B$32-$B$33/(1+((1+$B$14)/(1+$B$16)-1))^$B$34)/$B$11)+$B$35*(((B$81*$B$37-$B$10-$B$12+$B$13)/$B$11)-((B$81*$A84-$B$10-$B$12+$B$13)/$B$11))*((1+$B$39)/(1+$B$14))^$B$36+$B$35*(1-$B$20)*$B$38*($B$21*($B$22*(1-$B$18)-$B$19-$B$23)*$B$15/1000*$A84/(1+((1+$B$14)/(1+$B$16)-1))^$B$36-$B$25/(1+((1+$B$14)/(1+$B$16)-1))^($B$36-1))/$B$11 -> 88.135165 | C84: =((C$81*$A84-$B$10-$B$12+$B$13)/$B$11+$B$20*($B$21*($B$22*(1-$B$18)-$B$19-$B$23)*$B$15/1000*$A84/(1+((1+$B$14)/(1+$B$16)-1))^$B$24-$B$25/(1+((1+$B$14)/(1+$B$16)-1))^$B$26)/$B$11+$B$27*((($B$28*($B$29*(1-$B$18)-$B$19-$B$30)*$B$15/1000)*(1-$B$17)+$B$17*$B$33/$B$31)*(1-(1+((1+$B$14)/(1+$B$16)-1))^(-$B$31))/((1+$B$14)/(1+$B$16)-1)/(1+((1+$B$14)/(1+$B$16)-1))^$B$32-$B$33/(1+((1+$B$14)/(1+$B$16)-1))^$B$34)/$B$11)+$B$35*(((C$81*$B$37-$B$10-$B$12+$B$13)/$B$11)-((C$81*$A84-$B$10-$B$12+$B$13)/$B$11))*((1+$B$39)/(1+$B$14))^$B$36+$B$35*(1-$B$20)*$B$38*($B$21*($B$22*(1-$B$18)-$B$19-$B$23)*$B$15/1000*$A84/(1+((1+$B$14)/(1+$B$16)-1))^$B$36-$B$25/(1+((1+$B$14)/(1+$B$16)-1))^($B$36-1))/$B$11 -> 116.41981 | D84: =((D$81*$A84-$B$10-$B$12+$B$13)/$B$11+$B$20*($B$21*($B$22*(1-$B$18)-$B$19-$B$23)*$B$15/1000*$A84/(1+((1+$B$14)/(1+$B$16)-1))^$B$24-$B$25/(1+((1+$B$14)/(1+$B$16)-1))^$B$26)/$B$11+$B$27*((($B$28*($B$29*(1-$B$18)-$B$19-$B$30)*$B$15/1000)*(1-$B$17)+$B$17*$B$33/$B$31)*(1-(1+((1+$B$14)/(1+$B$16)-1))^(-$B$31))/((1+$B$14)/(1+$B$16)-1)/(1+((1+$B$14)/(1+$B$16)-1))^$B$32-$B$33/(1+((1+$B$14)/(1+$B$16)-1))^$B$34)/$B$11)+$B$35*(((D$81*$B$37-$B$10-$B$12+$B$13)/$B$11)-((D$81*$A84-$B$10-$B$12+$B$13)/$B$11))*((1+$B$39)/(1+$B$14))^$B$36+$B$35*(1-$B$20)*$B$38*($B$21*($B$22*(1-$B$18)-$B$19-$B$23)*$B$15/1000*$A84/(1+((1+$B$14)/(1+$B$16)-1))^$B$36-$B$25/(1+((1+$B$14)/(1+$B$16)-1))^($B$36-1))/$B$11 -> 144.70446 | E84: =((E$81*$A84-$B$10-$B$12+$B$13)/$B$11+$B$20*($B$21*($B$22*(1-$B$18)-$B$19-$B$23)*$B$15/1000*$A84/(1+((1+$B$14)/(1+$B$16)-1))^$B$24-$B$25/(1+((1+$B$14)/(1+$B$16)-1))^$B$26)/$B$11+$B$27*((($B$28*($B$29*(1-$B$18)-$B$19-$B$30)*$B$15/1000)*(1-$B$17)+$B$17*$B$33/$B$31)*(1-(1+((1+$B$14)/(1+$B$16)-1))^(-$B$31))/((1+$B$14)/(1+$B$16)-1)/(1+((1+$B$14)/(1+$B$16)-1))^$B$32-$B$33/(1+((1+$B$14)/(1+$B$16)-1))^$B$34)/$B$11)+$B$35*(((E$81*$B$37-$B$10-$B$12+$B$13)/$B$11)-((E$81*$A84-$B$10-$B$12+$B$13)/$B$11))*((1+$B$39)/(1+$B$14))^$B$36+$B$35*(1-$B$20)*$B$38*($B$21*($B$22*(1-$B$18)-$B$19-$B$23)*$B$15/1000*$A84/(1+((1+$B$14)/(1+$B$16)-1))^$B$36-$B$25/(1+((1+$B$14)/(1+$B$16)-1))^($B$36-1))/$B$11 -> 172.98911 | F84: =((F$81*$A84-$B$10-$B$12+$B$13)/$B$11+$B$20*($B$21*($B$22*(1-$B$18)-$B$19-$B$23)*$B$15/1000*$A84/(1+((1+$B$14)/(1+$B$16)-1))^$B$24-$B$25/(1+((1+$B$14)/(1+$B$16)-1))^$B$26)/$B$11+$B$27*((($B$28*($B$29*(1-$B$18)-$B$19-$B$30)*$B$15/1000)*(1-$B$17)+$B$17*$B$33/$B$31)*(1-(1+((1+$B$14)/(1+$B$16)-1))^(-$B$31))/((1+$B$14)/(1+$B$16)-1)/(1+((1+$B$14)/(1+$B$16)-1))^$B$32-$B$33/(1+((1+$B$14)/(1+$B$16)-1))^$B$34)/$B$11)+$B$35*(((F$81*$B$37-$B$10-$B$12+$B$13)/$B$11)-((F$81*$A84-$B$10-$B$12+$B$13)/$B$11))*((1+$B$39)/(1+$B$14))^$B$36+$B$35*(1-$B$20)*$B$38*($B$21*($B$22*(1-$B$18)-$B$19-$B$23)*$B$15/1000*$A84/(1+((1+$B$14)/(1+$B$16)-1))^$B$36-$B$25/(1+((1+$B$14)/(1+$B$16)-1))^($B$36-1))/$B$11 -> 201.27376
A85: 2.75 | B85: =((B$81*$A85-$B$10-$B$12+$B$13)/$B$11+$B$20*($B$21*($B$22*(1-$B$18)-$B$19-$B$23)*$B$15/1000*$A85/(1+((1+$B$14)/(1+$B$16)-1))^$B$24-$B$25/(1+((1+$B$14)/(1+$B$16)-1))^$B$26)/$B$11+$B$27*((($B$28*($B$29*(1-$B$18)-$B$19-$B$30)*$B$15/1000)*(1-$B$17)+$B$17*$B$33/$B$31)*(1-(1+((1+$B$14)/(1+$B$16)-1))^(-$B$31))/((1+$B$14)/(1+$B$16)-1)/(1+((1+$B$14)/(1+$B$16)-1))^$B$32-$B$33/(1+((1+$B$14)/(1+$B$16)-1))^$B$34)/$B$11)+$B$35*(((B$81*$B$37-$B$10-$B$12+$B$13)/$B$11)-((B$81*$A85-$B$10-$B$12+$B$13)/$B$11))*((1+$B$39)/(1+$B$14))^$B$36+$B$35*(1-$B$20)*$B$38*($B$21*($B$22*(1-$B$18)-$B$19-$B$23)*$B$15/1000*$A85/(1+((1+$B$14)/(1+$B$16)-1))^$B$36-$B$25/(1+((1+$B$14)/(1+$B$16)-1))^($B$36-1))/$B$11 -> 111.46494 | C85: =((C$81*$A85-$B$10-$B$12+$B$13)/$B$11+$B$20*($B$21*($B$22*(1-$B$18)-$B$19-$B$23)*$B$15/1000*$A85/(1+((1+$B$14)/(1+$B$16)-1))^$B$24-$B$25/(1+((1+$B$14)/(1+$B$16)-1))^$B$26)/$B$11+$B$27*((($B$28*($B$29*(1-$B$18)-$B$19-$B$30)*$B$15/1000)*(1-$B$17)+$B$17*$B$33/$B$31)*(1-(1+((1+$B$14)/(1+$B$16)-1))^(-$B$31))/((1+$B$14)/(1+$B$16)-1)/(1+((1+$B$14)/(1+$B$16)-1))^$B$32-$B$33/(1+((1+$B$14)/(1+$B$16)-1))^$B$34)/$B$11)+$B$35*(((C$81*$B$37-$B$10-$B$12+$B$13)/$B$11)-((C$81*$A85-$B$10-$B$12+$B$13)/$B$11))*((1+$B$39)/(1+$B$14))^$B$36+$B$35*(1-$B$20)*$B$38*($B$21*($B$22*(1-$B$18)-$B$19-$B$23)*$B$15/1000*$A85/(1+((1+$B$14)/(1+$B$16)-1))^$B$36-$B$25/(1+((1+$B$14)/(1+$B$16)-1))^($B$36-1))/$B$11 -> 141.71662 | D85: =((D$81*$A85-$B$10-$B$12+$B$13)/$B$11+$B$20*($B$21*($B$22*(1-$B$18)-$B$19-$B$23)*$B$15/1000*$A85/(1+((1+$B$14)/(1+$B$16)-1))^$B$24-$B$25/(1+((1+$B$14)/(1+$B$16)-1))^$B$26)/$B$11+$B$27*((($B$28*($B$29*(1-$B$18)-$B$19-$B$30)*$B$15/1000)*(1-$B$17)+$B$17*$B$33/$B$31)*(1-(1+((1+$B$14)/(1+$B$16)-1))^(-$B$31))/((1+$B$14)/(1+$B$16)-1)/(1+((1+$B$14)/(1+$B$16)-1))^$B$32-$B$33/(1+((1+$B$14)/(1+$B$16)-1))^$B$34)/$B$11)+$B$35*(((D$81*$B$37-$B$10-$B$12+$B$13)/$B$11)-((D$81*$A85-$B$10-$B$12+$B$13)/$B$11))*((1+$B$39)/(1+$B$14))^$B$36+$B$35*(1-$B$20)*$B$38*($B$21*($B$22*(1-$B$18)-$B$19-$B$23)*$B$15/1000*$A85/(1+((1+$B$14)/(1+$B$16)-1))^$B$36-$B$25/(1+((1+$B$14)/(1+$B$16)-1))^($B$36-1))/$B$11 -> 171.9683 | E85: =((E$81*$A85-$B$10-$B$12+$B$13)/$B$11+$B$20*($B$21*($B$22*(1-$B$18)-$B$19-$B$23)*$B$15/1000*$A85/(1+((1+$B$14)/(1+$B$16)-1))^$B$24-$B$25/(1+((1+$B$14)/(1+$B$16)-1))^$B$26)/$B$11+$B$27*((($B$28*($B$29*(1-$B$18)-$B$19-$B$30)*$B$15/1000)*(1-$B$17)+$B$17*$B$33/$B$31)*(1-(1+((1+$B$14)/(1+$B$16)-1))^(-$B$31))/((1+$B$14)/(1+$B$16)-1)/(1+((1+$B$14)/(1+$B$16)-1))^$B$32-$B$33/(1+((1+$B$14)/(1+$B$16)-1))^$B$34)/$B$11)+$B$35*(((E$81*$B$37-$B$10-$B$12+$B$13)/$B$11)-((E$81*$A85-$B$10-$B$12+$B$13)/$B$11))*((1+$B$39)/(1+$B$14))^$B$36+$B$35*(1-$B$20)*$B$38*($B$21*($B$22*(1-$B$18)-$B$19-$B$23)*$B$15/1000*$A85/(1+((1+$B$14)/(1+$B$16)-1))^$B$36-$B$25/(1+((1+$B$14)/(1+$B$16)-1))^($B$36-1))/$B$11 -> 202.21999 | F85: =((F$81*$A85-$B$10-$B$12+$B$13)/$B$11+$B$20*($B$21*($B$22*(1-$B$18)-$B$19-$B$23)*$B$15/1000*$A85/(1+((1+$B$14)/(1+$B$16)-1))^$B$24-$B$25/(1+((1+$B$14)/(1+$B$16)-1))^$B$26)/$B$11+$B$27*((($B$28*($B$29*(1-$B$18)-$B$19-$B$30)*$B$15/1000)*(1-$B$17)+$B$17*$B$33/$B$31)*(1-(1+((1+$B$14)/(1+$B$16)-1))^(-$B$31))/((1+$B$14)/(1+$B$16)-1)/(1+((1+$B$14)/(1+$B$16)-1))^$B$32-$B$33/(1+((1+$B$14)/(1+$B$16)-1))^$B$34)/$B$11)+$B$35*(((F$81*$B$37-$B$10-$B$12+$B$13)/$B$11)-((F$81*$A85-$B$10-$B$12+$B$13)/$B$11))*((1+$B$39)/(1+$B$14))^$B$36+$B$35*(1-$B$20)*$B$38*($B$21*($B$22*(1-$B$18)-$B$19-$B$23)*$B$15/1000*$A85/(1+((1+$B$14)/(1+$B$16)-1))^$B$36-$B$25/(1+((1+$B$14)/(1+$B$16)-1))^($B$36-1))/$B$11 -> 232.47167
A86: 3 | B86: =((B$81*$A86-$B$10-$B$12+$B$13)/$B$11+$B$20*($B$21*($B$22*(1-$B$18)-$B$19-$B$23)*$B$15/1000*$A86/(1+((1+$B$14)/(1+$B$16)-1))^$B$24-$B$25/(1+((1+$B$14)/(1+$B$16)-1))^$B$26)/$B$11+$B$27*((($B$28*($B$29*(1-$B$18)-$B$19-$B$30)*$B$15/1000)*(1-$B$17)+$B$17*$B$33/$B$31)*(1-(1+((1+$B$14)/(1+$B$16)-1))^(-$B$31))/((1+$B$14)/(1+$B$16)-1)/(1+((1+$B$14)/(1+$B$16)-1))^$B$32-$B$33/(1+((1+$B$14)/(1+$B$16)-1))^$B$34)/$B$11)+$B$35*(((B$81*$B$37-$B$10-$B$12+$B$13)/$B$11)-((B$81*$A86-$B$10-$B$12+$B$13)/$B$11))*((1+$B$39)/(1+$B$14))^$B$36+$B$35*(1-$B$20)*$B$38*($B$21*($B$22*(1-$B$18)-$B$19-$B$23)*$B$15/1000*$A86/(1+((1+$B$14)/(1+$B$16)-1))^$B$36-$B$25/(1+((1+$B$14)/(1+$B$16)-1))^($B$36-1))/$B$11 -> 134.79471 | C86: =((C$81*$A86-$B$10-$B$12+$B$13)/$B$11+$B$20*($B$21*($B$22*(1-$B$18)-$B$19-$B$23)*$B$15/1000*$A86/(1+((1+$B$14)/(1+$B$16)-1))^$B$24-$B$25/(1+((1+$B$14)/(1+$B$16)-1))^$B$26)/$B$11+$B$27*((($B$28*($B$29*(1-$B$18)-$B$19-$B$30)*$B$15/1000)*(1-$B$17)+$B$17*$B$33/$B$31)*(1-(1+((1+$B$14)/(1+$B$16)-1))^(-$B$31))/((1+$B$14)/(1+$B$16)-1)/(1+((1+$B$14)/(1+$B$16)-1))^$B$32-$B$33/(1+((1+$B$14)/(1+$B$16)-1))^$B$34)/$B$11)+$B$35*(((C$81*$B$37-$B$10-$B$12+$B$13)/$B$11)-((C$81*$A86-$B$10-$B$12+$B$13)/$B$11))*((1+$B$39)/(1+$B$14))^$B$36+$B$35*(1-$B$20)*$B$38*($B$21*($B$22*(1-$B$18)-$B$19-$B$23)*$B$15/1000*$A86/(1+((1+$B$14)/(1+$B$16)-1))^$B$36-$B$25/(1+((1+$B$14)/(1+$B$16)-1))^($B$36-1))/$B$11 -> 167.01343 | D86: =((D$81*$A86-$B$10-$B$12+$B$13)/$B$11+$B$20*($B$21*($B$22*(1-$B$18)-$B$19-$B$23)*$B$15/1000*$A86/(1+((1+$B$14)/(1+$B$16)-1))^$B$24-$B$25/(1+((1+$B$14)/(1+$B$16)-1))^$B$26)/$B$11+$B$27*((($B$28*($B$29*(1-$B$18)-$B$19-$B$30)*$B$15/1000)*(1-$B$17)+$B$17*$B$33/$B$31)*(1-(1+((1+$B$14)/(1+$B$16)-1))^(-$B$31))/((1+$B$14)/(1+$B$16)-1)/(1+((1+$B$14)/(1+$B$16)-1))^$B$32-$B$33/(1+((1+$B$14)/(1+$B$16)-1))^$B$34)/$B$11)+$B$35*(((D$81*$B$37-$B$10-$B$12+$B$13)/$B$11)-((D$81*$A86-$B$10-$B$12+$B$13)/$B$11))*((1+$B$39)/(1+$B$14))^$B$36+$B$35*(1-$B$20)*$B$38*($B$21*($B$22*(1-$B$18)-$B$19-$B$23)*$B$15/1000*$A86/(1+((1+$B$14)/(1+$B$16)-1))^$B$36-$B$25/(1+((1+$B$14)/(1+$B$16)-1))^($B$36-1))/$B$11 -> 199.23215 | E86: =((E$81*$A86-$B$10-$B$12+$B$13)/$B$11+$B$20*($B$21*($B$22*(1-$B$18)-$B$19-$B$23)*$B$15/1000*$A86/(1+((1+$B$14)/(1+$B$16)-1))^$B$24-$B$25/(1+((1+$B$14)/(1+$B$16)-1))^$B$26)/$B$11+$B$27*((($B$28*($B$29*(1-$B$18)-$B$19-$B$30)*$B$15/1000)*(1-$B$17)+$B$17*$B$33/$B$31)*(1-(1+((1+$B$14)/(1+$B$16)-1))^(-$B$31))/((1+$B$14)/(1+$B$16)-1)/(1+((1+$B$14)/(1+$B$16)-1))^$B$32-$B$33/(1+((1+$B$14)/(1+$B$16)-1))^$B$34)/$B$11)+$B$35*(((E$81*$B$37-$B$10-$B$12+$B$13)/$B$11)-((E$81*$A86-$B$10-$B$12+$B$13)/$B$11))*((1+$B$39)/(1+$B$14))^$B$36+$B$35*(1-$B$20)*$B$38*($B$21*($B$22*(1-$B$18)-$B$19-$B$23)*$B$15/1000*$A86/(1+((1+$B$14)/(1+$B$16)-1))^$B$36-$B$25/(1+((1+$B$14)/(1+$B$16)-1))^($B$36-1))/$B$11 -> 231.45086 | F86: =((F$81*$A86-$B$10-$B$12+$B$13)/$B$11+$B$20*($B$21*($B$22*(1-$B$18)-$B$19-$B$23)*$B$15/1000*$A86/(1+((1+$B$14)/(1+$B$16)-1))^$B$24-$B$25/(1+((1+$B$14)/(1+$B$16)-1))^$B$26)/$B$11+$B$27*((($B$28*($B$29*(1-$B$18)-$B$19-$B$30)*$B$15/1000)*(1-$B$17)+$B$17*$B$33/$B$31)*(1-(1+((1+$B$14)/(1+$B$16)-1))^(-$B$31))/((1+$B$14)/(1+$B$16)-1)/(1+((1+$B$14)/(1+$B$16)-1))^$B$32-$B$33/(1+((1+$B$14)/(1+$B$16)-1))^$B$34)/$B$11)+$B$35*(((F$81*$B$37-$B$10-$B$12+$B$13)/$B$11)-((F$81*$A86-$B$10-$B$12+$B$13)/$B$11))*((1+$B$39)/(1+$B$14))^$B$36+$B$35*(1-$B$20)*$B$38*($B$21*($B$22*(1-$B$18)-$B$19-$B$23)*$B$15/1000*$A86/(1+((1+$B$14)/(1+$B$16)-1))^$B$36-$B$25/(1+((1+$B$14)/(1+$B$16)-1))^($B$36-1))/$B$11 -> 263.66958
A87: Центр таблицы (жёлтая ячейка) = базовый сценарий; должен совпадать со справедливой ценой.
A89: ЧУВСТВИТЕЛЬНОСТЬ СПРАВЕДЛИВОЙ ЦЕНЫ, ₽: строки — вероятность «Северных потоков», столбцы — цена для Китая по «Силе Байкала», $/тыс. м³
A90: вероятность «Северных потоков» \ цена для Китая по «Силе Байкала», $/тыс. м³ | B90: 150 | C90: 200 | D90: 247.9 | E90: 300 | F90: 350
A91: 0 | B91: =(($B$8*$B$9-$B$10-$B$12+$B$13)/$B$11+$A91*($B$21*($B$22*(1-$B$18)-$B$19-$B$23)*$B$15/1000*$B$9/(1+((1+$B$14)/(1+$B$16)-1))^$B$24-$B$25/(1+((1+$B$14)/(1+$B$16)-1))^$B$26)/$B$11+$B$27*((($B$28*(B$90*(1-$B$18)-$B$19-$B$30)*$B$15/1000)*(1-$B$17)+$B$17*$B$33/$B$31)*(1-(1+((1+$B$14)/(1+$B$16)-1))^(-$B$31))/((1+$B$14)/(1+$B$16)-1)/(1+((1+$B$14)/(1+$B$16)-1))^$B$32-$B$33/(1+((1+$B$14)/(1+$B$16)-1))^$B$34)/$B$11)+$B$35*((($B$8*$B$37-$B$10-$B$12+$B$13)/$B$11)-(($B$8*$B$9-$B$10-$B$12+$B$13)/$B$11))*((1+$B$39)/(1+$B$14))^$B$36+$B$35*(1-$A91)*$B$38*($B$21*($B$22*(1-$B$18)-$B$19-$B$23)*$B$15/1000*$B$9/(1+((1+$B$14)/(1+$B$16)-1))^$B$36-$B$25/(1+((1+$B$14)/(1+$B$16)-1))^($B$36-1))/$B$11 -> 130.09338 | C91: =(($B$8*$B$9-$B$10-$B$12+$B$13)/$B$11+$A91*($B$21*($B$22*(1-$B$18)-$B$19-$B$23)*$B$15/1000*$B$9/(1+((1+$B$14)/(1+$B$16)-1))^$B$24-$B$25/(1+((1+$B$14)/(1+$B$16)-1))^$B$26)/$B$11+$B$27*((($B$28*(C$90*(1-$B$18)-$B$19-$B$30)*$B$15/1000)*(1-$B$17)+$B$17*$B$33/$B$31)*(1-(1+((1+$B$14)/(1+$B$16)-1))^(-$B$31))/((1+$B$14)/(1+$B$16)-1)/(1+((1+$B$14)/(1+$B$16)-1))^$B$32-$B$33/(1+((1+$B$14)/(1+$B$16)-1))^$B$34)/$B$11)+$B$35*((($B$8*$B$37-$B$10-$B$12+$B$13)/$B$11)-(($B$8*$B$9-$B$10-$B$12+$B$13)/$B$11))*((1+$B$39)/(1+$B$14))^$B$36+$B$35*(1-$A91)*$B$38*($B$21*($B$22*(1-$B$18)-$B$19-$B$23)*$B$15/1000*$B$9/(1+((1+$B$14)/(1+$B$16)-1))^$B$36-$B$25/(1+((1+$B$14)/(1+$B$16)-1))^($B$36-1))/$B$11 -> 135.93605 | D91: =(($B$8*$B$9-$B$10-$B$12+$B$13)/$B$11+$A91*($B$21*($B$22*(1-$B$18)-$B$19-$B$23)*$B$15/1000*$B$9/(1+((1+$B$14)/(1+$B$16)-1))^$B$24-$B$25/(1+((1+$B$14)/(1+$B$16)-1))^$B$26)/$B$11+$B$27*((($B$28*(D$90*(1-$B$18)-$B$19-$B$30)*$B$15/1000)*(1-$B$17)+$B$17*$B$33/$B$31)*(1-(1+((1+$B$14)/(1+$B$16)-1))^(-$B$31))/((1+$B$14)/(1+$B$16)-1)/(1+((1+$B$14)/(1+$B$16)-1))^$B$32-$B$33/(1+((1+$B$14)/(1+$B$16)-1))^$B$34)/$B$11)+$B$35*((($B$8*$B$37-$B$10-$B$12+$B$13)/$B$11)-(($B$8*$B$9-$B$10-$B$12+$B$13)/$B$11))*((1+$B$39)/(1+$B$14))^$B$36+$B$35*(1-$A91)*$B$38*($B$21*($B$22*(1-$B$18)-$B$19-$B$23)*$B$15/1000*$B$9/(1+((1+$B$14)/(1+$B$16)-1))^$B$36-$B$25/(1+((1+$B$14)/(1+$B$16)-1))^($B$36-1))/$B$11 -> 141.53333 | E91: =(($B$8*$B$9-$B$10-$B$12+$B$13)/$B$11+$A91*($B$21*($B$22*(1-$B$18)-$B$19-$B$23)*$B$15/1000*$B$9/(1+((1+$B$14)/(1+$B$16)-1))^$B$24-$B$25/(1+((1+$B$14)/(1+$B$16)-1))^$B$26)/$B$11+$B$27*((($B$28*(E$90*(1-$B$18)-$B$19-$B$30)*$B$15/1000)*(1-$B$17)+$B$17*$B$33/$B$31)*(1-(1+((1+$B$14)/(1+$B$16)-1))^(-$B$31))/((1+$B$14)/(1+$B$16)-1)/(1+((1+$B$14)/(1+$B$16)-1))^$B$32-$B$33/(1+((1+$B$14)/(1+$B$16)-1))^$B$34)/$B$11)+$B$35*((($B$8*$B$37-$B$10-$B$12+$B$13)/$B$11)-(($B$8*$B$9-$B$10-$B$12+$B$13)/$B$11))*((1+$B$39)/(1+$B$14))^$B$36+$B$35*(1-$A91)*$B$38*($B$21*($B$22*(1-$B$18)-$B$19-$B$23)*$B$15/1000*$B$9/(1+((1+$B$14)/(1+$B$16)-1))^$B$36-$B$25/(1+((1+$B$14)/(1+$B$16)-1))^($B$36-1))/$B$11 -> 147.62139 | F91: =(($B$8*$B$9-$B$10-$B$12+$B$13)/$B$11+$A91*($B$21*($B$22*(1-$B$18)-$B$19-$B$23)*$B$15/1000*$B$9/(1+((1+$B$14)/(1+$B$16)-1))^$B$24-$B$25/(1+((1+$B$14)/(1+$B$16)-1))^$B$26)/$B$11+$B$27*((($B$28*(F$90*(1-$B$18)-$B$19-$B$30)*$B$15/1000)*(1-$B$17)+$B$17*$B$33/$B$31)*(1-(1+((1+$B$14)/(1+$B$16)-1))^(-$B$31))/((1+$B$14)/(1+$B$16)-1)/(1+((1+$B$14)/(1+$B$16)-1))^$B$32-$B$33/(1+((1+$B$14)/(1+$B$16)-1))^$B$34)/$B$11)+$B$35*((($B$8*$B$37-$B$10-$B$12+$B$13)/$B$11)-(($B$8*$B$9-$B$10-$B$12+$B$13)/$B$11))*((1+$B$39)/(1+$B$14))^$B$36+$B$35*(1-$A91)*$B$38*($B$21*($B$22*(1-$B$18)-$B$19-$B$23)*$B$15/1000*$B$9/(1+((1+$B$14)/(1+$B$16)-1))^$B$36-$B$25/(1+((1+$B$14)/(1+$B$16)-1))^($B$36-1))/$B$11 -> 153.46406
A92: 0.075 | B92: =(($B$8*$B$9-$B$10-$B$12+$B$13)/$B$11+$A92*($B$21*($B$22*(1-$B$18)-$B$19-$B$23)*$B$15/1000*$B$9/(1+((1+$B$14)/(1+$B$16)-1))^$B$24-$B$25/(1+((1+$B$14)/(1+$B$16)-1))^$B$26)/$B$11+$B$27*((($B$28*(B$90*(1-$B$18)-$B$19-$B$30)*$B$15/1000)*(1-$B$17)+$B$17*$B$33/$B$31)*(1-(1+((1+$B$14)/(1+$B$16)-1))^(-$B$31))/((1+$B$14)/(1+$B$16)-1)/(1+((1+$B$14)/(1+$B$16)-1))^$B$32-$B$33/(1+((1+$B$14)/(1+$B$16)-1))^$B$34)/$B$11)+$B$35*((($B$8*$B$37-$B$10-$B$12+$B$13)/$B$11)-(($B$8*$B$9-$B$10-$B$12+$B$13)/$B$11))*((1+$B$39)/(1+$B$14))^$B$36+$B$35*(1-$A92)*$B$38*($B$21*($B$22*(1-$B$18)-$B$19-$B$23)*$B$15/1000*$B$9/(1+((1+$B$14)/(1+$B$16)-1))^$B$36-$B$25/(1+((1+$B$14)/(1+$B$16)-1))^($B$36-1))/$B$11 -> 131.67895 | C92: =(($B$8*$B$9-$B$10-$B$12+$B$13)/$B$11+$A92*($B$21*($B$22*(1-$B$18)-$B$19-$B$23)*$B$15/1000*$B$9/(1+((1+$B$14)/(1+$B$16)-1))^$B$24-$B$25/(1+((1+$B$14)/(1+$B$16)-1))^$B$26)/$B$11+$B$27*((($B$28*(C$90*(1-$B$18)-$B$19-$B$30)*$B$15/1000)*(1-$B$17)+$B$17*$B$33/$B$31)*(1-(1+((1+$B$14)/(1+$B$16)-1))^(-$B$31))/((1+$B$14)/(1+$B$16)-1)/(1+((1+$B$14)/(1+$B$16)-1))^$B$32-$B$33/(1+((1+$B$14)/(1+$B$16)-1))^$B$34)/$B$11)+$B$35*((($B$8*$B$37-$B$10-$B$12+$B$13)/$B$11)-(($B$8*$B$9-$B$10-$B$12+$B$13)/$B$11))*((1+$B$39)/(1+$B$14))^$B$36+$B$35*(1-$A92)*$B$38*($B$21*($B$22*(1-$B$18)-$B$19-$B$23)*$B$15/1000*$B$9/(1+((1+$B$14)/(1+$B$16)-1))^$B$36-$B$25/(1+((1+$B$14)/(1+$B$16)-1))^($B$36-1))/$B$11 -> 137.52162 | D92: =(($B$8*$B$9-$B$10-$B$12+$B$13)/$B$11+$A92*($B$21*($B$22*(1-$B$18)-$B$19-$B$23)*$B$15/1000*$B$9/(1+((1+$B$14)/(1+$B$16)-1))^$B$24-$B$25/(1+((1+$B$14)/(1+$B$16)-1))^$B$26)/$B$11+$B$27*((($B$28*(D$90*(1-$B$18)-$B$19-$B$30)*$B$15/1000)*(1-$B$17)+$B$17*$B$33/$B$31)*(1-(1+((1+$B$14)/(1+$B$16)-1))^(-$B$31))/((1+$B$14)/(1+$B$16)-1)/(1+((1+$B$14)/(1+$B$16)-1))^$B$32-$B$33/(1+((1+$B$14)/(1+$B$16)-1))^$B$34)/$B$11)+$B$35*((($B$8*$B$37-$B$10-$B$12+$B$13)/$B$11)-(($B$8*$B$9-$B$10-$B$12+$B$13)/$B$11))*((1+$B$39)/(1+$B$14))^$B$36+$B$35*(1-$A92)*$B$38*($B$21*($B$22*(1-$B$18)-$B$19-$B$23)*$B$15/1000*$B$9/(1+((1+$B$14)/(1+$B$16)-1))^$B$36-$B$25/(1+((1+$B$14)/(1+$B$16)-1))^($B$36-1))/$B$11 -> 143.1189 | E92: =(($B$8*$B$9-$B$10-$B$12+$B$13)/$B$11+$A92*($B$21*($B$22*(1-$B$18)-$B$19-$B$23)*$B$15/1000*$B$9/(1+((1+$B$14)/(1+$B$16)-1))^$B$24-$B$25/(1+((1+$B$14)/(1+$B$16)-1))^$B$26)/$B$11+$B$27*((($B$28*(E$90*(1-$B$18)-$B$19-$B$30)*$B$15/1000)*(1-$B$17)+$B$17*$B$33/$B$31)*(1-(1+((1+$B$14)/(1+$B$16)-1))^(-$B$31))/((1+$B$14)/(1+$B$16)-1)/(1+((1+$B$14)/(1+$B$16)-1))^$B$32-$B$33/(1+((1+$B$14)/(1+$B$16)-1))^$B$34)/$B$11)+$B$35*((($B$8*$B$37-$B$10-$B$12+$B$13)/$B$11)-(($B$8*$B$9-$B$10-$B$12+$B$13)/$B$11))*((1+$B$39)/(1+$B$14))^$B$36+$B$35*(1-$A92)*$B$38*($B$21*($B$22*(1-$B$18)-$B$19-$B$23)*$B$15/1000*$B$9/(1+((1+$B$14)/(1+$B$16)-1))^$B$36-$B$25/(1+((1+$B$14)/(1+$B$16)-1))^($B$36-1))/$B$11 -> 149.20696 | F92: =(($B$8*$B$9-$B$10-$B$12+$B$13)/$B$11+$A92*($B$21*($B$22*(1-$B$18)-$B$19-$B$23)*$B$15/1000*$B$9/(1+((1+$B$14)/(1+$B$16)-1))^$B$24-$B$25/(1+((1+$B$14)/(1+$B$16)-1))^$B$26)/$B$11+$B$27*((($B$28*(F$90*(1-$B$18)-$B$19-$B$30)*$B$15/1000)*(1-$B$17)+$B$17*$B$33/$B$31)*(1-(1+((1+$B$14)/(1+$B$16)-1))^(-$B$31))/((1+$B$14)/(1+$B$16)-1)/(1+((1+$B$14)/(1+$B$16)-1))^$B$32-$B$33/(1+((1+$B$14)/(1+$B$16)-1))^$B$34)/$B$11)+$B$35*((($B$8*$B$37-$B$10-$B$12+$B$13)/$B$11)-(($B$8*$B$9-$B$10-$B$12+$B$13)/$B$11))*((1+$B$39)/(1+$B$14))^$B$36+$B$35*(1-$A92)*$B$38*($B$21*($B$22*(1-$B$18)-$B$19-$B$23)*$B$15/1000*$B$9/(1+((1+$B$14)/(1+$B$16)-1))^$B$36-$B$25/(1+((1+$B$14)/(1+$B$16)-1))^($B$36-1))/$B$11 -> 155.04963
A93: 0.15 | B93: =(($B$8*$B$9-$B$10-$B$12+$B$13)/$B$11+$A93*($B$21*($B$22*(1-$B$18)-$B$19-$B$23)*$B$15/1000*$B$9/(1+((1+$B$14)/(1+$B$16)-1))^$B$24-$B$25/(1+((1+$B$14)/(1+$B$16)-1))^$B$26)/$B$11+$B$27*((($B$28*(B$90*(1-$B$18)-$B$19-$B$30)*$B$15/1000)*(1-$B$17)+$B$17*$B$33/$B$31)*(1-(1+((1+$B$14)/(1+$B$16)-1))^(-$B$31))/((1+$B$14)/(1+$B$16)-1)/(1+((1+$B$14)/(1+$B$16)-1))^$B$32-$B$33/(1+((1+$B$14)/(1+$B$16)-1))^$B$34)/$B$11)+$B$35*((($B$8*$B$37-$B$10-$B$12+$B$13)/$B$11)-(($B$8*$B$9-$B$10-$B$12+$B$13)/$B$11))*((1+$B$39)/(1+$B$14))^$B$36+$B$35*(1-$A93)*$B$38*($B$21*($B$22*(1-$B$18)-$B$19-$B$23)*$B$15/1000*$B$9/(1+((1+$B$14)/(1+$B$16)-1))^$B$36-$B$25/(1+((1+$B$14)/(1+$B$16)-1))^($B$36-1))/$B$11 -> 133.26452 | C93: =(($B$8*$B$9-$B$10-$B$12+$B$13)/$B$11+$A93*($B$21*($B$22*(1-$B$18)-$B$19-$B$23)*$B$15/1000*$B$9/(1+((1+$B$14)/(1+$B$16)-1))^$B$24-$B$25/(1+((1+$B$14)/(1+$B$16)-1))^$B$26)/$B$11+$B$27*((($B$28*(C$90*(1-$B$18)-$B$19-$B$30)*$B$15/1000)*(1-$B$17)+$B$17*$B$33/$B$31)*(1-(1+((1+$B$14)/(1+$B$16)-1))^(-$B$31))/((1+$B$14)/(1+$B$16)-1)/(1+((1+$B$14)/(1+$B$16)-1))^$B$32-$B$33/(1+((1+$B$14)/(1+$B$16)-1))^$B$34)/$B$11)+$B$35*((($B$8*$B$37-$B$10-$B$12+$B$13)/$B$11)-(($B$8*$B$9-$B$10-$B$12+$B$13)/$B$11))*((1+$B$39)/(1+$B$14))^$B$36+$B$35*(1-$A93)*$B$38*($B$21*($B$22*(1-$B$18)-$B$19-$B$23)*$B$15/1000*$B$9/(1+((1+$B$14)/(1+$B$16)-1))^$B$36-$B$25/(1+((1+$B$14)/(1+$B$16)-1))^($B$36-1))/$B$11 -> 139.10719 | D93: =(($B$8*$B$9-$B$10-$B$12+$B$13)/$B$11+$A93*($B$21*($B$22*(1-$B$18)-$B$19-$B$23)*$B$15/1000*$B$9/(1+((1+$B$14)/(1+$B$16)-1))^$B$24-$B$25/(1+((1+$B$14)/(1+$B$16)-1))^$B$26)/$B$11+$B$27*((($B$28*(D$90*(1-$B$18)-$B$19-$B$30)*$B$15/1000)*(1-$B$17)+$B$17*$B$33/$B$31)*(1-(1+((1+$B$14)/(1+$B$16)-1))^(-$B$31))/((1+$B$14)/(1+$B$16)-1)/(1+((1+$B$14)/(1+$B$16)-1))^$B$32-$B$33/(1+((1+$B$14)/(1+$B$16)-1))^$B$34)/$B$11)+$B$35*((($B$8*$B$37-$B$10-$B$12+$B$13)/$B$11)-(($B$8*$B$9-$B$10-$B$12+$B$13)/$B$11))*((1+$B$39)/(1+$B$14))^$B$36+$B$35*(1-$A93)*$B$38*($B$21*($B$22*(1-$B$18)-$B$19-$B$23)*$B$15/1000*$B$9/(1+((1+$B$14)/(1+$B$16)-1))^$B$36-$B$25/(1+((1+$B$14)/(1+$B$16)-1))^($B$36-1))/$B$11 -> 144.70446 | E93: =(($B$8*$B$9-$B$10-$B$12+$B$13)/$B$11+$A93*($B$21*($B$22*(1-$B$18)-$B$19-$B$23)*$B$15/1000*$B$9/(1+((1+$B$14)/(1+$B$16)-1))^$B$24-$B$25/(1+((1+$B$14)/(1+$B$16)-1))^$B$26)/$B$11+$B$27*((($B$28*(E$90*(1-$B$18)-$B$19-$B$30)*$B$15/1000)*(1-$B$17)+$B$17*$B$33/$B$31)*(1-(1+((1+$B$14)/(1+$B$16)-1))^(-$B$31))/((1+$B$14)/(1+$B$16)-1)/(1+((1+$B$14)/(1+$B$16)-1))^$B$32-$B$33/(1+((1+$B$14)/(1+$B$16)-1))^$B$34)/$B$11)+$B$35*((($B$8*$B$37-$B$10-$B$12+$B$13)/$B$11)-(($B$8*$B$9-$B$10-$B$12+$B$13)/$B$11))*((1+$B$39)/(1+$B$14))^$B$36+$B$35*(1-$A93)*$B$38*($B$21*($B$22*(1-$B$18)-$B$19-$B$23)*$B$15/1000*$B$9/(1+((1+$B$14)/(1+$B$16)-1))^$B$36-$B$25/(1+((1+$B$14)/(1+$B$16)-1))^($B$36-1))/$B$11 -> 150.79253 | F93: =(($B$8*$B$9-$B$10-$B$12+$B$13)/$B$11+$A93*($B$21*($B$22*(1-$B$18)-$B$19-$B$23)*$B$15/1000*$B$9/(1+((1+$B$14)/(1+$B$16)-1))^$B$24-$B$25/(1+((1+$B$14)/(1+$B$16)-1))^$B$26)/$B$11+$B$27*((($B$28*(F$90*(1-$B$18)-$B$19-$B$30)*$B$15/1000)*(1-$B$17)+$B$17*$B$33/$B$31)*(1-(1+((1+$B$14)/(1+$B$16)-1))^(-$B$31))/((1+$B$14)/(1+$B$16)-1)/(1+((1+$B$14)/(1+$B$16)-1))^$B$32-$B$33/(1+((1+$B$14)/(1+$B$16)-1))^$B$34)/$B$11)+$B$35*((($B$8*$B$37-$B$10-$B$12+$B$13)/$B$11)-(($B$8*$B$9-$B$10-$B$12+$B$13)/$B$11))*((1+$B$39)/(1+$B$14))^$B$36+$B$35*(1-$A93)*$B$38*($B$21*($B$22*(1-$B$18)-$B$19-$B$23)*$B$15/1000*$B$9/(1+((1+$B$14)/(1+$B$16)-1))^$B$36-$B$25/(1+((1+$B$14)/(1+$B$16)-1))^($B$36-1))/$B$11 -> 156.6352
A94: 0.3 | B94: =(($B$8*$B$9-$B$10-$B$12+$B$13)/$B$11+$A94*($B$21*($B$22*(1-$B$18)-$B$19-$B$23)*$B$15/1000*$B$9/(1+((1+$B$14)/(1+$B$16)-1))^$B$24-$B$25/(1+((1+$B$14)/(1+$B$16)-1))^$B$26)/$B$11+$B$27*((($B$28*(B$90*(1-$B$18)-$B$19-$B$30)*$B$15/1000)*(1-$B$17)+$B$17*$B$33/$B$31)*(1-(1+((1+$B$14)/(1+$B$16)-1))^(-$B$31))/((1+$B$14)/(1+$B$16)-1)/(1+((1+$B$14)/(1+$B$16)-1))^$B$32-$B$33/(1+((1+$B$14)/(1+$B$16)-1))^$B$34)/$B$11)+$B$35*((($B$8*$B$37-$B$10-$B$12+$B$13)/$B$11)-(($B$8*$B$9-$B$10-$B$12+$B$13)/$B$11))*((1+$B$39)/(1+$B$14))^$B$36+$B$35*(1-$A94)*$B$38*($B$21*($B$22*(1-$B$18)-$B$19-$B$23)*$B$15/1000*$B$9/(1+((1+$B$14)/(1+$B$16)-1))^$B$36-$B$25/(1+((1+$B$14)/(1+$B$16)-1))^($B$36-1))/$B$11 -> 136.43565 | C94: =(($B$8*$B$9-$B$10-$B$12+$B$13)/$B$11+$A94*($B$21*($B$22*(1-$B$18)-$B$19-$B$23)*$B$15/1000*$B$9/(1+((1+$B$14)/(1+$B$16)-1))^$B$24-$B$25/(1+((1+$B$14)/(1+$B$16)-1))^$B$26)/$B$11+$B$27*((($B$28*(C$90*(1-$B$18)-$B$19-$B$30)*$B$15/1000)*(1-$B$17)+$B$17*$B$33/$B$31)*(1-(1+((1+$B$14)/(1+$B$16)-1))^(-$B$31))/((1+$B$14)/(1+$B$16)-1)/(1+((1+$B$14)/(1+$B$16)-1))^$B$32-$B$33/(1+((1+$B$14)/(1+$B$16)-1))^$B$34)/$B$11)+$B$35*((($B$8*$B$37-$B$10-$B$12+$B$13)/$B$11)-(($B$8*$B$9-$B$10-$B$12+$B$13)/$B$11))*((1+$B$39)/(1+$B$14))^$B$36+$B$35*(1-$A94)*$B$38*($B$21*($B$22*(1-$B$18)-$B$19-$B$23)*$B$15/1000*$B$9/(1+((1+$B$14)/(1+$B$16)-1))^$B$36-$B$25/(1+((1+$B$14)/(1+$B$16)-1))^($B$36-1))/$B$11 -> 142.27832 | D94: =(($B$8*$B$9-$B$10-$B$12+$B$13)/$B$11+$A94*($B$21*($B$22*(1-$B$18)-$B$19-$B$23)*$B$15/1000*$B$9/(1+((1+$B$14)/(1+$B$16)-1))^$B$24-$B$25/(1+((1+$B$14)/(1+$B$16)-1))^$B$26)/$B$11+$B$27*((($B$28*(D$90*(1-$B$18)-$B$19-$B$30)*$B$15/1000)*(1-$B$17)+$B$17*$B$33/$B$31)*(1-(1+((1+$B$14)/(1+$B$16)-1))^(-$B$31))/((1+$B$14)/(1+$B$16)-1)/(1+((1+$B$14)/(1+$B$16)-1))^$B$32-$B$33/(1+((1+$B$14)/(1+$B$16)-1))^$B$34)/$B$11)+$B$35*((($B$8*$B$37-$B$10-$B$12+$B$13)/$B$11)-(($B$8*$B$9-$B$10-$B$12+$B$13)/$B$11))*((1+$B$39)/(1+$B$14))^$B$36+$B$35*(1-$A94)*$B$38*($B$21*($B$22*(1-$B$18)-$B$19-$B$23)*$B$15/1000*$B$9/(1+((1+$B$14)/(1+$B$16)-1))^$B$36-$B$25/(1+((1+$B$14)/(1+$B$16)-1))^($B$36-1))/$B$11 -> 147.8756 | E94: =(($B$8*$B$9-$B$10-$B$12+$B$13)/$B$11+$A94*($B$21*($B$22*(1-$B$18)-$B$19-$B$23)*$B$15/1000*$B$9/(1+((1+$B$14)/(1+$B$16)-1))^$B$24-$B$25/(1+((1+$B$14)/(1+$B$16)-1))^$B$26)/$B$11+$B$27*((($B$28*(E$90*(1-$B$18)-$B$19-$B$30)*$B$15/1000)*(1-$B$17)+$B$17*$B$33/$B$31)*(1-(1+((1+$B$14)/(1+$B$16)-1))^(-$B$31))/((1+$B$14)/(1+$B$16)-1)/(1+((1+$B$14)/(1+$B$16)-1))^$B$32-$B$33/(1+((1+$B$14)/(1+$B$16)-1))^$B$34)/$B$11)+$B$35*((($B$8*$B$37-$B$10-$B$12+$B$13)/$B$11)-(($B$8*$B$9-$B$10-$B$12+$B$13)/$B$11))*((1+$B$39)/(1+$B$14))^$B$36+$B$35*(1-$A94)*$B$38*($B$21*($B$22*(1-$B$18)-$B$19-$B$23)*$B$15/1000*$B$9/(1+((1+$B$14)/(1+$B$16)-1))^$B$36-$B$25/(1+((1+$B$14)/(1+$B$16)-1))^($B$36-1))/$B$11 -> 153.96366 | F94: =(($B$8*$B$9-$B$10-$B$12+$B$13)/$B$11+$A94*($B$21*($B$22*(1-$B$18)-$B$19-$B$23)*$B$15/1000*$B$9/(1+((1+$B$14)/(1+$B$16)-1))^$B$24-$B$25/(1+((1+$B$14)/(1+$B$16)-1))^$B$26)/$B$11+$B$27*((($B$28*(F$90*(1-$B$18)-$B$19-$B$30)*$B$15/1000)*(1-$B$17)+$B$17*$B$33/$B$31)*(1-(1+((1+$B$14)/(1+$B$16)-1))^(-$B$31))/((1+$B$14)/(1+$B$16)-1)/(1+((1+$B$14)/(1+$B$16)-1))^$B$32-$B$33/(1+((1+$B$14)/(1+$B$16)-1))^$B$34)/$B$11)+$B$35*((($B$8*$B$37-$B$10-$B$12+$B$13)/$B$11)-(($B$8*$B$9-$B$10-$B$12+$B$13)/$B$11))*((1+$B$39)/(1+$B$14))^$B$36+$B$35*(1-$A94)*$B$38*($B$21*($B$22*(1-$B$18)-$B$19-$B$23)*$B$15/1000*$B$9/(1+((1+$B$14)/(1+$B$16)-1))^$B$36-$B$25/(1+((1+$B$14)/(1+$B$16)-1))^($B$36-1))/$B$11 -> 159.80633
A95: 0.5 | B95: =(($B$8*$B$9-$B$10-$B$12+$B$13)/$B$11+$A95*($B$21*($B$22*(1-$B$18)-$B$19-$B$23)*$B$15/1000*$B$9/(1+((1+$B$14)/(1+$B$16)-1))^$B$24-$B$25/(1+((1+$B$14)/(1+$B$16)-1))^$B$26)/$B$11+$B$27*((($B$28*(B$90*(1-$B$18)-$B$19-$B$30)*$B$15/1000)*(1-$B$17)+$B$17*$B$33/$B$31)*(1-(1+((1+$B$14)/(1+$B$16)-1))^(-$B$31))/((1+$B$14)/(1+$B$16)-1)/(1+((1+$B$14)/(1+$B$16)-1))^$B$32-$B$33/(1+((1+$B$14)/(1+$B$16)-1))^$B$34)/$B$11)+$B$35*((($B$8*$B$37-$B$10-$B$12+$B$13)/$B$11)-(($B$8*$B$9-$B$10-$B$12+$B$13)/$B$11))*((1+$B$39)/(1+$B$14))^$B$36+$B$35*(1-$A95)*$B$38*($B$21*($B$22*(1-$B$18)-$B$19-$B$23)*$B$15/1000*$B$9/(1+((1+$B$14)/(1+$B$16)-1))^$B$36-$B$25/(1+((1+$B$14)/(1+$B$16)-1))^($B$36-1))/$B$11 -> 140.66383 | C95: =(($B$8*$B$9-$B$10-$B$12+$B$13)/$B$11+$A95*($B$21*($B$22*(1-$B$18)-$B$19-$B$23)*$B$15/1000*$B$9/(1+((1+$B$14)/(1+$B$16)-1))^$B$24-$B$25/(1+((1+$B$14)/(1+$B$16)-1))^$B$26)/$B$11+$B$27*((($B$28*(C$90*(1-$B$18)-$B$19-$B$30)*$B$15/1000)*(1-$B$17)+$B$17*$B$33/$B$31)*(1-(1+((1+$B$14)/(1+$B$16)-1))^(-$B$31))/((1+$B$14)/(1+$B$16)-1)/(1+((1+$B$14)/(1+$B$16)-1))^$B$32-$B$33/(1+((1+$B$14)/(1+$B$16)-1))^$B$34)/$B$11)+$B$35*((($B$8*$B$37-$B$10-$B$12+$B$13)/$B$11)-(($B$8*$B$9-$B$10-$B$12+$B$13)/$B$11))*((1+$B$39)/(1+$B$14))^$B$36+$B$35*(1-$A95)*$B$38*($B$21*($B$22*(1-$B$18)-$B$19-$B$23)*$B$15/1000*$B$9/(1+((1+$B$14)/(1+$B$16)-1))^$B$36-$B$25/(1+((1+$B$14)/(1+$B$16)-1))^($B$36-1))/$B$11 -> 146.5065 | D95: =(($B$8*$B$9-$B$10-$B$12+$B$13)/$B$11+$A95*($B$21*($B$22*(1-$B$18)-$B$19-$B$23)*$B$15/1000*$B$9/(1+((1+$B$14)/(1+$B$16)-1))^$B$24-$B$25/(1+((1+$B$14)/(1+$B$16)-1))^$B$26)/$B$11+$B$27*((($B$28*(D$90*(1-$B$18)-$B$19-$B$30)*$B$15/1000)*(1-$B$17)+$B$17*$B$33/$B$31)*(1-(1+((1+$B$14)/(1+$B$16)-1))^(-$B$31))/((1+$B$14)/(1+$B$16)-1)/(1+((1+$B$14)/(1+$B$16)-1))^$B$32-$B$33/(1+((1+$B$14)/(1+$B$16)-1))^$B$34)/$B$11)+$B$35*((($B$8*$B$37-$B$10-$B$12+$B$13)/$B$11)-(($B$8*$B$9-$B$10-$B$12+$B$13)/$B$11))*((1+$B$39)/(1+$B$14))^$B$36+$B$35*(1-$A95)*$B$38*($B$21*($B$22*(1-$B$18)-$B$19-$B$23)*$B$15/1000*$B$9/(1+((1+$B$14)/(1+$B$16)-1))^$B$36-$B$25/(1+((1+$B$14)/(1+$B$16)-1))^($B$36-1))/$B$11 -> 152.10378 | E95: =(($B$8*$B$9-$B$10-$B$12+$B$13)/$B$11+$A95*($B$21*($B$22*(1-$B$18)-$B$19-$B$23)*$B$15/1000*$B$9/(1+((1+$B$14)/(1+$B$16)-1))^$B$24-$B$25/(1+((1+$B$14)/(1+$B$16)-1))^$B$26)/$B$11+$B$27*((($B$28*(E$90*(1-$B$18)-$B$19-$B$30)*$B$15/1000)*(1-$B$17)+$B$17*$B$33/$B$31)*(1-(1+((1+$B$14)/(1+$B$16)-1))^(-$B$31))/((1+$B$14)/(1+$B$16)-1)/(1+((1+$B$14)/(1+$B$16)-1))^$B$32-$B$33/(1+((1+$B$14)/(1+$B$16)-1))^$B$34)/$B$11)+$B$35*((($B$8*$B$37-$B$10-$B$12+$B$13)/$B$11)-(($B$8*$B$9-$B$10-$B$12+$B$13)/$B$11))*((1+$B$39)/(1+$B$14))^$B$36+$B$35*(1-$A95)*$B$38*($B$21*($B$22*(1-$B$18)-$B$19-$B$23)*$B$15/1000*$B$9/(1+((1+$B$14)/(1+$B$16)-1))^$B$36-$B$25/(1+((1+$B$14)/(1+$B$16)-1))^($B$36-1))/$B$11 -> 158.19184 | F95: =(($B$8*$B$9-$B$10-$B$12+$B$13)/$B$11+$A95*($B$21*($B$22*(1-$B$18)-$B$19-$B$23)*$B$15/1000*$B$9/(1+((1+$B$14)/(1+$B$16)-1))^$B$24-$B$25/(1+((1+$B$14)/(1+$B$16)-1))^$B$26)/$B$11+$B$27*((($B$28*(F$90*(1-$B$18)-$B$19-$B$30)*$B$15/1000)*(1-$B$17)+$B$17*$B$33/$B$31)*(1-(1+((1+$B$14)/(1+$B$16)-1))^(-$B$31))/((1+$B$14)/(1+$B$16)-1)/(1+((1+$B$14)/(1+$B$16)-1))^$B$32-$B$33/(1+((1+$B$14)/(1+$B$16)-1))^$B$34)/$B$11)+$B$35*((($B$8*$B$37-$B$10-$B$12+$B$13)/$B$11)-(($B$8*$B$9-$B$10-$B$12+$B$13)/$B$11))*((1+$B$39)/(1+$B$14))^$B$36+$B$35*(1-$A95)*$B$38*($B$21*($B$22*(1-$B$18)-$B$19-$B$23)*$B$15/1000*$B$9/(1+((1+$B$14)/(1+$B$16)-1))^$B$36-$B$25/(1+((1+$B$14)/(1+$B$16)-1))^($B$36-1))/$B$11 -> 164.03451
A96: Центр таблицы (жёлтая ячейка) = базовый сценарий; должен совпадать со справедливой ценой.
A98: ТЕЗИС И УСЛОВИЯ ЕГО СЛОМА (сигнал при любой цене)
A99: Тезис: Ставка на геополитику и экспорт. База слабая: газовый сегмент убыточен, долг 6 трлн ₽, дивидендов нет с 2022 года. Ценность сверх базы дают два опциона: «Северные потоки» (уцелевшая нитка почти не требует вложений) и «Сила Байкала» — при цене как у «Силы Сибири» (~$248) она окупает трубу и добавляет стоимость, но всё решает цена в контракте.
A100: • ЧД/EBITDA выше 2,5x — порог пересмотра дивполитики, выплаты отодвигаются ещё дальше
A101: • Новое повышение налогов: возврат надбавки к НДПИ или разовые изъятия
A102: • Контракт «Силы Байкала» с ценой ниже точки окупаемости (строка проверки) или капзатраты сильно выше 1 трлн ₽
A103: • Турция не продлевает контракты после 2026 года
A105: ЧТО ОТСЛЕЖИВАЕТ БОТ В НОВОСТЯХ
A106: • Мирные переговоры и позиция ЕС по газу → вероятность «Северных потоков»
A107: • Переговоры Газпрома и CNPC по «Силе Байкала»: цена, объём, кто финансирует → цена для Китая и капзатраты
A108: • Решение по дивидендам за 2026 год (весна 2027), отчёт за 9М 2026
...

Sheet NLMK
A1: NLMK — НЛМК: модель справедливой стоимости
A2: Метод: EV/EBITDA на нормализованную (среднецикличную) EBITDA с дисконтом за ожидание
A3: Металлург на дне цикла: текущая EBITDA занижена, оценивать по ней — продать на дне. Берём EBITDA «нормального» года (выручка × среднецикличная маржа), умножаем на мультипликатор, дисконтируем за годы до восстановления спроса и прибавляем чистый кэш.
A4: Синий — вводные (меняйте их), чёрный — формулы, зелёный — ссылки на другие листы, жёлтый — главные рычаги модели.
A6: Показатель | B6: Значение | C6: Ед. | D6: Источник / комментарий
A7: ВВОДНЫЕ
A8: Выручка нормального года | B8: 830 | C8: млрд ₽ | D8: 2025: 831,4 млрд (−15%); LTM на 30.06.2026: 780 млрд. Берём уровень 2025 — без расчёта на возврат к пику 2021–2022.
A9: Среднецикличная маржа EBITDA | B9: 0.2 | C9: % | D9: 2024 ≈ 26%, 2025 — 16,9%, 1П 2026 — 14,8% (дно). Берём 20% — середину, ниже исторических 25–30% из‑за потери экспорта.
A10: Справедливый EV/EBITDA | B10: 4 | C10: x | D10: До 2022 НЛМК стоил 5–6x при выплате 100% FCF; сейчас дивидендов нет два года подряд — дисконт до 4x.
A11: Ставка дисконтирования | B11: =Параметры!$B$9 -> 0.19 | C11: % | D11: Из «Параметров».
A12: Лет до восстановления спроса | B12: 1.5 | C12: лет | D12: НКР: восстановление спроса не раньше 2П 2027, заметное — в 2028; Т-Инвестиции допускают, что 2026 — дно.
A13: Чистый долг (минус = чистый кэш) | B13: -40.7 | C13: млрд ₽ | D13: На 30.06.2026: кэш 80,3 млрд, долг 39,7 млрд (МСФО 1П 2026).
A14: Акций в обращении | B14: 5.9932 | C14: млрд шт | D14: 5 993 227 240 акций; 5,993 × 76,38 ₽ = 457,8 млрд ₽ капитализации.
A15: EBITDA 2026П (для проверки) | B15: 115 | C15: млрд ₽ | D15: 1П 2026: 57,2 млрд × 2.
A16: Мир: вероятность мира и снятия санкций | B16: =Параметры!$B$15 -> 0.5 | C16: % | D16: Из «Параметров».
A17: Мир: лет до снятия санкций | B17: =Параметры!$B$16 -> 5 | C17: лет | D17: Из «Параметров».
A18: Мир: EV/EBITDA как до 2022 года | B18: 5.5 | C18: x | D18: НЛМК в 2017–2021 стоил ~5–6x EBITDA при выплате 100% FCF.
A19: Мир: маржа EBITDA после снятия санкций | B19: 0.24 | C19: % | D19: До 2022 маржа EBITDA НЛМК была 25–30%; после снятия санкций возвращается экспорт в ЕС и США. Берём 24%.
A20: Мир: рост показателя до года мира, % в год | B20: 0.05 | C20: % | D20: Рост выручки и EBITDA в среднем за 5 лет.
A22: РАСЧЁТ
A23: Нормализованная EBITDA | B23: =$B$8*$B$9 -> 166 | C23: млрд ₽
A24: Стоимость бизнеса в нормальный год | B24: =$B$23*$B$10 -> 664 | C24: млрд ₽
A25: Стоимость бизнеса сегодня (дисконт за ожидание) | B25: =$B$24/(1+$B$11)^$B$12 -> 511.50235 | C25: млрд ₽
A26: Стоимость акционерного капитала | B26: =$B$25-$B$13 -> 552.20235 | C26: млрд ₽
A27: Справедливая цена без мира | B27: =IF($B$14>0,$B$26/$B$14,0) -> 92.138149 | C27: ₽
A28: Мир: цена в мирном режиме на сегодняшних показателях | B28: =($B$8*$B$19*$B$18/(1+$B$11)^$B$12-$B$13)/$B$14 -> 147.61378 | C28: ₽ | D28: Если бы рынок уже сегодня оценивал компанию как до 2022 года.
A29: Мир: прибавка к цене сегодня | B29: =$B$16*($B$28-$B$27)*((1+$B$20)/(1+$B$11))^$B$17 -> 14.834876 | C29: ₽ | D29: Вероятность × разница цен × рост показателя до года мира, приведённый к сегодняшнему дню.
A30: Справедливая цена с миром | B30: =$B$27+$B$29 -> 106.97302 | C30: ₽
A32: РЕЗУЛЬТАТ
A33: Справедливая цена | B33: =$B$30 -> 106.97302 | C33: ₽ | D33: Главный вывод модели
A34: Текущая цена | B34: =Сводка!$D$12 -> 76.44 | C34: ₽ | D34: Берётся со «Сводки» (столбец D)
A35: Зона покупки: цена не выше | B35: =$B$33*(1-Параметры!$B$10) -> 82.369229 | C35: ₽ | D35: Справедливая минус скидка из «Параметров»
A36: Цена продажи | B36: =$B$33*(1+Параметры!$B$11) -> 126.22817 | C36: ₽ | D36: Справедливая плюс премия из «Параметров»
A37: Сигнал «приближается к продаже» от | B37: =$B$36*(1-Параметры!$B$12) -> 119.91676 | C37: ₽ | D37: За сколько % до цены продажи бот предупреждает
A38: Потенциал до справедливой | B38: =IF($B$34>0,$B$33/$B$34-1,0) -> 0.39943779 | C38: %
A39: До цены продажи | B39: =IF($B$34>0,$B$36/$B$34-1,0) -> 0.65133659 | C39: %
A40: Статус | B40: =IF($B$34<=$B$35,"ЗОНА ПОКУПКИ",IF($B$34>=$B$36,"ЦЕНА ПРОДАЖИ",IF($B$34>=$B$37,"ПРИБЛИЖАЕТСЯ К ПРОДАЖЕ","ДЕРЖАТЬ"))) -> ЗОНА ПОКУПКИ | D40: Слом тезиса — отдельный сигнал, см. ниже
A42: ПЕРЕКРЁСТНАЯ ПРОВЕРКА
A43: EV/EBITDA 2026П при текущей цене | B43: =IF($B$15>0,($B$34*$B$14+$B$13)/$B$15,0) -> 3.6297409 | C43: x | D43: Рынок уже платит ~3,6x даже за дно цикла.
A44: EV/нормализованная EBITDA при текущей цене | B44: =IF($B$23>0,($B$34*$B$14+$B$13)/$B$23,0) -> 2.5145796 | C44: x
A45: Цель Финама (июль 2026) | B45: =74.1 -> 74.1 | C45: ₽ | D45: Единственная свежая цель брокера; консенсус не найден.
A47: ЧУВСТВИТЕЛЬНОСТЬ СПРАВЕДЛИВОЙ ЦЕНЫ, ₽: строки — EV/EBITDA, столбцы — маржа EBITDA
A48: EV/EBITDA \ маржа EBITDA | B48: 0.16 | C48: 0.18 | D48: 0.2 | E48: 0.22 | F48: 0.24
A49: 3 | B49: =(($B$8*B$48*$A49/(1+$B$11)^$B$12-$B$13)/$B$14)+$B$16*((($B$8*$B$19*$B$18/(1+$B$11)^$B$12-$B$13)/$B$14)-(($B$8*B$48*$A49/(1+$B$11)^$B$12-$B$13)/$B$14))*((1+$B$20)/(1+$B$11))^$B$17 -> 81.963332 | C49: =(($B$8*C$48*$A49/(1+$B$11)^$B$12-$B$13)/$B$14)+$B$16*((($B$8*$B$19*$B$18/(1+$B$11)^$B$12-$B$13)/$B$14)-(($B$8*C$48*$A49/(1+$B$11)^$B$12-$B$13)/$B$14))*((1+$B$20)/(1+$B$11))^$B$17 -> 86.652649 | D49: =(($B$8*D$48*$A49/(1+$B$11)^$B$12-$B$13)/$B$14)+$B$16*((($B$8*$B$19*$B$18/(1+$B$11)^$B$12-$B$13)/$B$14)-(($B$8*D$48*$A49/(1+$B$11)^$B$12-$B$13)/$B$14))*((1+$B$20)/(1+$B$11))^$B$17 -> 91.341967 | E49: =(($B$8*E$48*$A49/(1+$B$11)^$B$12-$B$13)/$B$14)+$B$16*((($B$8*$B$19*$B$18/(1+$B$11)^$B$12-$B$13)/$B$14)-(($B$8*E$48*$A49/(1+$B$11)^$B$12-$B$13)/$B$14))*((1+$B$20)/(1+$B$11))^$B$17 -> 96.031284 | F49: =(($B$8*F$48*$A49/(1+$B$11)^$B$12-$B$13)/$B$14)+$B$16*((($B$8*$B$19*$B$18/(1+$B$11)^$B$12-$B$13)/$B$14)-(($B$8*F$48*$A49/(1+$B$11)^$B$12-$B$13)/$B$14))*((1+$B$20)/(1+$B$11))^$B$17 -> 100.7206
A50: 3.5 | B50: =(($B$8*B$48*$A50/(1+$B$11)^$B$12-$B$13)/$B$14)+$B$16*((($B$8*$B$19*$B$18/(1+$B$11)^$B$12-$B$13)/$B$14)-(($B$8*B$48*$A50/(1+$B$11)^$B$12-$B$13)/$B$14))*((1+$B$20)/(1+$B$11))^$B$17 -> 88.215755 | C50: =(($B$8*C$48*$A50/(1+$B$11)^$B$12-$B$13)/$B$14)+$B$16*((($B$8*$B$19*$B$18/(1+$B$11)^$B$12-$B$13)/$B$14)-(($B$8*C$48*$A50/(1+$B$11)^$B$12-$B$13)/$B$14))*((1+$B$20)/(1+$B$11))^$B$17 -> 93.686625 | D50: =(($B$8*D$48*$A50/(1+$B$11)^$B$12-$B$13)/$B$14)+$B$16*((($B$8*$B$19*$B$18/(1+$B$11)^$B$12-$B$13)/$B$14)-(($B$8*D$48*$A50/(1+$B$11)^$B$12-$B$13)/$B$14))*((1+$B$20)/(1+$B$11))^$B$17 -> 99.157496 | E50: =(($B$8*E$48*$A50/(1+$B$11)^$B$12-$B$13)/$B$14)+$B$16*((($B$8*$B$19*$B$18/(1+$B$11)^$B$12-$B$13)/$B$14)-(($B$8*E$48*$A50/(1+$B$11)^$B$12-$B$13)/$B$14))*((1+$B$20)/(1+$B$11))^$B$17 -> 104.62837 | F50: =(($B$8*F$48*$A50/(1+$B$11)^$B$12-$B$13)/$B$14)+$B$16*((($B$8*$B$19*$B$18/(1+$B$11)^$B$12-$B$13)/$B$14)-(($B$8*F$48*$A50/(1+$B$11)^$B$12-$B$13)/$B$14))*((1+$B$20)/(1+$B$11))^$B$17 -> 110.09924
A51: 4 | B51: =(($B$8*B$48*$A51/(1+$B$11)^$B$12-$B$13)/$B$14)+$B$16*((($B$8*$B$19*$B$18/(1+$B$11)^$B$12-$B$13)/$B$14)-(($B$8*B$48*$A51/(1+$B$11)^$B$12-$B$13)/$B$14))*((1+$B$20)/(1+$B$11))^$B$17 -> 94.468178 | C51: =(($B$8*C$48*$A51/(1+$B$11)^$B$12-$B$13)/$B$14)+$B$16*((($B$8*$B$19*$B$18/(1+$B$11)^$B$12-$B$13)/$B$14)-(($B$8*C$48*$A51/(1+$B$11)^$B$12-$B$13)/$B$14))*((1+$B$20)/(1+$B$11))^$B$17 -> 100.7206 | D51: =(($B$8*D$48*$A51/(1+$B$11)^$B$12-$B$13)/$B$14)+$B$16*((($B$8*$B$19*$B$18/(1+$B$11)^$B$12-$B$13)/$B$14)-(($B$8*D$48*$A51/(1+$B$11)^$B$12-$B$13)/$B$14))*((1+$B$20)/(1+$B$11))^$B$17 -> 106.97302 | E51: =(($B$8*E$48*$A51/(1+$B$11)^$B$12-$B$13)/$B$14)+$B$16*((($B$8*$B$19*$B$18/(1+$B$11)^$B$12-$B$13)/$B$14)-(($B$8*E$48*$A51/(1+$B$11)^$B$12-$B$13)/$B$14))*((1+$B$20)/(1+$B$11))^$B$17 -> 113.22545 | F51: =(($B$8*F$48*$A51/(1+$B$11)^$B$12-$B$13)/$B$14)+$B$16*((($B$8*$B$19*$B$18/(1+$B$11)^$B$12-$B$13)/$B$14)-(($B$8*F$48*$A51/(1+$B$11)^$B$12-$B$13)/$B$14))*((1+$B$20)/(1+$B$11))^$B$17 -> 119.47787
A52: 4.5 | B52: =(($B$8*B$48*$A52/(1+$B$11)^$B$12-$B$13)/$B$14)+$B$16*((($B$8*$B$19*$B$18/(1+$B$11)^$B$12-$B$13)/$B$14)-(($B$8*B$48*$A52/(1+$B$11)^$B$12-$B$13)/$B$14))*((1+$B$20)/(1+$B$11))^$B$17 -> 100.7206 | C52: =(($B$8*C$48*$A52/(1+$B$11)^$B$12-$B$13)/$B$14)+$B$16*((($B$8*$B$19*$B$18/(1+$B$11)^$B$12-$B$13)/$B$14)-(($B$8*C$48*$A52/(1+$B$11)^$B$12-$B$13)/$B$14))*((1+$B$20)/(1+$B$11))^$B$17 -> 107.75458 | D52: =(($B$8*D$48*$A52/(1+$B$11)^$B$12-$B$13)/$B$14)+$B$16*((($B$8*$B$19*$B$18/(1+$B$11)^$B$12-$B$13)/$B$14)-(($B$8*D$48*$A52/(1+$B$11)^$B$12-$B$13)/$B$14))*((1+$B$20)/(1+$B$11))^$B$17 -> 114.78855 | E52: =(($B$8*E$48*$A52/(1+$B$11)^$B$12-$B$13)/$B$14)+$B$16*((($B$8*$B$19*$B$18/(1+$B$11)^$B$12-$B$13)/$B$14)-(($B$8*E$48*$A52/(1+$B$11)^$B$12-$B$13)/$B$14))*((1+$B$20)/(1+$B$11))^$B$17 -> 121.82253 | F52: =(($B$8*F$48*$A52/(1+$B$11)^$B$12-$B$13)/$B$14)+$B$16*((($B$8*$B$19*$B$18/(1+$B$11)^$B$12-$B$13)/$B$14)-(($B$8*F$48*$A52/(1+$B$11)^$B$12-$B$13)/$B$14))*((1+$B$20)/(1+$B$11))^$B$17 -> 128.85651
A53: 5 | B53: =(($B$8*B$48*$A53/(1+$B$11)^$B$12-$B$13)/$B$14)+$B$16*((($B$8*$B$19*$B$18/(1+$B$11)^$B$12-$B$13)/$B$14)-(($B$8*B$48*$A53/(1+$B$11)^$B$12-$B$13)/$B$14))*((1+$B$20)/(1+$B$11))^$B$17 -> 106.97302 | C53: =(($B$8*C$48*$A53/(1+$B$11)^$B$12-$B$13)/$B$14)+$B$16*((($B$8*$B$19*$B$18/(1+$B$11)^$B$12-$B$13)/$B$14)-(($B$8*C$48*$A53/(1+$B$11)^$B$12-$B$13)/$B$14))*((1+$B$20)/(1+$B$11))^$B$17 -> 114.78855 | D53: =(($B$8*D$48*$A53/(1+$B$11)^$B$12-$B$13)/$B$14)+$B$16*((($B$8*$B$19*$B$18/(1+$B$11)^$B$12-$B$13)/$B$14)-(($B$8*D$48*$A53/(1+$B$11)^$B$12-$B$13)/$B$14))*((1+$B$20)/(1+$B$11))^$B$17 -> 122.60408 | E53: =(($B$8*E$48*$A53/(1+$B$11)^$B$12-$B$13)/$B$14)+$B$16*((($B$8*$B$19*$B$18/(1+$B$11)^$B$12-$B$13)/$B$14)-(($B$8*E$48*$A53/(1+$B$11)^$B$12-$B$13)/$B$14))*((1+$B$20)/(1+$B$11))^$B$17 -> 130.41961 | F53: =(($B$8*F$48*$A53/(1+$B$11)^$B$12-$B$13)/$B$14)+$B$16*((($B$8*$B$19*$B$18/(1+$B$11)^$B$12-$B$13)/$B$14)-(($B$8*F$48*$A53/(1+$B$11)^$B$12-$B$13)/$B$14))*((1+$B$20)/(1+$B$11))^$B$17 -> 138.23514
A54: Центр таблицы (жёлтая ячейка) = базовый сценарий; должен совпадать со справедливой ценой.
A56: ТЕЗИС И УСЛОВИЯ ЕГО СЛОМА (сигнал при любой цене)
A57: Тезис: Один из самых эффективных металлургов мира с чистым кэшем на балансе. Сейчас дно цикла: спрос на сталь в РФ падает третий год, рубль крепкий, экспорт ограничен. При снижении ставки строительство и спрос восстанавливаются, маржа возвращается к 20%+, и акция переоценивается. Слабое место — дивидендов нет с 2024 года.
A58: • Дивиденды не возобновлены и после возврата FCF в плюс (решение по итогам 2026 года, весна 2027)
A59: • Чистый долг выше 1x EBITDA — крупная сделка или выкуп активов у мажоритария
A60: • Спрос на сталь в РФ в 2027 году падает ещё более чем на 10%
A61: • Маржа EBITDA ниже 12% два полугодия подряд
A62: • Ужесточение налога на сверхдоходы металлургов сверх параметров октября 2026
A64: ЧТО ОТСЛЕЖИВАЕТ БОТ В НОВОСТЯХ
A65: • Спрос и цены на сталь в РФ (Северсталь, Cbonds: арматура, горячий прокат)
A66: • Отчёты Северстали и ММК как опережающий индикатор
A67: • Курс рубля и экспортные цены на заготовку и слябы
... A76: Эксперт РА — рейтинг ruAAA, 21.10.2026: https://raexpert.ru/releases/2026/oct21c

Sheet BSPB
A1: BSPB — Банк Санкт-Петербург: модель справедливой стоимости
A2: Метод: дивидендная модель (формула Гордона)
A3: Для справки: позиции в портфеле нет. Банк платит 50% прибыли по МСФО дважды в год, поэтому стоимость акции = дивиденд / (требуемая доходность − рост дивиденда). Проверка — P/E и ROE против истории банка.
A4: Синий — вводные (меняйте их), чёрный — формулы, зелёный — ссылки на другие листы, жёлтый — главные рычаги модели.
A6: Показатель | B6: Значение | C6: Ед. | D6: Источник / комментарий
A7: ВВОДНЫЕ
A8: Чистая прибыль 2026П (МСФО) | B8: 30 | C8: млрд ₽ | D8: Менеджмент снизил прогноз с 35 до 30 млрд (август 2026); 1П 2026 МСФО: 16,5 млрд (−33% г/г); 9М 2026 РСБУ: 24,3 млрд после налога. Прибыль падает вместе со ставкой: у банка много дешёвых остатков на счетах.
A9: Доля прибыли на дивиденды | B9: 0.5 | C9: % | D9: Политика: 20–50% прибыли МСФО; фактически платит 50% (за 1П 2026 — 19,17 ₽, за 2П 2025 — 26,23 ₽).
A10: Обыкновенных акций в обращении | B10: 0.4454 | C10: млрд шт | D10: ~445,4 млн (investmint, капитализация 114,4 млрд ₽ при 257 ₽). Привилегированные получают символические 0,22 ₽ и не учитываются.
A11: Базовая требуемая доходность | B11: =Параметры!$B$9 -> 0.19 | C11: % | D11: Из «Параметров»: ставка ЦБ 2027 + премия за риск акций.
A12: Премия за специфический риск | B12: 0.01 | C12: % | D12: Региональный банк с контролирующим акционером; аналитики отмечают рост рисков у небольших банков при жёсткой ДКП (Freedom, август 2026).
A13: Долгосрочный рост дивиденда | B13: 0.06 | C13: % | D13: Устойчивый рост ≈ ROE ~14% × нераспределённая прибыль 50% ≈ 7%; берём 6%.
A14: Собственный капитал (для проверки) | B14: 223.4 | C14: млрд ₽ | D14: На 01.10.2026 по РСБУ (Фонтанка); по МСФО на 30.06.2026 — 218,4 млрд.
A15: Мир: вероятность мира и снятия санкций | B15: =Параметры!$B$15 -> 0.5 | C15: % | D15: Из «Параметров».
A16: Мир: лет до снятия санкций | B16: =Параметры!$B$16 -> 5 | C16: лет | D16: Из «Параметров».
A17: Мир: P/E как до 2022 года | B17: 4.5 | C17: x | D17: В 2019–2021 банк стоил ~3,5–4,5 годовые прибыли при ROE 10–12%. Берём 4,5x.
A18: Мир: рост показателя до года мира, % в год | B18: 0.06 | C18: % | D18: Как рост дивиденда.
A20: РАСЧЁТ
A21: Дивиденд за 2026 (1П выплачен, 2П — весной 2027) | B21: =$B$8*$B$9/$B$10 -> 33.677593 | C21: ₽/акц.
A22: Требуемая доходность | B22: =$B$11+$B$12 -> 0.2 | C22: %
A23: Справедливая дивдоходность (r − g) | B23: =$B$22-$B$13 -> 0.14 | C23: %
A24: Справедливая цена без мира | B24: =IF($B$23>0,$B$21/$B$23,0) -> 240.55424 | C24: ₽
A25: Мир: цена в мирном режиме на сегодняшних показателях | B25: =$B$17*$B$8/$B$10 -> 303.09834 | C25: ₽ | D25: Если бы рынок уже сегодня оценивал компанию как до 2022 года.
A26: Мир: прибавка к цене сегодня | B26: =$B$15*($B$25-$B$24)*((1+$B$18)/(1+$B$11))^$B$16 -> 17.536822 | C26: ₽ | D26: Вероятность × разница цен × рост показателя до года мира, приведённый к сегодняшнему дню.
A27: Справедливая цена с миром | B27: =$B$24+$B$26 -> 258.09106 | C27: ₽
A29: РЕЗУЛЬТАТ
A30: Справедливая цена | B30: =$B$27 -> 258.09106 | C30: ₽ | D30: Главный вывод модели
A31: Текущая цена | B31: =Сводка!$D$13 -> 257.06 | C31: ₽ | D31: Берётся со «Сводки» (столбец D)
A32: Зона покупки: цена не выше | B32: =$B$30*(1-Параметры!$B$10) -> 198.73012 | C32: ₽ | D32: Справедливая минус скидка из «Параметров»
A33: Цена продажи | B33: =$B$30*(1+Параметры!$B$11) -> 304.54745 | C33: ₽ | D33: Справедливая плюс премия из «Параметров»
A34: Сигнал «приближается к продаже» от | B34: =$B$33*(1-Параметры!$B$12) -> 289.32008 | C34: ₽ | D34: За сколько % до цены продажи бот предупреждает
A35: Потенциал до справедливой | B35: =IF($B$31>0,$B$30/$B$31-1,0) -> 0.0040109644 | C35: %
A36: До цены продажи | B36: =IF($B$31>0,$B$33/$B$31-1,0) -> 0.18473294 | C36: %
A37: Статус | B37: =IF($B$31<=$B$32,"ЗОНА ПОКУПКИ",IF($B$31>=$B$33,"ЦЕНА ПРОДАЖИ",IF($B$31>=$B$34,"ПРИБЛИЖАЕТСЯ К ПРОДАЖЕ","ДЕРЖАТЬ"))) -> ДЕРЖАТЬ | D37: Слом тезиса — отдельный сигнал, см. ниже
A39: ПЕРЕКРЁСТНАЯ ПРОВЕРКА
A40: Прибыль на акцию 2026П | B40: =$B$8/$B$10 -> 67.355186 | C40: ₽
A41: P/E при справедливой цене | B41: =IF($B$40>0,$B$30/$B$40,0) -> 3.8317919 | C41: x | D41: Исторически банк стоил 3–4,5 годовые прибыли.
A42: ROE 2026П | B42: =IF($B$14>0,$B$8/$B$14,0) -> 0.13428827 | C42: % | D42: В 2023–2024 было 25%+; падает вместе со ставкой.
A43: Дивдоходность к текущей цене | B43: =IF($B$31>0,$B$21/$B$31,0) -> 0.13101063 | C43: %
A44: Доходность, которую закладывает текущая цена (D/P + g) | B44: =IF($B$31>0,$B$21/$B$31+$B$13,0) -> 0.19101063 | C44: % | D44: Сравните с длинными ОФЗ 16,6%.
A45: Цель Freedom Global | B45: =280 -> 280 | C45: ₽ | D45: 21.08.2026: «держать», цель снижена с 375 до 280 ₽.
A47: ЧУВСТВИТЕЛЬНОСТЬ СПРАВЕДЛИВОЙ ЦЕНЫ, ₽: строки — рост дивиденда, столбцы — прибыль 2026П, млрд ₽
A48: рост дивиденда \ прибыль 2026П, млрд ₽ | B48: 26 | C48: 28 | D48: 30 | E48: 32 | F48: 34
A49: 0.04 | B49: =(B$48*$B$9/$B$10/($B$11+$B$12-$A49))+$B$15*(($B$17*B$48/$B$10)-(B$48*$B$9/$B$10/($B$11+$B$12-$A49)))*((1+$B$18)/(1+$B$11))^$B$16 -> 204.92588 | C49: =(C$48*$B$9/$B$10/($B$11+$B$12-$A49))+$B$15*(($B$17*C$48/$B$10)-(C$48*$B$9/$B$10/($B$11+$B$12-$A49)))*((1+$B$18)/(1+$B$11))^$B$16 -> 220.68941 | D49: =(D$48*$B$9/$B$10/($B$11+$B$12-$A49))+$B$15*(($B$17*D$48/$B$10)-(D$48*$B$9/$B$10/($B$11+$B$12-$A49)))*((1+$B$18)/(1+$B$11))^$B$16 -> 236.45294 | E49: =(E$48*$B$9/$B$10/($B$11+$B$12-$A49))+$B$15*(($B$17*E$48/$B$10)-(E$48*$B$9/$B$10/($B$11+$B$12-$A49)))*((1+$B$18)/(1+$B$11))^$B$16 -> 252.21647 | F49: =(F$48*$B$9/$B$10/($B$11+$B$12-$A49))+$B$15*(($B$17*F$48/$B$10)-(F$48*$B$9/$B$10/($B$11+$B$12-$A49)))*((1+$B$18)/(1+$B$11))^$B$16 -> 267.98
A50: 0.05 | B50: =(B$48*$B$9/$B$10/($B$11+$B$12-$A50))+$B$15*(($B$17*B$48/$B$10)-(B$48*$B$9/$B$10/($B$11+$B$12-$A50)))*((1+$B$18)/(1+$B$11))^$B$16 -> 213.6773 | C50: =(C$48*$B$9/$B$10/($B$11+$B$12-$A50))+$B$15*(($B$17*C$48/$B$10)-(C$48*$B$9/$B$10/($B$11+$B$12-$A50)))*((1+$B$18)/(1+$B$11))^$B$16 -> 230.11401 | D50: =(D$48*$B$9/$B$10/($B$11+$B$12-$A50))+$B$15*(($B$17*D$48/$B$10)-(D$48*$B$9/$B$10/($B$11+$B$12-$A50)))*((1+$B$18)/(1+$B$11))^$B$16 -> 246.55073 | E50: =(E$48*$B$9/$B$10/($B$11+$B$12-$A50))+$B$15*(($B$17*E$48/$B$10)-(E$48*$B$9/$B$10/($B$11+$B$12-$A50)))*((1+$B$18)/(1+$B$11))^$B$16 -> 262.98745 | F50: =(F$48*$B$9/$B$10/($B$11+$B$12-$A50))+$B$15*(($B$17*F$48/$B$10)-(F$48*$B$9/$B$10/($B$11+$B$12-$A50)))*((1+$B$18)/(1+$B$11))^$B$16 -> 279.42416
A51: 0.06 | B51: =(B$48*$B$9/$B$10/($B$11+$B$12-$A51))+$B$15*(($B$17*B$48/$B$10)-(B$48*$B$9/$B$10/($B$11+$B$12-$A51)))*((1+$B$18)/(1+$B$11))^$B$16 -> 223.67892 | C51: =(C$48*$B$9/$B$10/($B$11+$B$12-$A51))+$B$15*(($B$17*C$48/$B$10)-(C$48*$B$9/$B$10/($B$11+$B$12-$A51)))*((1+$B$18)/(1+$B$11))^$B$16 -> 240.88499 | D51: =(D$48*$B$9/$B$10/($B$11+$B$12-$A51))+$B$15*(($B$17*D$48/$B$10)-(D$48*$B$9/$B$10/($B$11+$B$12-$A51)))*((1+$B$18)/(1+$B$11))^$B$16 -> 258.09106 | E51: =(E$48*$B$9/$B$10/($B$11+$B$12-$A51))+$B$15*(($B$17*E$48/$B$10)-(E$48*$B$9/$B$10/($B$11+$B$12-$A51)))*((1+$B$18)/(1+$B$11))^$B$16 -> 275.29713 | F51: =(F$48*$B$9/$B$10/($B$11+$B$12-$A51))+$B$15*(($B$17*F$48/$B$10)-(F$48*$B$9/$B$10/($B$11+$B$12-$A51)))*((1+$B$18)/(1+$B$11))^$B$16 -> 292.5032
A52: 0.07 | B52: =(B$48*$B$9/$B$10/($B$11+$B$12-$A52))+$B$15*(($B$17*B$48/$B$10)-(B$48*$B$9/$B$10/($B$11+$B$12-$A52)))*((1+$B$18)/(1+$B$11))^$B$16 -> 235.21925 | C52: =(C$48*$B$9/$B$10/($B$11+$B$12-$A52))+$B$15*(($B$17*C$48/$B$10)-(C$48*$B$9/$B$10/($B$11+$B$12-$A52)))*((1+$B$18)/(1+$B$11))^$B$16 -> 253.31303 | D52: =(D$48*$B$9/$B$10/($B$11+$B$12-$A52))+$B$15*(($B$17*D$48/$B$10)-(D$48*$B$9/$B$10/($B$11+$B$12-$A52)))*((1+$B$18)/(1+$B$11))^$B$16 -> 271.40682 | E52: =(E$48*$B$9/$B$10/($B$11+$B$12-$A52))+$B$15*(($B$17*E$48/$B$10)-(E$48*$B$9/$B$10/($B$11+$B$12-$A52)))*((1+$B$18)/(1+$B$11))^$B$16 -> 289.50061 | F52: =(F$48*$B$9/$B$10/($B$11+$B$12-$A52))+$B$15*(($B$17*F$48/$B$10)-(F$48*$B$9/$B$10/($B$11+$B$12-$A52)))*((1+$B$18)/(1+$B$11))^$B$16 -> 307.5944
A53: 0.08 | B53: =(B$48*$B$9/$B$10/($B$11+$B$12-$A53))+$B$15*(($B$17*B$48/$B$10)-(B$48*$B$9/$B$10/($B$11+$B$12-$A53)))*((1+$B$18)/(1+$B$11))^$B$16 -> 248.68296 | C53: =(C$48*$B$9/$B$10/($B$11+$B$12-$A53))+$B$15*(($B$17*C$48/$B$10)-(C$48*$B$9/$B$10/($B$11+$B$12-$A53)))*((1+$B$18)/(1+$B$11))^$B$16 -> 267.81242 | D53: =(D$48*$B$9/$B$10/($B$11+$B$12-$A53))+$B$15*(($B$17*D$48/$B$10)-(D$48*$B$9/$B$10/($B$11+$B$12-$A53)))*((1+$B$18)/(1+$B$11))^$B$16 -> 286.94188 | E53: =(E$48*$B$9/$B$10/($B$11+$B$12-$A53))+$B$15*(($B$17*E$48/$B$10)-(E$48*$B$9/$B$10/($B$11+$B$12-$A53)))*((1+$B$18)/(1+$B$11))^$B$16 -> 306.07134 | F53: =(F$48*$B$9/$B$10/($B$11+$B$12-$A53))+$B$15*(($B$17*F$48/$B$10)-(F$48*$B$9/$B$10/($B$11+$B$12-$A53)))*((1+$B$18)/(1+$B$11))^$B$16 -> 325.2008
A54: Центр таблицы (жёлтая ячейка) = базовый сценарий; должен совпадать со справедливой ценой.
A56: ТЕЗИС И УСЛОВИЯ ЕГО СЛОМА (сигнал при любой цене)
A57: Тезис: Крупнейший частный банк Северо-Запада, платит 50% прибыли дважды в год и исторически стоит дёшево (3–4 годовые прибыли). Прибыль снижается вместе со ставкой ЦБ — высокие ставки были банку выгодны. Позиции нет: держим для сравнения со Сбером и как кандидата при дивдоходности 15%+.
A58: • ROE ниже 12% или прогноз прибыли 2026 снова снижен (ниже 27 млрд ₽)
A59: • Доля прибыли на дивиденды ниже 50% или отказ от промежуточных выплат
A60: • Стоимость риска выше 2% — ухудшение качества кредитов у региональных заёмщиков
A61: • Достаточность капитала приближается к минимуму ЦБ
A63: ЧТО ОТСЛЕЖИВАЕТ БОТ В НОВОСТЯХ
A64: • Ежемесячная РСБУ и квартальная МСФО → вводная «Чистая прибыль 2026П»
A65: • Рекомендация по дивидендам за 2П 2026 (весна 2027)
A66: • Решения ЦБ по ставке: снижение ставки давит на процентный доход банка
A67: • Обратный выкуп акций и сделки контролирующего акционера
... A73: investmint — история дивидендов и число акций: https://investmint.ru/bspb/

Sheet Журнал
A1: Журнал изменений оценок
A2: Каждое изменение справедливой цены — с причиной и источником. Изменения больше 10% бот только предлагает, применяете вы.
A4: Дата | B4: Тикер | C4: Что изменилось | D4: Было | E4: Стало | F4: Справедливая после, ₽ | G4: Причина | H4: Источник | I4: Кто
A5: 24.10.2026 | B5: SBER | C5: Модель создана | F5: 392.42 | G5: Первичная оценка: Дивиденды (Гордон). | I5: Claude
A6: 24.10.2026 | B6: PLZL | C6: Модель создана | F6: 1228.95 | G6: Первичная оценка: EV/EBITDA от золота. | I6: Claude
A7: 24.10.2026 | B7: POSI | C7: Модель создана | F7: 1381.75 | G7: Первичная оценка: P/E на NIC 2027П. | I7: Claude
A8: 24.10.2026 | B8: PRMD | C8: Модель создана | F8: 608.19 | G8: Первичная оценка: EV/EBITDA 2027П. | I8: Claude
A9: 24.10.2026 | B9: YDEX | C9: Модель создана | F9: 4646.97 | G9: Первичная оценка: EV/EBITDA 2027П. | I9: Claude
A10: 24.10.2026 | B10: MTSS | C10: Модель создана | F10: 206.05 | G10: Первичная оценка: Выплаты акционерам (Гордон). | I10: Claude
A11: 24.10.2026 | B11: GAZP | C11: Модель создана | F11: 111.79 | G11: Первичная оценка: EV/EBITDA + опционы. | I11: Claude
A12: 24.10.2026 | B12: NLMK | C12: Модель создана | F12: 92.14 | G12: Первичная оценка: EV/EBITDA цикла. | I12: Claude
A13: 24.10.2026 | B13: GAZP | C13: Добавлены опционы «Северные потоки» и «Сила Байкала» | D13: 113,84 | E13: 111,79 | F13: 111.79 | G13: Первая версия опционов (цена для Китая $224 по майскому прогнозу МЭР). Пересмотрено 25.10. | I13: Claude
A14: 25.10.2026 | B14: GAZP | C14: Цена «Силы Байкала» = цена «Силы Сибири»; опционы пересобраны | D14: $224 | E14: $247,9 | F14: 114.95 | G14: По указанию пользователя. Цена «Силы Сибири» по материалам бюджета (ТАСС, 02.10.2026): $247,9 в 2026, $251,3 в 2027. Исправлены две ошибки модели: транспорт считался и в марже, и в капзатратах; долларовые потоки дисконтировались рублёвой ставкой при постоянном курсе. Добавлен налог на прибыль. «Сила Байкала» теперь +6,2 ₽ вместо −5,2 ₽, окупаемость при цене от ~$195. | H14: https://www1.ru/news/2026/10/02/rossiia-podnimet-ceny-na-gaz-dlia-kitaia.html | I14: Claude
A15: 25.10.2026 | B15: GAZP | C15: Нормализованная EBITDA | D15: 3 500 | E15: 3 350 | F15: 114.95 | G15: Независимая проверка: 3 500 выше LTM и прогноза компании (~3,1 трлн); 1П сезонно сильнее. Берём LTM. | H15: https://ru.themoscowtimes.com/2026/06/26/update-1-gazprom-zhdet-rosta-ebitda-v-26g-na-6-7-za-schet-postavok-gaza-v-rf-i-kitay-povysheniya-tsen-a199276 | I15: Claude
A16: 25.10.2026 | B16: GAZP | C16: Доли меньшинства и ассоциированные компании | D16: — | E16: −360 / +520 млрд | F16: 114.95 | G16: EBITDA консолидированная: вычтены чужие доли в «дочках», добавлены доли в «Славнефти», «Арктикгазе» и др. Оценки модели, уточнить по МСФО. | I16: Claude
A17: 25.10.2026 | B17: YDEX | C17: Мультипликатор и база | D17: 5,0x к EBITDA 2027 | E17: 4,5x к EBITDA 2027 после выплат акциями | F17: 3953.66 | G17: Проверка: 5x обосновывался сравнением с рынком на 2026, а применялся к 2027 (= 5,75x на 2026). Выплаты сотрудникам акциями (~40 млрд в год) вычтены из EBITDA. | I17: Claude
A18: 25.10.2026 | B18: YDEX | C18: Число акций | D18: 407,9 млн | E18: 383 млн | F18: 3953.66 | G18: Брались все выпущенные плюс допэмиссия; теперь — акции в обращении (382,1 млн за 1П 2026). Новые акции для сотрудников уже учтены через выплаты акциями. | H18: https://yastatic.net/s3/ir-docs/docs/2026/q2/9616f5e520b9c0d999be8066069d154d/2Q26_Press_Release_ENG_99be.pdf | I18: Claude
A19: 25.10.2026 | B19: PLZL | C19: Налог на сверхдоходы | D19: 25 млрд в год из EBITDA | E19: 25 млрд разово, как долг | F19: 1288.82 | G19: Налог берётся с доходов 2026 года (законопроект Минфина, 20% для золотодобытчиков); вычитать его каждый год было ошибкой. Постоянный рост НДПИ — отдельная вводная, сейчас 0. | H19: https://interfax.ru/business/1118171 | I19: Claude
A20: 25.10.2026 | B20: PRMD | C20: Чистый долг | D20: 33,3 (30.06.2026) | E20: 38,3 (конец 2026П) | F20: 584.66 | G20: Долг на дату оценки: FCF во 2П 2026 ожидается отрицательным (~−5 млрд). | I20: Claude
A21: 25.10.2026 | B21: SBER | C21: Добавлена проверка по длинным ОФЗ | D21: — | E21: 296 ₽ при ставке ОФЗ | F21: 392.42 | G21: Длинные ОФЗ дают ~16,6%. Если ставка = ОФЗ + 6% при прежнем росте, справедливая ≈ 296 ₽. Базовая модель не изменена: она опирается на прогноз ставки ЦБ. | H21: https://smart-lab.ru/bonds/ofz | I21: Claude
A22: 25.10.2026 | B22: MTSS | C22: Добавлена проверка по длинным ОФЗ | D22: — | E22: 170 ₽ при ставке ОФЗ | F22: 206.05 | G22: То же для МТС: при ставке длинных ОФЗ справедливая ≈ 170 ₽. | H22: https://smart-lab.ru/bonds/ofz | I22: Claude
A23: 25.10.2026 | B23: YDEX | C23: Ущерб от атак на ЦОДы | D23: 110 млрд | E23: 20 млрд | F23: 4188.64 | G23: По оценке пользователя. Компания ущерб не раскрыла; облако — 2–4% выручки. Уточнится в отчёте за 3К (29.10.2026). | I23: Пользователь
A24: 25.10.2026 | B24: — | C24: Добавлен ИИ-блок (лист «Параметры») | D24: — | E24: рынок 778 млрд ₽ в 2030 × 17x | G24: По указанию пользователя: ИИ-бизнес оценивается как у OpenAI (28x выручки), Anthropic (15x) и Alphabet (8x), рынок — только РФ, его делят российские игроки. Поправка на стоимость денег в РФ = 1,0; консервативный вариант (0,2) — в строках проверки. | H24: https://just-ai.com/blog/rossijskij-rynok-genai-vyrastet-do-778-mlrd-rub-k-kontsu-2030-goda | I24: Пользователь
A25: 25.10.2026 | B25: YDEX | C25: ИИ-блок: доля 40% рынка генИИ | D25: 4 188,64 | E25: 11 063,27 | F25: 11063.27 | G25: +6 875 ₽ на акцию. При скидке рынка РФ к США (0,2) прибавка 1 375 ₽, справедливая 5 564 ₽. | I25: Claude
A26: 25.10.2026 | B26: SBER | C26: ИИ-блок: доля 40% рынка генИИ | D26: 392,42 | E26: 508,99 | F26: 508.99 | G26: +117 ₽ на акцию (GigaChat). При скидке рынка РФ к США прибавка 23 ₽, справедливая 416 ₽. | I26: Claude
A27: 25.10.2026 | B27: MTSS | C27: ИИ-блок: доля 5% рынка генИИ | D27: 206,05 | E27: 370,74 | F27: 370.74 | G27: +165 ₽ на акцию (MWS AI). При скидке рынка РФ к США прибавка 33 ₽, справедливая 239 ₽. | I27: Claude
A28: 25.10.2026 | B28: — | C28: Добавлен сценарий мира (лист «Параметры») | D28: — | E28: 100%, через 5 лет | G28: По указанию пользователя: мир и снятие всех санкций через 5 лет. К этому году рынок возвращается к оценкам до 2022 года; прибавка приводится к сегодняшнему дню. Вероятность и срок — ячейки на «Параметрах». | I28: Пользователь
A29: 25.10.2026 | B29: SBER | C29: Сценарий мира: мультипликатор как до 2022 года (6.0x) | D29: 508,99 | E29: 586,31 | F29: 586.31 | G29: P/E Сбера в 2017–2021 был ~5–7x (2019 ~6,7x, 2021 ~5x). Применяется к прибыли 2026П. | I29: Claude
A30: 25.10.2026 | B30: PLZL | C30: Сценарий мира: мультипликатор как до 2022 года (7.0x) | D30: 1 288,82 | E30: 1 932,38 | F30: 1932.38 | G30: В 2019–2021 Полюс стоил ~7–9x EBITDA. Дисконт за паузу дивидендов сохраняем — мир его не отменяет. | I30: Claude
A31: 25.10.2026 | B31: POSI | C31: Сценарий мира: мультипликатор как до 2022 года (15.0x) | D31: 1 381,75 | E31: 1 964,06 | F31: 1964.06 | G31: До 2022 российские IT-компании стоили 20–30x прибыли, мировые лидеры кибербезопасности — 40x+. Берём 15x: после снятия санкций могут вернуться иностранные вендоры. | I31: Claude
A32: 25.10.2026 | B32: PRMD | C32: Сценарий мира: мультипликатор как до 2022 года (7.0x) | D32: 584,66 | E32: 842,54 | F32: 842.54 | G32: Мировые производители дженериков ~8–10x EBITDA; истории до 2022 нет (IPO 2024). Берём 7x. | I32: Claude
A33: 25.10.2026 | B33: YDEX | C33: Сценарий мира: мультипликатор как до 2022 года (10.0x) | D33: 11 063,27 | E33: 14 907,66 | F33: 14907.66 | G33: До 2022 Яндекс стоил 15–20x скорр. EBITDA (листинг в США); мировые интернет-компании ~12–15x. Берём 10x. ИИ-блок не переоцениваем — он уже по мультипликаторам США. | I33: Claude
A34: 25.10.2026 | B34: MTSS | C34: Сценарий мира: мультипликатор как до 2022 года (4.5x) | D34: 370,74 | E34: 490,01 | F34: 490.01 | G34: МТС в 2017–2021 стоил ~4,5–5x OIBDA (акция 250–350 ₽). Применяется к OIBDA 2026П с нынешним долгом. | I34: Claude
A35: 25.10.2026 | B35: GAZP | C35: Сценарий мира: мультипликатор как до 2022 года (3.2x) | D35: 114,95 | E35: 174,45 | F35: 174.45 | G35: Газпром в 2017–2021 стоил ~3–3,5x EBITDA (при дивидендах). | I35: Claude
A36: 25.10.2026 | B36: NLMK | C36: Сценарий мира: мультипликатор как до 2022 года (5.5x) | D36: 92,14 | E36: 121,81 | F36: 121.81 | G36: НЛМК в 2017–2021 стоил ~5–6x EBITDA при выплате 100% FCF. | I36: Claude
A37: 25.10.2026 | B37: — | C37: Вероятность мира и снятия санкций | D37: 100% | E37: 50% | G37: Решение пользователя. Прибавка от мира по всем бумагам уменьшилась вдвое. | I37: Пользователь
A38: 25.10.2026 | B38: BSPB | C38: Модель создана (для справки, позиции нет) | E38: 258,09 | F38: 258.09 | G38: По просьбе пользователя. Дивиденды (Гордон): прибыль 2026П 30 млрд (прогноз менеджмента), 50% на дивиденды, r 20%, g 6% → 241 ₽; сценарий мира +18 ₽. | H38: https://fomag.ru/news/otchet-bsp-stal-povodom-dlya-peresmotra-targeta-vniz/ | I38: Claude
